Workbook
Name a: #REF!
Name a: #REF!
Name Attendance: #REF!
Name Attendance: #REF!
Name BSDStatus: #REF!
Name Effort: #REF!
Name fhgcnhfv: '[1]Drop Down Fields'!$D$16:$D$19
Name FollowUPCategory: #REF!
Name FollowUpStatus: #REF!
Name FSDStatus: #REF!
Name GapPriority: #REF!
Name GapStatus: #REF!
Name Level: #REF!
Name MoSCoW: #REF!
Name NewGapStatus: #REF!
Name NewGapType: #REF!
Name Owner: #REF!
Name Priority: #REF!
Name ProcessStatus: #REF!
Name RAG: #REF!
Name ScopingGapStatus: #REF!
Name ScopingGapType: #REF!
Name Status: #REF!

Sheet Day1 - E2E Accounting Entries
A1: Stage | B1: Debit/Credit | C1: Accounting Entries | D1: Description | E1: Core/ Customized | F1: Account Reflection
A2: Status - Request | B2: DR | C2: No Accounting Entry | H2: Finance Amount | J2: 10000
B3: CR | H3: Admin Fee 1% | J3: =J2*1% -> 100
A4: Status - Approval | B4: DR | C4: GIT | D4: Goods in Transit | E4: =-J2 -> -10000 | F4: On Balance Sheet | H4: VAT | J4: =J3*15% -> 15
B5: CR | C5: Purchase Order | D5: Purchase Order | E5: =-E4 -> 10000 | F5: On Balance Sheet | H5: Net Finance Amount | J5: =J2-J3-J4 -> 9885
A6: Status - Purchase | B6: DR | C6: Purchase Order | D6: Purchase Order | E6: =-E5 -> -10000 | F6: On Balance Sheet
B7: CR | C7: GIT | D7: Goods in Transit | E7: =-E5 -> -10000 | F7: On Balance Sheet | H7: Profit Amount | I7: 0.12 | J7: =J2*I7 -> 1200
B8: DR | C8: Purchases | D8: Purchase | E8: =-J2 -> -10000 | F8: On Balance Sheet
B9: CR | C9: Buy Broker's account | D9: Internal Account | E9: =-E8 -> 10000 | F9: On Balance Sheet
A10: Finance / Sale | B10: DR | C10: CURACCOUNT | D10: AA Arrangeement - ACCOUNT | E10: =-J2 -> -10000 | F10: On Balance Sheet | H10: Back
B11: CR | C11: Purchases | D11: Purchase | E11: =-E8 -> 10000 | F11: On Balance Sheet
B12: DR | C12: RECDEFPFT | D12: Profit Receivable | E12: =-J7 -> -1200 | F12: On Balance Sheet
B13: CR | C13: ACCDEFPFT | D13: Unearned Accrued Profit | E13: =-E12 -> 1200 | F13: On Balance Sheet
A14: Admin Fee Due with VAT | B14: Dr | C14: DUEADMINFEE | D14: Admin Fee | E14: =-J3 -> -100
B15: Cr | C15: ACCADMINFEE | D15: Unamortise Admin Fee | E15: =-E14 -> 100
B16: Dr | C16: DUEVAT | D16: VAT Receivable | E16: =-J4 -> -15
B17: Cr | C17: VAT Payable | E17: =-E16 -> 15
A18: Payment to Customer | B18: DR | C18: Sell Broker's Account | D18: Internal Account | E18: -10000 | F18: On Balance Sheet
B19: CR | C19: Customer's Account | D19: Disbursment/Repayment Account | E19: 10000 | F19: On Balance Sheet | G19: 1
A20: Broker Settlement (incase of different) | B20: DR | C20: Buy Broker's Account | D20: Internal Account | E20: =-E9 -> -10000 | F20: On Balance Sheet
B21: CR | C21: Sell Broker's Account | D21: Internal Account | E21: =-E18 -> 10000 | F21: On Balance Sheet
A22: Recovery of Admin Fee & VAT | B22: Dr | C22: Customer's Account | D22: Disbursment/Repayment Account | E22: =E14 -> -100
B23: Cr | C23: DUEADMINFEE | D23: Admin Fee | E23: =-E14 -> 100
B24: Dr | C24: Customer's Account | D24: Disbursment/Repayment Account | E24: =E16 -> -15
B25: Cr | C25: DUEVAT | D25: VAT | E25: =-E16 -> 15
A26: Actual Repayment to Customer (Net of Financing) | B26: Dr | C26: Customer's Account | D26: Disbursment/Repayment Account | E26: =E19+E22+E24 -> 9885
B27: Cr | C27: BF Account | D27: Internal Account | E27: =-E26 -> -9885
B28: Dr | C28: BF Account | D28: Internal Account | E28: =E26 -> 9885
B29: Cr | C29: Customer Bank Account | D29: XYZ bank account- customer current account | E29: =E27 -> -9885
A30: Upfront Admin Fee By Customer | B30: Dr | C30: BF Account | D30: Internal Account | E30: =E22+E24 -> -115
B31: Cr | C31: Customer's Account | D31: Disbursment/Repayment Account | E31: =-E30 -> 115
A32: Actual Repayment to Customer (Full Financing) | B32: Dr | C32: Customer's Account | D32: Disbursment/Repayment Account | E32: =E19+E22+E24+E31 -> 10000
B33: Cr | C33: BF Account | D33: Internal Account | E33: =-E32 -> -10000
B34: Dr | C34: BF Account | D34: Internal Account | E34: =E32 -> 10000
B35: Cr | C35: Customer Bank Account | D35: XYZ bank account- customer current account | E35: =E33 -> -10000
A37: Daily Amortization Profit based on reducing balance | B37: DR | C37: ACCDEFPFT | D37: Unearned Accrued Profit | E37: =-E13/365 -> -3.2876712 | F37: On Balance Sheet
B38: CR | C38: PL/ Income | D38: PL Category | E38: =-E37 -> 3.2876712 | F38: On Balance Sheet
A39: Daily Amortization of Admin Fee based on reducing balance | B39: DR | C39: ACCADMINFEE | D39: Unamortised Admin Fee | E39: =E14/365 -> -0.2739726
B40: CR | C40: PL/ Income | D40: PL Category | E40: =-E39 -> 0.2739726
A43: On Installment Date | B43: DR | C43: DUEACCOUNT | D43: Principal Portion due of Installment | E43: By Core | F43: On Balance Sheet
B44: CR | C44: CURACCOUNT | D44: AA Arrangement - ACCOUNT | E44: By Core | F44: On Balance Sheet
B45: DR | C45: DUEDEFPFT | D45: Profit Portion due of Installment | E45: By Core | F45: On Balance Sheet
B46: CR | C46: RECDEFPFT | D46: Profit Receivable | E46: By Core | F46: On Balance Sheet
A47: Repayment of Finance | B47: DR | C47: Customer's Account | D47: Disbursment/Repayment Account | E47: By Core | F47: On Balance Sheet
B48: CR | C48: DUEACCOUNT | D48: Principal portion of repayment | E48: By Core | F48: On Balance Sheet
B49: CR | C49: DUEDEFPFT | D49: Profit portion of repayment | E49: By Core | F49: On Balance Sheet
A50: Payoff | B50: DR | C50: Customer's Account | D50: Outstanding Principal Amount | E50: By Core | F50: On Balance Sheet
B51: CR | C51: CURACCOUNT | D51: Outstanding Principal Amount | E51: By Core | F51: On Balance Sheet
B52: DR | C52: Customer's Account | D52: Outstanding Profit Amount | E52: By Core | F52: On Balance Sheet
B53: CR | C53: RECDEFPFT | D53: Outstanding Profit Amount | E53: By Core | F53: On Balance Sheet
B54: DR | C54: ACCDEFPFT | D54: Unearned Accrued Profit Amount | E54: By Core | F54: On Balance Sheet
B55: CR | C55: PL/ Income | D55: Unearned Accrued Profit Amount | E55: By Core | F55: On Balance Sheet
B56: DR | C56: PL/ Income | D56: With Bonus amount if applied | E56: By Core | F56: On Balance Sheet
B57: CR | C57: Customer's Account | D57: With Bonus amount if applied | E57: By Core | F57: On Balance Sheet
A59: Comparing contract GL
A60: TA GL | G60: T24 GL
A61: TRANS DATE | B61: Event | C61: Account Code | D61: Debit | E61: Credit | L61: TA Internal use
A62: 45474 | B62: Purchase of New Asset_2 | C62: 1106310001 - Inventory | D62: 24900 | G62: Status - Approval | H62: DR | I62: GIT | J62: Goods in Transit | K62: -10000
A63: 45474 | B63: Purchase of New Asset_2 | C63: 2101000001 - A/c Payable | E63: 24900 | H63: CR | I63: Purchase Order | J63: Purchase Order | K63: 10000
A64: 45474 | B64: commodity | C64: 2101000001 - A/c Payable | E64: 24900 | G64: Status - Purchase | H64: DR | I64: Purchase Order | J64: Purchase Order | K64: 10000
A65: 45474 | B65: commodity | C65: 1104000001 - Account Recievable | D65: 24900 | H65: CR | I65: GIT | J65: Goods in Transit | K65: -10000
A66: 45474 | B66: commodity | C66: 1104000001 - Account Recievable | E66: 24900 | H66: DR | I66: Purchases | J66: Purchase | K66: -10000
A67: 45474 | B67: commodity | C67: 1104000004 - Ashton vendor | D67: 24900 | H67: CR | I67: Buy Broker's account | J67: Internal Account | K67: 10000
A68: 45474 | B68: Disbursement | C68: 1106310001 - Inventory | E68: 24900 | G68: Finance / Sale | H68: DR | I68: CURACCOUNT | J68: AA Arrangeement - ACCOUNT | K68: -10000
A69: 45474 | B69: Disbursement | C69: 2104310001 - Deferred Rev - Interest | E69: 26144.99 | H69: CR | I69: Purchases | J69: Purchase | K69: 10000
A70: 45474 | B70: Disbursement | C70: 1104000001 - Account Recievable | D70: 26144.99 | H70: DR | I70: RECDEFPFT | J70: Profit Receivable | K70: -1200
A71: 45474 | B71: Disbursement | C71: 1104000001 - Account Recievable | D71: 24900 | H71: CR | I71: ACCDEFPFT | J71: Unearned Accrued Profit | K71: 1200
A72: 45474 | B72: Admin fees | C72: 2112000001 - Output VAT 15% for domestic | E72: 37.35 | G72: Admin Fee Due with VAT | H72: Dr | I72: DUEADMINFEE | J72: Admin Fee | K72: -100
A73: 45474 | B73: Admin fees | C73: 2104310003 - Deferred Revenue-Admin Fees | E73: 249 | H73: Cr | I73: ACCADMINFEE | J73: Unamortise Admin Fee | K73: 100
A74: 45474 | B74: Admin fees | C74: 1104000001 - Account Recievable | D74: 249 | H74: Dr | I74: DUEVAT | J74: VAT Receivable | K74: -15
A75: 45474 | B75: Admin fees | C75: 1104000001 - Account Recievable | D75: 37.35 | H75: Cr | I75: VAT Payable | K75: 15
A76: 14/01/2024 | B76: NORMAL - Rental Payment | C76: 1104000001 - Account Recievable | E76: 24900 | G76: Payment to Customer | H76: DR | I76: Sell Broker's Account | J76: Internal Account | K76: -10000
A77: 14/01/2024 | B77: NORMAL - Rental Payment | C77: Sell Broker's Account | D77: 24900 | H77: CR | I77: Customer's Account | J77: Disbursment/Repayment Account | K77: 10000
A78: 14/01/2024 | C78: Buy Broker's Account | E78: 24900 | G78: Broker Settlement (incase of different) | H78: DR | I78: Buy Broker's Account | J78: Internal Account | K78: -10000
A79: 14/01/2024 | C79: Sell Broker's Account | D79: 24900 | H79: CR | I79: Sell Broker's Account | J79: Internal Account | K79: 10000
A81: 17/01/2024 | B81: REFUND - Refund | C81: 1103310542 - Gulf International Bank Tamweel 20000001232-O/C | E81: 24613.65 | G81: Actual Repayment to Customer (Net of Financing) | H81: Dr | I81: Customer's Account | J81: Disbursment/Repayment Account | K81: -100
A82: 17/01/2024 | B82: REFUND - Refund | C82: 1104000001 - Account Recievable | D82: 24613.65 | H82: Cr | I82: DUEADMINFEE | J82: Admin Fee | K82: 100
H83: Dr | I83: Customer's Account | J83: Disbursment/Repayment Account | K83: -15
H84: Cr | I84: DUEVAT | J84: VAT | K84: 15
H85: Dr | I85: Customer's Account | J85: Disbursment/Repayment Account | K85: 9885
H86: Cr | I86: BF Account | J86: Internal Account | K86: -9885
H87: Dr | I87: BF Account | J87: Internal Account | K87: 9885
H88: Cr | I88: Customer Bank Account | J88: XYZ bank account- customer current account | K88: -9885

Sheet Day2 - Simulated Schedule
A1: System Date | B1: 45320
A2: Offer Issue Date | B2: =+B1 -> 45320 | F2: =+XIRR(C8:C68,A8:A68) -> 0.13247654
A3: Grace Period | B3: 15 Days
A4: Offer Expiry Date | B4: =+B2+14 -> 45334 | E4: 100000 | F4: =+F5/E4 -> 0.06557076
A5: Payment Schedule | F5: =+F6/5 -> 6557.076 | M5: Generated Date: 12-Aug-2024 18:52:41
F6: =SUM(F7:F68) -> 32785.38
A7: Date | B7: Defer Date | C7: Total Due | D7: Total Cap | E7: Principal | F7: Principal Profit | G7: REC Profit | H7: Charge | I7: Tax | J7: Total Pymt | K7: Outstanding | L7: O/S Principal + Profit
A8: 45334 | C8: -98850 | D8: 0 | E8: -98850 | H8: 1000 | I8: 150 | J8: 100000 | K8: -100000
A9: 45350 | C9: 2213.09 | D9: 0 | E9: 1719.94 | F9: 493.15 | H9: 0 | K9: -98280.06
A10: 45379 | C10: 2213.09 | D10: 0 | E10: 1276.06 | F10: 937.03 | H10: 0 | K10: -97004
A11: 45410 | C11: 2213.09 | D11: 0 | E11: 1224.45 | F11: 988.64 | H11: 0 | K11: -95779.55
A12: 45440 | C12: 2213.09 | D12: 0 | E12: 1268.42 | F12: 944.67 | H12: 0 | K12: -94511.13
A13: 45471 | C13: 2213.09 | D13: 0 | E13: 1249.85 | F13: 963.24 | H13: 0 | K13: -93261.28
A14: 45501 | C14: 2213.09 | D14: 0 | E14: 1293.25 | F14: 919.84 | H14: 0 | K14: -91968.03
A15: 45532 | C15: 2213.09 | D15: 0 | E15: 1275.77 | F15: 937.32 | H15: 0 | K15: -90692.26
A16: 45563 | C16: 2213.09 | D16: 0 | E16: 1288.77 | F16: 924.32 | H16: 0 | K16: -89403.49
A17: 45593 | C17: 2213.09 | D17: 0 | E17: 1331.3 | F17: 881.79 | H17: 0 | K17: -88072.19
A18: 45624 | C18: 2213.09 | D18: 0 | E18: 1315.48 | F18: 897.61 | H18: 0 | K18: -86756.71
A19: 45654 | C19: 2213.09 | D19: 0 | E19: 1357.41 | F19: 855.68 | H19: 0 | K19: -85399.3
A20: 45685 | C20: 2213.09 | D20: 0 | E20: 1342.72 | F20: 870.37 | H20: 0 | K20: -84056.58
... A68: 47146 | C68: 2213.07 | D68: 0 | E68: 2190.72 | F68: 22.35 | H68: 0 | K68: 0

Sheet Day4-Cooling Period Cancelation
A1: Cancellation – Cooling Period
A2: Stage | B2: Debit/Credit | C2: Accounting Entries | D2: Description | E2: Core/ Customized | F2: Account Reflection
A3: Reversal of Admin Fee | B3: DR | C3: PL/ Income | D3: Income GL | E3: By Core | F3: On Balance Sheet
B4: CR | C4: Customer A/c. | D4: Disbursment/Repayment Account | E4: By Core | F4: On Balance Sheet
B5: DR | C5: VAT Payable | D5: VAT Payable | E5: By Core | F5: On Balance Sheet
B6: CR | C6: Customer A/c. | D6: Disbursment/Repayment Account | E6: By Core | F6: On Balance Sheet
A7: Reversal of Profit | B7: DR | C7: PL/ Income | D7: PL Category | E7: By Core | F7: On Balance Sheet
B8: CR | C8: ACCDEFPFT | D8: Unearned Profit | E8: By Core | F8: On Balance Sheet
B9: DR | C9: ACCDEFPFT | D9: Unearned Profit | E9: By Core | F9: On Balance Sheet
B10: CR | C10: RECDEFPFT | D10: Profit Receivable | E10: By Core | F10: On Balance Sheet
A11: Principal Settlement | B11: DR | C11: Customer A/c. | D11: Disbursment/Repayment Account | E11: By Core | F11: On Balance Sheet
B12: CR | C12: CURACCOUNT | D12: Outstanding Principal Amount | E12: By Core | F12: On Balance Sheet
A14: SADAD ENTRY
A15: Stage | B15: Debit/Credit | C15: Accounting Entries | D15: Description | E15: Core/ Customized
A16: Recovery Entry 24-04-2024 | B16: DR | D16: BF Bank Account | E16: -14988.5
B17: CR | D17: Internal Account | E17: 14988.5
A19: SADAD Fee Entry - 24-04-2024 | B19: DR | D19: PL - Expense | E19: -10
B20: CR | D20: Internal Account | E20: 10
A22: VAT Entry - 24-04-2024 | B22: DR | D22: VAT Asset | E22: -1.5
B23: CR | D23: Internal Account | E23: 1.5
A26: Transfer of Funds to Settlement Acocunt 24-04-2024 | B26: DR | D26: Internal Account | E26: -15000
B27: CR | D27: Customer Account - Settlement account | E27: 15000
A30: Instalment Settlement Entry - 28-04-2024 | B30: DR | D30: Customer Account - settlement account | E30: -15000
B31: CR | D31: Receivable (total bill amount) - loan account | E31: 15000

Sheet Day4 - Deferment
A1: Deferment - Original
A4: Payment Schedule | M4: Generated Date: 16-Aug-2024 16:24:21
A6: Date | B6: Defer Date | C6: Total Due | D6: Total Cap | E6: Principal | F6: Principal Profit | G6: REC Profit | H6: Charge | I6: Tax | J6: Total Pymt | K6: Outstanding | L6: O/S Principal + Profit
A7: 45320 | C7: 1150 | D7: 0 | E7: 100000 | H7: 1000 | I7: 150 | J7: 100000 | K7: '-100,000.00' | L7: '-132,785.38'
A8: 45350 | C8: 2213.09 | D8: 0 | E8: 1244.5 | G8: 968.59 | H8: 0 | K8: '-98,755.50' | L8: '-130,572.29'
A9: 45379 | C9: 2213.09 | D9: 0 | E9: 1288.44 | G9: 924.65 | H9: 0 | K9: '-97,467.06' | L9: '-128,359.20'
A10: 45410 | C10: 2213.09 | D10: 0 | E10: 1237.56 | G10: 975.53 | H10: 0 | K10: '-96,229.50' | L10: '-126,146.11'
A11: 45440 | C11: 2213.09 | D11: 0 | E11: 1281.02 | G11: 932.07 | H11: 0 | K11: '-94,948.48' | L11: '-123,933.02'
A12: 45471 | C12: 2213.09 | D12: 0 | E12: 1262.77 | G12: 950.32 | H12: 0 | K12: '-93,685.71' | L12: '-121,719.93'
A13: 45501 | C13: 2213.09 | D13: 0 | E13: 1305.66 | G13: 907.43 | H13: 0 | K13: '-92,380.05' | L13: '-119,506.84'
A14: 45532 | C14: 2213.09 | D14: 0 | E14: 1288.48 | G14: 924.61 | H14: 0 | K14: '-91,091.57' | L14: '-117,293.75'
A15: 45563 | C15: 2213.09 | D15: 0 | E15: 1301.37 | G15: 911.72 | H15: 0 | K15: '-89,790.20' | L15: '-115,080.66'
A16: 45593 | C16: 2213.09 | D16: 0 | E16: 1343.39 | G16: 869.7 | H16: 0 | K16: '-88,446.81' | L16: '-112,867.57'
A17: 45624 | C17: 2213.09 | D17: 0 | E17: 1327.84 | G17: 885.25 | H17: 0 | K17: '-87,118.97' | L17: '-110,654.48'
A18: 45654 | C18: 2213.09 | D18: 0 | E18: 1369.26 | G18: 843.83 | H18: 0 | K18: '-85,749.71' | L18: '-108,441.39'
A19: 45685 | C19: 2213.09 | D19: 0 | E19: 1354.84 | G19: 858.25 | H19: 0 | K19: '-84,394.87' | L19: '-106,228.30'
... A66: 47115 | C66: 2213.09 | D66: 0 | E66: 2170.84 | G66: 42.25 | H66: 0 | K66: '-2,191.16' | L66: '-2,213.07'
A67: 47146 | C67: 2213.07 | D67: 0 | E67: 2191.16 | G67: 21.91 | H67: 0 | K67: 0 | L67: 0
A70: Deferment - Term Increased
A72: Payment Schedule | K72: Generated Date: 16-Aug-2024 16:18:24
A74: Date | B74: Defer Date | C74: Total Due | D74: Total Cap | E74: Principal | F74: Profit | G74: Charge | H74: Tax | I74: Total Pymt | J74: Outstanding
A75: 45320 | C75: 101150 | D75: 0 | E75: 100000 | G75: 1000 | H75: 150 | I75: 100000 | J75: '-100,000.00'
A76: 45350 | C76: 0 | D76: 0 | G76: 0 | J76: '-100,000.00'
A77: 45379 | C77: 0 | D77: 0 | G77: 0 | J77: '-100,000.00'
A78: 45410 | C78: 2213.09 | D78: 0 | E78: 0 | G78: 0 | J78: '-100,000.00'
A79: 45440 | C79: 2213.09 | D79: 0 | E79: 692.33 | G79: 0 | J79: '-99,307.67'
A80: 45471 | C80: 2213.09 | D80: 0 | E80: 1290.06 | G80: 0 | J80: '-98,017.61'
A81: 45501 | C81: 2213.09 | D81: 0 | E81: 1331.44 | G81: 0 | J81: '-96,686.17'
A82: 45532 | C82: 2213.09 | D82: 0 | E82: 1314.43 | G82: 0 | J82: '-95,371.74'
A83: 45563 | C83: 2213.09 | D83: 0 | E83: 1326.64 | G83: 0 | J83: '-94,045.10'
A84: 45593 | C84: 2213.09 | D84: 0 | E84: 1367.17 | G84: 0 | J84: '-92,677.93'
A85: 45624 | C85: 2213.09 | D85: 0 | E85: 1351.68 | G85: 0 | J85: '-91,326.25'
A86: 45654 | C86: 2213.09 | D86: 0 | E86: 1391.63 | G86: 0 | J86: '-89,934.62'
A87: 45685 | C87: 2213.09 | D87: 0 | E87: 1377.18 | G87: 0 | J87: '-88,557.44'
A88: 45716 | C88: 2213.09 | D88: 0 | E88: 1389.98 | G88: 0 | J88: '-87,167.46'
A89: 45744 | C89: 2213.09 | D89: 0 | E89: 1481.3 | G89: 0 | J89: '-85,686.16'
... A136: 47177 | C136: 2213.09 | D136: 0 | E136: 2172.5 | G136: 0 | J136: '-2,194.59'
A137: 47205 | C137: 2213.07 | D137: 0 | E137: 2194.59 | G137: 0 | J137: 0
A140: Deferment - Add Residual
A142: Payment Schedule | K142: Generated Date: 16-Aug-2024 16:21:17
A144: Date | B144: Defer Date | C144: Total Due | D144: Total Cap | E144: Principal | F144: Profit | G144: Charge | H144: Tax | I144: Total Pymt | J144: Outstanding
A145: 45320 | C145: 101150 | D145: 0 | E145: 100000 | G145: 1000 | H145: 150 | I145: 100000 | J145: '-100,000.00'
A146: 45350 | C146: 0 | D146: 0 | G146: 0 | J146: '-100,000.00'
A147: 45379 | C147: 0 | D147: 0 | G147: 0 | J147: '-100,000.00'
A148: 45410 | C148: 2213.09 | D148: 0 | E148: 0 | G148: 0 | J148: '-100,000.00'
A149: 45440 | C149: 2213.09 | D149: 0 | E149: 690.26 | G149: 0 | J149: '-99,309.74'
A150: 45471 | C150: 2213.09 | D150: 0 | E150: 1288.99 | G150: 0 | J150: '-98,020.75'
A151: 45501 | C151: 2213.09 | D151: 0 | E151: 1330.41 | G151: 0 | J151: '-96,690.34'
A152: 45532 | C152: 2213.09 | D152: 0 | E152: 1313.37 | G152: 0 | J152: '-95,376.97'
A153: 45563 | C153: 2213.09 | D153: 0 | E153: 1325.59 | G153: 0 | J153: '-94,051.38'
A154: 45593 | C154: 2213.09 | D154: 0 | E154: 1366.16 | G154: 0 | J154: '-92,685.22'
A155: 45624 | C155: 2213.09 | D155: 0 | E155: 1350.64 | G155: 0 | J155: '-91,334.58'
A156: 45654 | C156: 2213.09 | D156: 0 | E156: 1390.62 | G156: 0 | J156: '-89,943.96'
A157: 45685 | C157: 2213.09 | D157: 0 | E157: 1376.14 | G157: 0 | J157: '-88,567.82'
A158: 45716 | C158: 2213.09 | D158: 0 | E158: 1388.95 | G158: 0 | J158: '-87,178.87'
A159: 45744 | C159: 2213.09 | D159: 0 | E159: 1480.38 | G159: 0 | J159: '-85,698.49'
... A204: 47115 | C204: 1095.96 | D204: 0 | E204: 1017.59 | G204: 0 | J204: '-7,685.33'
A205: 47146 | C205: 7756.38 | D205: 0 | E205: 7685.33 | G205: 0 | J205: 0

Sheet Day4 - Early Settlement
A1: Date | B1: Defer Date | C1: Total Due | D1: Total Cap | E1: Principal | F1: Principal Profit | G1: REC Profit | H1: Charge | I1: Tax | J1: Total Pymt | K1: Outstanding | L1: O/S Principal + Profit
A2: 45351 | C2: 1150 | D2: 0 | E2: 100000 | H2: 1000 | I2: 150 | J2: 100000 | K2: '-100,000.00' | L2: '-105,459.11'
A3: 45352 | B3: customer request
A4: 45378 | B4: payoff
A5: 45379 | C5: 11460.72 | D5: 0 | E5: 8021.14 | G5: 767.12 | H5: 2672.46 | K5: -39249.3 | L5: '-43,941.29'
A6: 45381 | B6: payoff request
A7: 45410 | C7: 3994.66 | D7: 0 | E7: 3227.05 | G7: 767.61 | H7: 0 | K7: -36022.25 | L7: '-39,946.63'
A8: 45440 | C8: 3994.66 | D8: 0 | E8: 3312.89 | G8: 681.77 | H8: 0 | K8: -32709.36 | L8: '-35,951.97'
A9: 45471 | C9: 3994.66 | D9: 0 | E9: 3354.95 | G9: 639.71 | H9: 0 | K9: -29354.41 | L9: '-31,957.31'
A10: 45501 | C10: 3994.66 | D10: 0 | E10: 3439.09 | G10: 555.57 | H10: 0 | K10: -25915.32 | L10: '-27,962.65'
A11: 45532 | C11: 3994.66 | D11: 0 | E11: 3487.83 | G11: 506.83 | H11: 0 | K11: -22427.49 | L11: '-23,967.99'
A12: 45563 | C12: 3994.66 | D12: 0 | E12: 3556.04 | G12: 438.62 | H12: 0 | K12: -18871.45 | L12: '-19,973.33'
A13: 45593 | C13: 3994.66 | D13: 0 | E13: 3637.49 | G13: 357.17 | H13: 0 | K13: -15233.96 | L13: '-15,978.67'
A14: 45624 | C14: 3994.66 | D14: 0 | E14: 3696.73 | G14: 297.93 | H14: 0 | K14: -11537.23 | L14: '-11,984.01'
A15: 45654 | C15: 3994.66 | D15: 0 | E15: 3776.3 | G15: 218.36 | H15: 0 | K15: -7760.93 | L15: '-7,989.35'
A16: 45685 | C16: 3994.66 | D16: 0 | E16: 3842.88 | G16: 151.78 | H16: 0 | K16: -3918.05 | L16: '-3,994.69'
A17: 45716 | C17: 3994.69 | D17: 0 | E17: 3918.05 | G17: 76.64 | H17: 0 | K17: 0 | L17: 0
B19: Payoff invoice generation date | C19: 45381 | D19: 45379
B20: Principal O/s | C20: =-K5 -> 39249.3 | D20: =+C20 -> 39249.3
B21: Profit Current month installment | C21: =+G7 -> 767.61
B22: Payoff Charge | C22: =SUM(G8:G10) -> 1877.05 | D22: =SUM(G7:G9) -> 2089.09
B23: Payoff Invoice Amount- Total | C23: =SUM(C20:C22) -> 41893.96 | D23: =SUM(D20:D22) -> 41338.39
A41: Payment Schedule | M41: Generated Date: 12-Jun-2024 18:26:24
A43: Date | B43: Defer Date | C43: Total Due | D43: Total Cap | E43: Principal | F43: Principal Profit | G43: REC Profit | H43: Charge | I43: Tax | J43: Total Pymt | K43: Outstanding | L43: O/S Principal + Profit
A44: 45351 | C44: 1150 | D44: 0 | E44: 100000 | H44: 1000 | I44: 150 | J44: 100000 | K44: '-100,000.00' | L44: '-105,459.11'
A45: 45368 | B45: the customer will send request for early sttlement and on 19-Mar-24 it will expire
A46: 45371 | B46: early settlement bill expiry date
A47: =A48-7 -> 45372 | B47: sadad bill issuance
A48: 45379 | C48: 11460.72 | D48: 0 | E48: 8021.14 | G48: 767.12 | H48: 2672.46 | K48: '-39,249.30' | L48: '-43,941.29'
A49: 45410 | C49: 3994.66 | D49: 0 | E49: 3227.05 | G49: 767.61 | H49: 0 | K49: '-36,022.25' | L49: '-39,946.63'
A50: 45440 | C50: 3994.66 | D50: 0 | E50: 3312.89 | G50: 681.77 | H50: 0 | K50: '-32,709.36' | L50: '-35,951.97'
A51: 45471 | C51: 3994.66 | D51: 0 | E51: 3354.95 | G51: 639.71 | H51: 0 | K51: '-29,354.41' | L51: '-31,957.31'
A52: 45501 | C52: 3994.66 | D52: 0 | E52: 3439.09 | G52: 555.57 | H52: 0 | K52: '-25,915.32' | L52: '-27,962.65'
A53: 45532 | C53: 3994.66 | D53: 0 | E53: 3487.83 | G53: 506.83 | H53: 0 | K53: '-22,427.49' | L53: '-23,967.99'
A54: 45563 | C54: 3994.66 | D54: 0 | E54: 3556.04 | G54: 438.62 | H54: 0 | K54: '-18,871.45' | L54: '-19,973.33'
A55: 45593 | C55: 3994.66 | D55: 0 | E55: 3637.49 | G55: 357.17 | H55: 0 | K55: '-15,233.96' | L55: '-15,978.67'
A56: 45624 | C56: 3994.66 | D56: 0 | E56: 3696.73 | G56: 297.93 | H56: 0 | K56: '-11,537.23' | L56: '-11,984.01'
A57: 45654 | C57: 3994.66 | D57: 0 | E57: 3776.3 | G57: 218.36 | H57: 0 | K57: '-7,760.93' | L57: '-7,989.35'
A58: 45685 | C58: 3994.66 | D58: 0 | E58: 3842.88 | G58: 151.78 | H58: 0 | K58: '-3,918.05' | L58: '-3,994.69'
A59: 45716 | C59: 3994.69 | D59: 0 | E59: 3918.05 | G59: 76.64 | H59: 0 | K59: 0 | L59: 0
F62: 4MONTHS | G62: =SUM(G49:G52) -> 2644.66 | H62: PAYOFF FEE
B63: 28MAY,JUNE & JULY SHOULD BE TREATED AS FEE
B64: 28APR SHOULD BE TREATED AS PROFIT ACCRUAL
B65: From 21 till 28 of month customer cannot request for early payoff
A66: expiry | B66: prior 1 day of bill issuance date

Sheet Day4 - IRR & Flat Rate
A1: Simulation Details
A2: System Date | B2: 45322
A3: Amount | B3: 200000 | C3: Profit Start Date | D3: 45337
A4: Rate | B4: 0.12 | C4: Total Profit | D4: =SUM(F13:F24) -> 11995.63 | E4: =+D7*1*B3 -> 12545.573
A5: Term | B5: 1Y | C5: Instalment Amount | D5: =+C13 -> 17666.3
A6: 1st Instalment Date | B6: 45350 | C6: APR | D6: 0.153299 | J6: =+XIRR(J12:J24,A12:A24) -> 0.15329998
A7: Last Intalment Date | B7: 45685 | C7: Flat Rate | D7: =(D4/(A24-A12)*365)/B3 -> 0.062727865
A8: Simulation Reference | B8: AASIM240312PJW03LG | C8: # on Accrual Days | D8: =+B7-D3 -> 348 | E8: Arrangement | F8: AA24031JMN87
A10: Payment Schedule
A11: Date | B11: Defer Date | C11: Total Due | D11: Total Cap | E11: Principal | F11: Principal Profit | G11: REC Profit = IRR | H11: Charge | I11: Tax | J11: Total Pymt | K11: Outstanding
A12: 45336 | C12: 2300 | D12: 0 | E12: 200000 | H12: 2000 | I12: 300 | J12: =C12-E12 -> -197700 | K12: -200000
A13: 45350 | B13: =A13-D3 -> 13 | C13: 17666.3 | D13: 0 | E13: 16811.51 | F13: 854.79 | G13: =(F13/B13*365)/-K12 -> 0.11999937 | H13: 0 | J13: =+C13 -> 17666.3 | K13: -183188.49
A14: 45379 | B14: =A14-A13 -> 29 | C14: 17666.3 | D14: 0 | E14: 15919.74 | F14: 1746.56 | G14: =(F14/B14*365)/-K13 -> 0.11999971 | H14: 0 | J14: =+C14 -> 17666.3 | K14: -167268.75
A15: 45410 | B15: =A15-A14 -> 31 | C15: 17666.3 | D15: 0 | E15: 15961.53 | F15: 1704.77 | G15: =(F15/B15*365)/-K14 -> 0.12000025 | H15: 0 | J15: =+C15 -> 17666.3 | K15: -151307.22
A16: 45440 | B16: =A16-A15 -> 30 | C16: 17666.3 | D16: 0 | E16: 16173.96 | F16: 1492.34 | G16: =(F16/B16*365)/-K15 -> 0.11999958 | H16: 0 | J16: =+C16 -> 17666.3 | K16: -135133.26
A17: 45471 | B17: =A17-A16 -> 31 | C17: 17666.3 | D17: 0 | E17: 16289.05 | F17: 1377.25 | G17: =(F17/B17*365)/-K16 -> 0.12000012 | H17: 0 | J17: =+C17 -> 17666.3 | K17: -118844.21
A18: 45501 | B18: =A18-A17 -> 30 | C18: 17666.3 | D18: 0 | E18: 16494.14 | F18: 1172.16 | G18: =(F18/B18*365)/-K17 -> 0.11999979 | H18: 0 | J18: =+C18 -> 17666.3 | K18: -102350.07
A19: 45532 | B19: =A19-A18 -> 31 | C19: 17666.3 | D19: 0 | E19: 16623.17 | F19: 1043.13 | G19: =(F19/B19*365)/-K18 -> 0.12000006 | H19: 0 | J19: =+C19 -> 17666.3 | K19: -85726.9
A20: 45563 | B20: =A20-A19 -> 31 | C20: 17666.3 | D20: 0 | E20: 16792.59 | F20: 873.71 | G20: =(F20/B20*365)/-K19 -> 0.12000003 | H20: 0 | J20: =+C20 -> 17666.3 | K20: -68934.31
A21: 45593 | B21: =A21-A20 -> 30 | C21: 17666.3 | D21: 0 | E21: 16986.4 | F21: 679.9 | G21: =(F21/B21*365)/-K20 -> 0.11999999 | H21: 0 | J21: =+C21 -> 17666.3 | K21: -51947.91
A22: 45624 | B22: =A22-A21 -> 31 | C22: 17666.3 | D22: 0 | E22: 17136.86 | F22: 529.44 | G22: =(F22/B22*365)/-K21 -> 0.11999961 | H22: 0 | J22: =+C22 -> 17666.3 | K22: -34811.05
A23: 45654 | B23: =A23-A22 -> 30 | C23: 17666.3 | D23: 0 | E23: 17322.96 | F23: 343.34 | G23: =(F23/B23*365)/-K22 -> 0.11999935 | H23: 0 | J23: =+C23 -> 17666.3 | K23: -17488.09
A24: 45685 | B24: =A24-A23 -> 31 | C24: 17666.33 | D24: 0 | E24: 17488.09 | F24: 178.24 | G24: =(F24/B24*365)/-K23 -> 0.12000351 | H24: 0 | J24: =+C24 -> 17666.33 | K24: 0
B25: =SUM(B13:B24) -> 348 | D25: =B51-B25 -> 15 | F25: =SUM(F13:F24) -> 11995.63
A26: Arrangement / Contract Details
A27: System Date | B27: 45322
A28: Amount | B28: 200000 | C28: Profit Start Date | D28: 45322
A29: Rate | B29: =+I39 -> 0.11056697 | C29: Total Profit | D29: =SUM(G39:G50) -> 11995.63 | F29: IRR | G29: =+B4 -> 0.12 | J29: =B29-G29 -> -0.0094330268
A30: Term | B30: 1Y | C30: Instalment Amount | D30: =+C39 -> 17666.3
A31: 1st Instalment Date | B31: 45350 | C31: APR | D31: 0.141284 | F31: =D29/B28 -> 0.05997815
A32: Last Intalment Date | B32: 45685 | C32: Flat Rate | D32: =(D29/(A50-A38)*365)/B28 -> 0.060308608 | E32: =+D32*B28 -> 12061.722
A33: Arrangement Reference | B33: AA24031HGFQ5 | C33: # on Accrual Days | D33: =+B32-D28 -> 363
A34: IS Contract | B34: IS24031XRVB9
A36: Payment Schedule
A37: Date | B37: Defer Date | C37: Total Due | D37: Total Cap | E37: Principal | F37: Principal Profit | G37: REC Profit | H37: Charge | I37: Tax | J37: Total Pymt | K37: Outstanding | L37: O/S Principal + Profit
A38: 45322 | C38: 2300 | D38: 0 | E38: 200000 | H38: 2000 | I38: 300 | J38: 200000 | K38: -200000 | L38: '-211,995.63'
A39: 45350 | B39: =+A39-A38 -> 28 | C39: 17666.3 | D39: 0 | E39: 15969.93 | G39: 1696.37 | H39: 0 | I39: =(G39/B39*365)/-K38 -> 0.11056697 | K39: -184030.07 | L39: '-194,329.33'
A40: 45379 | B40: =+A40-A39 -> 29 | C40: 17666.3 | D40: 0 | E40: 16049.63 | G40: 1616.67 | H40: 0 | I40: =(G40/B40*365)/-K39 -> 0.11056749 | K40: -167980.44 | L40: '-176,663.03'
A41: 45410 | B41: =+A41-A40 -> 31 | C41: 17666.3 | D41: 0 | E41: 16088.85 | G41: 1577.45 | H41: 0 | I41: =(G41/B41*365)/-K40 -> 0.11056764 | K41: -151891.59 | L41: '-158,996.73'
A42: 45440 | B42: =+A42-A41 -> 30 | C42: 17666.3 | D42: 0 | E42: 16285.95 | G42: 1380.35 | H42: 0 | I42: =(G42/B42*365)/-K41 -> 0.1105674 | K42: -135605.64 | L42: '-141,330.43'
A43: 45471 | B43: =+A43-A42 -> 31 | C43: 17666.3 | D43: 0 | E43: 16392.88 | G43: 1273.42 | H43: 0 | I43: =(G43/B43*365)/-K42 -> 0.11056689 | K43: -119212.76 | L43: '-123,664.13'
A44: 45501 | B44: =+A44-A43 -> 30 | C44: 17666.3 | D44: 0 | E44: 16582.93 | G44: 1083.37 | H44: 0 | I44: =(G44/B44*365)/-K43 -> 0.11056704 | K44: -102629.83 | L44: '-105,997.83'
A45: 45532 | B45: =+A45-A44 -> 31 | C45: 17666.3 | D45: 0 | E45: 16702.54 | G45: 963.76 | H45: 0 | I45: =(G45/B45*365)/-K44 -> 0.11056724 | K45: -85927.29 | L45: '-88,331.53'
A46: 45563 | B46: =+A46-A45 -> 31 | C46: 17666.3 | D46: 0 | E46: 16859.39 | G46: 806.91 | H46: 0 | I46: =(G46/B46*365)/-K45 -> 0.11056691 | K46: -69067.9 | L46: '-70,665.23'
A47: 45593 | B47: =+A47-A46 -> 30 | C47: 17666.3 | D47: 0 | E47: 17038.63 | G47: 627.67 | H47: 0 | I47: =(G47/B47*365)/-K46 -> 0.11056731 | K47: -52029.27 | L47: '-52,998.93'
A48: 45624 | B48: =+A48-A47 -> 31 | C48: 17666.3 | D48: 0 | E48: 17177.71 | G48: 488.59 | H48: 0 | I48: =(G48/B48*365)/-K47 -> 0.11056763 | K48: -34851.56 | L48: '-35,332.63'
A49: 45654 | B49: =+A49-A48 -> 30 | C49: 17666.3 | D49: 0 | E49: 17349.58 | G49: 316.72 | H49: 0 | I49: =(G49/B49*365)/-K48 -> 0.11056683 | K49: -17501.98 | L49: '-17,666.33'
A50: 45685 | B50: =+A50-A49 -> 31 | C50: 17666.33 | D50: 0 | E50: 17501.98 | G50: 164.35 | H50: 0 | I50: =(G50/B50*365)/-K49 -> 0.11056399 | K50: 0 | L50: 0
B51: =SUM(B39:B50) -> 363 | G51: =SUM(G39:G50) -> 11995.63
A53: Variance Analysis | B53: Offer Letter | C53: Finance Arrangement | D53: Difference
A54: Profit Start Date | B54: =+D3 -> 45337 | C54: =+D28 -> 45322
A55: Profit Amount | B55: =+D4 -> 11995.63 | C55: =+D29 -> 11995.63 | D55: =+C55-B55 -> 0
A56: IRR | B56: =+B4 -> 0.12 | C56: =+B29 -> 0.11056697 | D56: =+C56-B56 -> -0.0094330268
A57: APR | B57: =+D6 -> 0.153299 | C57: =+D31 -> 0.141284 | D57: =C57-B57 -> -0.012015
A58: Flat Rate | B58: =+D7 -> 0.062727865 | C58: =+D32 -> 0.060308608 | D58: =C58-B58 -> -0.0024192565
A78: The approved IRR rate for 350 days however in workaround solution goes to 365 days which resulted changed in approved IRR.
A79: There is an impact on reporting where IRR is missing on AA.ARR.INTEREST
A80: CRC & CRF reports will not reflects any rate in finance report
A81: Impact on Early settlement amount
A82: Impact on Early settlement fee and partial ssettlement fee amounts
A83: Impact on APR if workaround approach is also used for simulation

Sheet Day4 - Product Setup
A6: Personal Finance - Personal Finance Product (New Finance, Restructured Finance, Buy-out Finance and Top-up Finance)
A7: Product | B7: Product Attributes | C7: T24 Table Name | D7: T24 Field Name | E7: FREquency in which the Interest is Paid/Collected | F7: Business Values | H7: Is given business rule fixed for all Contracts or can be modified at Contract level | I7: If there is a change in the business rule, for example an interest rate change, does it affect existing Contracts also or only new Contracts | J7: RESETTING - During any Renewal Activities (for eg : change.product, rollover or reset) the property conditions will be reset from the product. NON-RESETTING - During any Renewal Activities property conditions will be maintained from the Arrangement level. | K7: Comments
B8: Currency | C8: AA.PRODUCT.DESIGNER | D8: CURRENCY | E8: Allowed Currency to open contract | F8: SAR | H8: FIXED
B9: Mode of Operation | C9: AA.PRD.DES.CUSTOMER | D9: CUSTOMER/ROLE | E9: Single Person / More than 1 person allowed | F9: Single | H9: FIXED
B10: Eligibility | C10: AA.PRD.DES.ELIGIBILITY | D10: RULE | E10: Customer eligibility criteria to get into the Contract like Age,Customer Group etc | F10: NO | H10: FIXED
B11: IBAN | C11: AA.PRD.DES.ACCOUNT | D11: ALD.ID.TYPE | E11: Is IBAN applicable | F11: NO | H11: FIXED
B12: Legacy Contract ID | C12: AA.PRD.DES.ACCOUNT | D12: ALD.ID.TYPE | E12: Legacy Contract ID (Data Migration) | F12: NO
B13: Category | C13: AA.PRD.DES.ACCOUNT | D13: CATEGORY | E13: GL Category(can be filled later) | F13: TO BE SHARED BY FINANCE
B14: Base Date | C14: AA.PRD.DES.ACCOUNT | D14: BASE.DATE | E14: What should be the Base date to considered, Contract Date or Disbursement Date | F14: Disbursement Date | H14: FIXED
B15: Date Convention | C15: AA.PRD.DES.ACCOUNT | D15: DATE.CONVENTION | E15: What should be the days convention to collect the Interest & Charges if the collection days is Holiday like Forward, Backward, Forward Same Month | F15: CALENDER | H15: NEGOTIABLE
B16: Limit | C16: AA.PRD.DES.LIMIT | D16: LIMIT.REFERENCE | E16: Is Limit applicable for this product? | F16: YES | H16: Negotiable
B17: Credit Check | C17: AC.BALANCE.TYPE | D17: EXCLUDE.CR.CHECK | E17: Determines whether Limit should be hit during Transactions like Disbursement, Make Due etc (This should be set in every Balance type created for the Property like Principal, Interest & Charges) | F17: only principal | H17: Negotiable
B18: Alerts | C18: AA.PRD.DES.ALERTS | D18: EVENT | E18: Mobile Alerts required | F18: YES | H18: Negotiable
B19: Messaging/Advices | C19: AA.PRD.DES.ACTIVITY.MESSAGING | D19: ADVICE | E19: Print advices sent to Customer like Loan Sanction Letter, Disbursement, schedule etc | F19: YES
B20: Change Product | C20: AA.PRD.DES.CHANGE.PRODUCT | D20: Config | E20: Can this Loan can be modified into other Loan products? | F20: N/A | H20: FIXED
B21: Charge Override | C21: AA.PRD.DES.CHARGE.OVERRIDE | E21: Will the Product allow Charge waive - Fixed Charge ? | F21: N/A | H21: NEGOTIABLE
B22: Constraint/Restriction | C22: AA.PRD.DES.CONSTRAINT | E22: AA Loan has a privilege of doing Backdated activities, Do you want to allow or Restrict. Setup required to restrict | F22: NO | H22: NEGOTIABLE
B23: Overdue | C23: AA.PRD.DES.OVERDUE | E23: Business process of Unpaid Loan Dues | F23: YES
A24: Interest/profit | B24: Product Attributes | C24: T24 Table Name | D24: T24 Field Name | E24: Rules | F24: Principal Profit | G24: Penalty / Charity Interest | H24: Is given business rule fixed for all Contracts or can be modified at Contract level | I24: If there is a change in the business rule, for example an interest rate change, does it affect existing Contracts also or only new Contracts | J24: RESETTING - During any Renewal Activities (for eg : change.product, rollover or reset) the property conditions will be reset from the product. NON-RESETTING - During any Renewal Activities property conditions will be maintained from the Arrangement level. | K24: Comments
B25: Accrual Frequency | C25: AA.ACCRUAL.FREQUENCY | D25: DEFAULT.LCY/FCY | E25: Daily or Monthly or Quarterly | F25: Daily | G25: N/A
B26: Interest Schedule | C26: AA.PRD.DES.PAYMENT.SCHEDULE | D26: FREQUENCY | E26: Frequency in which the Interest is Paid/Collected | F26: Monthly(EMI) | G26: N/A | H26: Negotiable
A27: Loan frequency must match with customer salary date | B27: Collection Method | C27: AA.PRD.DES.PAYMENT.SCHEDULE | D27: PAYMENT.METHOD | E27: Always Due to collect from the Customer on the Scheduled Date | F27: Due | G27: N/A
B28: Interest Basis | C28: AA.PRD.DES.INTEREST | D28: DAY.BASIS | E28: Interest calculation method (360/360, 366/365, 366/360) | F28: Actual/365 = E | G28: N/A
B29: Accrual Rule | C29: AA.PRD.DES.INTEREST | D29: ACCRUAL.RULE | E29: Actual days balance to be included for Accruals (First, Last & Both) | F29: First | G29: N/A | H29: Negotiable
B30: Threshold | C30: AA.PRD.DES.INTEREST | D30: CALC.THRESHOLD | E30: NA | F30: N/A | G30: N/A
B31: Interest Type | C31: AA.PRD.DES.INTEREST | E31: Fixed or Floating or Periodic | F31: Fixed | G31: N/A | H31: Negotiable
E32: Fixed Rate | F32: will come from LOS | G32: N/A | H32: Negotiable
E33: Floating Rate(linke to Internal Bank Index) | F33: N/A | G33: N/A | H33: Negotiable
E34: Fixed Rate (Linked to External Index such as AEIBOR , or varies according to Amount). | F34: N/A | G34: N/A
B35: Rate Type | C35: AA.PRD.DES.INTEREST | D35: RATE.TYPE | E35: Specifies whether Interest definition is based on a rate or amount and in case of rate what type of rate. Reducing rate, Flat rate, Flat amount, weighted Average Rate. | F35: Reducing Rate | G35: N/A
B36: Tier Type / Interest Calculation method | C36: AA.PRD.DES.INTEREST | D36: RATE.TIER.TYPE | E36: Rules for calculation, please provide example - is it straight forward percentage on the eligible balance, or does the percentage vary depending on the balance? | F36: N/A | G36: N/A
B37: Minimum Interest | C37: AA.PRD.DES.INTEREST | D37: MIN.INT.AMOUNT | E37: Minimum Interest amount to be paid by the customer, for this product | F37: N/A | G37: N/A
B38: Minimum Interest Waive | C38: AA.PRD.DES.INTEREST | D38: MIN.INT.WAIVE | E38: If the Calculated Interest is lesser than Minimum Interest Amount, whether the Interest is to be collected or not collected from the customer | F38: N/A | G38: N/A
B39: Charges Collection | C39: AA.PRD.DES.CHARGE | D39: Config | E39: If the Contract does not contain sufficient funds for charges, what is the business process? | F39: N/A | G39: N/A
A40: Fees & Charges | B40: Product Attributes | C40: T24 Table Name | D40: T24 Field Name | E40: Rules | F40: Activity | G40: Frequency (If scheduled) | H40: Rules for calculation, if any | I40: Is given business rule fixed for all Contracts or can be modified at Contract level | J40: Transaction Name (If Activity Based) | K40: Charge Type | L40: Fixed Amount | M40: Percentage (If Calculated) | N40: Min Charge | O40: Max Charge | P40: Charge Tier | Q40: PL Category (Acctng) | R40: RESETTING - During any Renewal Activities (for eg : change.product, rollover or reset) the property conditions will be reset from the product. NON-RESETTING - During any Renewal Activities property conditions will be maintained from the Arrangement level. | S40: Comments
B41: Upfront Admin Fee | C41: AA.PRD.DES.CHARGE | D41: Config | E41: Monthly Charges Leived | F41: YES | G41: Treatment of PL credit is amortized over the life of contract through straight line method- Activity based | H41: 1% or Max. of 5000 whichever is lower | I41: Negotiable | S41: non tracking
B42: Monthly Admin Fee | C42: AA.PRD.DES.ACTIVITY.CHARGES | D42: Config | E42: Fee charged against the Loan Principal Decrease | F42: YES | G42: Monthly Installment | H42: 1% or Max. of 5000 whichever is lower and divided by No. of Installments | I42: Negotiable | K42: CALCULATED | M42: 0 | S42: non tracking
B43: Payoff Fee (Early Settlement Fee) | C43: AA.PRD.DES.ACTIVITY.CHARGES | D43: Config | E43: Loan Closure charges before Maturity | F43: YES | G43: Activity | H43: Three months Profit proceeding months if available else remaining days profit | I43: Negotiable | K43: CALCULATED | M43: 0 | S43: non tracking
B44: Partial Payment Fee | C44: AA.PRD.DES.ACTIVITY.CHARGES | D44: Config | E44: Loan repayment installment changes, changes either in Payment Amount or Decrese/Increase in Term | F44: YES | G44: Activity | H44: Three months Profit proceeding months if available else remaining days profit | I44: Negotiable | K44: CALCULATED | M44: 0 | S44: non tracking
B45: Bonus | C45: AA.PRD.DES.ACTIVITY.CHARGES | D45: Config | E45: rebate | F45: YES | G45: Activity | I45: Negotiable | S45: non tracking
A46: Overdue | B46: Product Attributes | C46: T24 Table Name | D46: T24 Field Name | E46: Rules | F46: Business Values | H46: Is given business rule fixed for all Contracts or can be modified at Contract level | I46: If there is a change in the business rule, for example an interest rate change, does it affect existing Contracts also or only new Contracts | K46: Comments
B47: Bill Type | C47: AA.PRD.DES.OVERDUE | D47: BILL.TYPE | E47: On What bill type that the Overdue processing should Apply EX: Payment Bill (P+I), Activity Charges etc | F47: PAYMENT BILL
B48: Overdue Status | C48: AA.PRD.DES.OVERDUE | D48: OVERDUE.STATUS | E48: List of Overdue Aging Process that the bill should undergo, EBLOOKUP records to be configured
C49: RETAIL | E49: Grace
E50: Bucket 1 - Satge I | F50: 1 to 30 | H50: BF need to be confirm whether they go for number of days or bills.
E51: Bucket 2 - Stage IIA | F51: 31 to 60 | H51: System will recalculate bucket based on repayment of instalment.
E52: Bucket 3 - Stage IIB | F52: 61 to 90
E53: Bucket 4 - Stage IIIA | F53: 91-120
E54: Bucket 5 - Stage IIIB | F54: 121-150
E55: Bucket 6 - Stage VIA | F55: 151-180
E56: Bucket N - Stage IVB | F56: 180+
B57: Aging all - Suspend | C57: AA.PRD.DES.OVERDUE | D57: AGE.ALL.BILLS | E57: Suspension of Contract is Allowed, ie Accrual are not taken into P&L | F57: YES | H57: Suspension will be applied only on upcoming profit and not on overdue bills. We need to make the Property as Suspend. Previous accrual would not be reversed.
E58: From which OD Status the Suspension should apply | F58: STAGE IIIA - 91-120
C59: AA.PRD.DES.OVERDUE
B60: Arrangement Bill Type | C60: AA.PRD.DES.OVERDUE | D60: ARR.BILL.TYPE | E60: Overall Status of the Contract should be Determined by the Bill Type | F60: INSTALLMENT for all
A61: Payment Rules | B61: Product Attributes | C61: T24 Table Name | D61: T24 Field Name | E61: Rules | F61: Business Values | H61: Is given business rule fixed for all Contracts or can be modified at Contract level | I61: If there is a change in the business rule, for example an interest rate change, does it affect existing Contracts also or only new Contracts | J61: Comments
B62: Payment Type | C62: AA.PRD.DES.PAYMENT.RULES | D62: APPLICATION.TYPE | E62: How the Payment rule should be applied, By Date or By Property or Current Balances | F62: Date
B63: Order of Payment | C63: AA.PRD.DES.PAYMENT.RULES | D63: APPLICATION.ORDER | E63: On what order the Payment Bill should be Paid Ex: Oldest First or Newest First | F63: OLDEST
B64: Sequence | C64: AA.PRD.DES.PAYMENT.RULES | D64: SEQUENCE | E64: Sequence in settling the Dues, Like Revenues First followed by the Principal, EX: Charges, Interest, Commisions, Insurance, Principal | F64: FEE + PROFIT + PRINCIPAL | U64: Charity added in sequence on 16-08-23
B65: Remainder Activity | C65: AA.PRD.DES.PAYMENT.RULES | D65: REMAINDER.ACTIVITY | E65: What should be allocation of Any Excess remittances more than the Loan Due amount | F65: not allowed
E66: 1. After Settling Dues, Do Principal Decrease | F66: not allowed | H66: As per MB
E67: 2. After Settling Dues, park it as Advance for Future Bill | F67: not allowed | H67: As per MB
E68: 3. After Settling Dues, Park it in Allocated Credit (to Settle Future Bills) | F68: not allowed | H68: As per MB
E69: 4. Do not allow more than the Due Amount | F69: not allowed | H69: As per MB
E70: Payment Rules must be defined for the Below | F70: As per MB | H70: As per MB
E71: 1. Installment Payment | F71: As per MB
E72: 2. Principal Decrease | F72: As per MB
E73: 3. Loan Payoff | F73: As per MB
A74: Payout Rules | B74: Product Attributes | C74: T24 Table Name | D74: T24 Field Name | E74: Rules | F74: Business Values | H74: Is given business rule fixed for all Contracts or can be modified at Contract level | I74: If there is a change in the business rule, for example an interest rate change, does it affect existing Contracts also or only new Contracts | J74: Comments
B75: Payment Type | C75: AA.PRD.DES.PAYOUT.RULES | D75: APPLICATION.TYPE | E75: How the Payout rule should be applied - Default vaule is By Property for Disbursement | F75: YES
B76: Order of Payment | C76: AA.PRD.DES.PAYOUT.RULES | D76: APPLICATION.ORDER | E76: On what order the Payment Bill should be Paid Ex: Oldest First or Newest First | F76: as per MB
B77: Sequence | C77: AA.PRD.DES.PAYOUT.RULES | D77: SEQUENCE | E77: Sequence in Disbursing the Sanctioned Amount with any Bonus, EX: Bonus, Disbursement Amount (Principal) | F77: as per MB
B78: Remainder Activity | C78: AA.PRD.DES.PAYOUT.RULES | D78: REMAINDER.ACTIVITY | E78: By Default Disburse activity | F78: no
A79: Payment Schedule | B79: Product Attributes | C79: T24 Table Name | D79: T24 Field Name | E79: Rules | F79: Business Values | H79: Is given business rule fixed for all Contracts or can be modified at Contract level | I79: If there is a change in the business rule, for example an interest rate change, does it affect existing Contracts also or only new Contracts | J79: RESETTING - During any Renewal Activities (for eg : change.product, rollover or reset) the property conditions will be reset from the product. NON-RESETTING - During any Renewal Activities property conditions will be maintained from the Arrangement level. | K79: Comments
B80: Payment Type | C80: AA.PRD.DES.PAYMENT.SCHEDULE | D80: PAYMENT.TYPE | E80: Type of Payment Bill ex: Constant, Liner, Interest Only etc | F80: Constant / Special Payment Type 1=(Principal + profit) Payment Type2=Advance Period Profit Payment Type 3= Miscelleneous Expenses | H80: Negotiable
E81: Disbursement - For Auto Disbursement activity | F81: Auto
B82: Payment Method | C82: AA.PRD.DES.PAYMENT.SCHEDULE | D82: PAYMENT.METHOD | E82: Method of Collecting the Payment - Bill needs to made Due (Default Due for Loan) | F82: DUE
B83: Payment Frequency | C83: AA.PRD.DES.PAYMENT.SCHEDULE | D83: PAYMENT.FREQ | E83: Frequency of Collecting the Installments Ex: Monthly, Every 3 Months, or @ Defined Frequncy | F83: MONTHLY | H83: Negotiable
B84: Property | C84: AA.PRD.DES.PAYMENT.SCHEDULE | D84: PROPERTY | E84: Payment split up property wise, Principal, Interest, Penalty, Charges | F84: Principal + Profit + Charge (Admin Fee + VAT) | H84: Negotiable | I84: BF will confirm whether the Admin Fee be part of repayment schedule in case of monthly admin fee charge
B85: Start Date | C85: AA.PRD.DES.PAYMENT.SCHEDULE | D85: START.DATE | E85: Start date of the Loan Installment to begin | F85: yes | H85: Negotiable
B86: End Date | C86: AA.PRD.DES.PAYMENT.SCHEDULE | D86: END.DATE | E86: End date of the Installment or Maturity | F86: yes | H86: Negotiable
B87: Actual Amount | C87: AA.PRD.DES.PAYMENT.SCHEDULE | D87: ACTUAL.AMT | E87: Any Fixed Installment needs to be collected irrespective of Calculated Payment | F87: no
B88: On Activity | C88: AA.PRD.DES.PAYMENT.SCHEDULE | D88: ON.ACTIVITY | E88: List of Activities on which the payment schedule needs to be recalculated. Ex: On Interest changes, whether payment or term of the contract to be recalculated | F88: as per MB | H88: Negotiable
B89: Recalculate | C89: AA.PRD.DES.PAYMENT.SCHEDULE | D89: RECALCULATE | E89: Values to be defined with the Above setup, predefined values Term, Payment, Residual, Nothing | F89: as per MB | H89: Negotiable
B90: Recalculation Frequency | C90: AA.PRD.DES.PAYMENT.SCHEDULE | D90: RECALC.FREQUENCY | E90: Frequency is required if any of the recalution type is set as "Nothing" | F90: MONTHLY ( end of the month) | H90: Negotiable
B91: Repay from Credit Balance | C91: AA.PRD.DES.PAYMENT.SCHEDULE | D91: APPLY.PAYMENT | E91: Any Allocated Credit available in Loan will be used for settling the Payment bill before debiting the customer Account | F91: Yes
A92: Payoff | B92: Product Attributes | C92: T24 Table Name | D92: T24 Field Name | E92: Rules | F92: Business Values | H92: Is given business rule fixed for all Contracts or can be modified at Contract level | I92: If there is a change in the business rule, for example an interest rate change, does it affect existing Contracts also or only new Contracts | J92: Comments
B93: Expiry Days | C93: AA.PRD.DES.PAYOFF | D93: EXPIRY.DAYS | E93: Days to expire after a Payoff Bill is generated (After the expiry date, the bill will be deleted) | F93: NO
A94: Settlement | B94: Product Attributes | C94: T24 Table Name | D94: T24 Field Name | E94: Rules | F94: Business Values | H94: Is given business rule fixed for all Contracts or can be modified at Contract level | I94: If there is a change in the business rule, for example an interest rate change, does it affect existing Contracts also or only new Contracts | J94: Comments
B95: Payin Payment Type | C95: AA.PRD.DES.SETTLEMENT | D95: PAYMENT.TYPE | E95: Payment type based on which the Settlement will be processed (This should be same as defined in the Schedule) | F95: constant Payment Type 1=(Principal + profit) Payment Type 2= Charges | H95: Negotiable
B96: Payin Settlement (Active Y/N) | C96: AA.PRD.DES.SETTLEMENT | D96: PAYIN.SETTLEMENT | E96: This is the Switch to turn On or Off the Settlement Processing - What should be the vaule by default | F96: YES | H96: Negotiable
B97: Debit Rule | C97: AA.PRD.DES.SETTLEMENT | D97: PAYIN.AC.DB.RULE | E97: This helps in utilisation of funds available in Customer Account, Full, Partial & None | F97: PARTIAL | H97: Negotiable
B98: RC Condition | C98: AA.PRD.DES.SETTLEMENT | D98: PAYIN.RC.CONDITION | E98: Frequency to retry the settlement process | F98: RC
B99: RC Type | C99: AA.PRD.DES.SETTLEMENT | D99: PAYIN.RC.TYPE | E99: Default will be AA | F99: AA
B100: Payout Payment Type | C100: AA.PRD.DES.SETTLEMENT | D100: PAYOUT.PPTY.CLASS | E100: Property based on which the Settlement will be processed (This should be same as defined in the Schedule) | F100: Account | H100: Negotiable
B101: Payout Settlement (Active Y/N) | C101: AA.PRD.DES.SETTLEMENT | D101: PAYOUT.SETTLEMENT | E101: This is the Switch to turn On or Off the Settlement Processing - What should be the vaule by default | F101: YES
A102: Term Amount | B102: Product Attributes | C102: T24 Table Name | D102: T24 Field Name | E102: Rules | F102: Business Values | H102: Is given business rule fixed for all Contracts or can be modified at Contract level | I102: If there is a change in the business rule, for example an interest rate change, does it affect existing Contracts also or only new Contracts | J102: Comments
B103: Maturity Date Convention | C103: AA.PRD.DES.TERM.AMOUNT | D103: MAT.DATE.CONVENTION | E103: This setup is to determine the Maturity Date when falls on Holiday (If Yes, System will reference date Convention in ACCOUNT property, If NO system will raise Override if end date is HOLIDAY) | F103: Calender Date
B104: Revolving | C104: AA.PRD.DES.TERM.AMOUNT | D104: REVOLVING | E104: Field value required if the Facility is of Revolving Nature | F104: Non-Revolving | H104: Negotiable
B105: Cooling Period | C105: AA.PRD.DES.TERM.AMOUNT | D105: COOLING.PERIOD | E105: Cooling Period untill the Loan can be disbursed from the creation date | F105: 10 Days | J105: Maker & Checker is required
...

Sheet Day4 - Partial Settlement
A1: PARTIAL SETTLEMENT - ORIGINAL (1 of 3)
A4: Payment Schedule
A5: Date | B5: Defer Date | C5: Total Due | D5: Total Cap | E5: Principal | F5: Principal Profit | G5: REC Profit | H5: Charge | I5: Tax | J5: Total Pymt | K5: Outstanding | L5: O/S Principal + Profit
A6: 44944 | C6: 2000 | D6: 0 | E6: 200000 | H6: 2000 | J6: 200000 | K6: -200000 | L6: -235967.12
A7: 44975 | C7: 13109.28 | D7: 0 | E7: 9427.43 | G7: 3681.85 | K7: -190572.57 | L7: -222857.84
A8: 45003 | C8: 13109.28 | D8: 0 | E8: 9940.5 | G8: 3168.78 | K8: -180632.07 | L8: -209748.56
A9: 45034 | C9: 13109.28 | D9: 0 | E9: 9783.98 | G9: 3325.3 | K9: -170848.09 | L9: -196639.28 | M9: System Date
A10: 45064 | C10: 13109.28 | D10: 0 | E10: 10065.56 | G10: 3043.72 | K10: -160782.53 | L10: -183530 | O10: 5 INSTALLMENT | Q10: =SUM(C10:C14) -> 65546.4
A11: 45095 | C11: 13109.28 | D11: 0 | E11: 10149.4 | G11: 2959.88 | K11: -150633.13 | L11: -170420.72 | O11: 5 PROFIT | Q11: =SUM(G11:G15) -> 12731.13 | R11: =SUM(G10:G14) -> 13655.58
A12: 45125 | C12: 13109.28 | D12: 0 | E12: 10425.7 | G12: 2683.58 | K12: -140207.43 | L12: -157311.44 | O12: 5 PRINCIPAL | Q12: =Q10-Q11 -> 52815.27 | R12: =+Q10-R11 -> 51890.82
A13: 45156 | C13: 13109.28 | D13: 0 | E13: 10528.17 | G13: 2581.11 | K13: -129679.26 | L13: -144202.16
A14: 45187 | C14: 13109.28 | D14: 0 | E14: 10721.99 | G14: 2387.29 | K14: -118957.27 | L14: -131092.88
A15: 45217 | C15: 13109.28 | D15: 0 | E15: 10990.01 | G15: 2119.27 | K15: -107967.26 | L15: -117983.6 | O15: 5 PRINCIPAL | Q15: 52815.27 | R15: =SUM(E11:E15) -> 52815.27
A16: 45248 | C16: 13109.28 | D16: 0 | E16: 11121.69 | G16: 1987.59 | K16: -96845.57 | L16: -104874.32 | O16: 5 PROFIT | Q16: 12731.13 | R16: =SUM(G11:G15) -> 12731.13
A17: 45278 | C17: 13109.28 | D17: 0 | E17: 11383.94 | G17: 1725.34 | K17: -85461.63 | L17: -91765.04 | O17: 5 INSTALLMENT | Q17: =SUM(Q15:Q16) -> 65546.4 | R17: =SUM(C11:C15) -> 65546.4 | S17: Transaction Amount
A18: 45309 | C18: 13109.28 | D18: 0 | E18: 11536 | G18: 1573.28 | K18: -73925.63 | L18: -78655.76
A19: 45340 | C19: 13109.28 | D19: 0 | E19: 11748.37 | G19: 1360.91 | K19: -62177.26 | L19: -65546.48
A20: 45369 | C20: 13109.28 | D20: 0 | E20: 12038.49 | G20: 1070.79 | K20: -50138.77 | L20: -52437.2
A21: 45400 | C21: 13109.28 | D21: 0 | E21: 12186.26 | G21: 923.02 | K21: -37952.51 | L21: -39327.92
A22: 45430 | C22: 13109.28 | D22: 0 | E22: 12433.14 | G22: 676.14 | K22: -25519.37 | L22: -26218.64
A23: 45461 | C23: 13109.28 | D23: 0 | E23: 12639.49 | G23: 469.79 | K23: -12879.88 | L23: -13109.36
A24: 45491 | C24: 13109.36 | D24: 0 | E24: 12879.88 | G24: 229.48 | K24: 0 | L24: 0
E25: =SUM(E7:E24) -> 200000 | G25: =SUM(G7:G24) -> 35967.12
A75: After 5 Inst. Compression As Advance Installment (2 of 3)
A78: Payment Schedule
A79: Date | B79: Defer Date | C79: Total Due | D79: Total Cap | E79: Principal | F79: Principal Profit | G79: REC Profit | H79: Charge | I79: Tax | J79: Total Pymt | K79: Outstanding | L79: O/S Principal + Profit
A80: 44944 | C80: 2000 | D80: 0 | E80: 200000 | H80: 2000 | J80: 200000 | K80: -200000 | L80: -235967.12
A81: 44975 | C81: 13109.28 | D81: 0 | E81: 9427.43 | G81: 3681.85 | K81: -190572.57 | L81: -222857.84
A82: 45003 | C82: 13109.28 | D82: 0 | E82: 9940.5 | G82: 3168.78 | K82: -180632.07 | L82: -209748.56
A83: 45034 | C83: 13109.28 | D83: 0 | E83: 9783.98 | G83: 3325.3 | K83: -118032.82 | L83: -131092.88
A84: 45064 | C84: 8739.53 | D84: 0 | E84: 7182.17 | G84: 1557.36 | K84: -110850.65 | L84: -122353.35
A85: 45095 | C85: 8739.53 | D85: 0 | E85: 7228.18 | G85: 1511.35 | K85: -103622.47 | L85: -113613.82
A86: 45125 | C86: 8739.53 | D86: 0 | E86: 7372.31 | G86: 1367.22 | K86: -96250.16 | L86: -104874.29
A87: 45156 | C87: 8739.53 | D87: 0 | E87: 7427.25 | G87: 1312.28 | K87: -88822.91 | L87: -96134.76
A88: 45187 | C88: 8739.53 | D88: 0 | E88: 7528.51 | G88: 1211.02 | K88: -81294.4 | L88: -87395.23
A89: 45217 | C89: 8739.53 | D89: 0 | E89: 7666.91 | G89: 1072.62 | K89: -73627.49 | L89: -78655.7
A90: 45248 | C90: 8739.53 | D90: 0 | E90: 7735.69 | G90: 1003.84 | K90: -65891.8 | L90: -69916.17
A91: 45278 | C91: 8739.53 | D91: 0 | E91: 7870.13 | G91: 869.4 | K91: -58021.67 | L91: -61176.64
A92: 45309 | C92: 8739.53 | D92: 0 | E92: 7948.46 | G92: 791.07 | K92: -50073.21 | L92: -52437.11
... A98: 45491 | C98: 8739.46 | D98: 0 | E98: 8625.65 | G98: 113.81 | K98: 0 | L98: 0
G99: =SUM(G81:G98) -> 23235.99 | I99: 25791.19
G100: ='[2]Prior to Compression'!G99 -> 0 | I100: 13060.06
G101: =G100-G99 -> -23235.99 | I101: =I100-I99 -> -12731.13
F110: Debit | G110: Credit | J110: Findings
A111: Unearned Profit | C111: ACCDEFERREDPFT | F111: 12731.13 | J111: Profit reduced by recovered amount in Payment Schedule.
A112: Profit | C112: PL | G112: =+F111 -> 12731.13 | J112: Installment amount recalculated keeping the tenor of deal intact.
J113: Recovered profit immediately taken into PL.
A114: Arrangement Int. A/c. | C114: AA SUSPENSE | F114: =+F111 -> 12731.13 | J114: Profit & Principal being recorded with recovered amount as per stated entries
A115: Receivable Profit | C115: RECDEFERREDPFT | G115: =+F114 -> 12731.13
J116: Challenge
A117: Customer A/c. | C117: SETTLEMENT A/C. | F117: =+F114 -> 12731.13 | J117: APR recalculated on revised payment schedule not considering partial payment amount.
A118: Arrangement Int. A/c. | C118: AA SUSPENSE | G118: =+F117 -> 12731.13 | J118: No reflection of partial payment on schedule
A120: Arrangement Int. A/c. | C120: AA SUSPENSE | F120: 52815.27
A121: Prinaicpal | C121: CURACCOUNT | G121: =+F120 -> 52815.27
A123: Customer A/c. | C123: SETTLEMENT A/C. | F123: =+F120 -> 52815.27
A124: Arrangement Int. A/c. | C124: AA SUSPENSE | G124: =+F123 -> 52815.27
A126: For Financial Institution
F127: Debit | G127: Credit
A128: Unearned Profit | C128: ACCDEFERREDPFT | F128: 12731.13
A129: Profit | C129: PL | G129: =+F128 -> 12731.13
A131: Arrangement Int. A/c. | C131: AA SUSPENSE | F131: =+F128 -> 12731.13
A132: Receivable Profit | C132: RECDEFERREDPFT | G132: =+F131 -> 12731.13
A134: Customer A/c. | C134: SETTLEMENT A/C. | F134: =+F131 -> 12731.13
A135: Arrangement Int. A/c. | C135: AA SUSPENSE | G135: =+F134 -> 12731.13
A137: Arrangement Int. A/c. | C137: AA SUSPENSE | F137: 52815.27
A138: Prinaicpal | C138: CURACCOUNT | G138: =+F137 -> 52815.27
A140: Customer A/c. | C140: SETTLEMENT A/C. | F140: =+F137 -> 52815.27
A141: Arrangement Int. A/c. | C141: AA SUSPENSE | G141: =+F140 -> 52815.27
A146: After Maturity Decrease 5 Months (3 of 3)
A148: Payment Schedule
A149: Date | B149: Defer Date | C149: Total Due | D149: Total Cap | E149: Principal | F149: Principal Profit | G149: REC Profit | H149: Charge | I149: Tax | J149: Total Pymt | K149: Outstanding | L149: O/S Principal + Profit
A150: 44944 | C150: 2000 | D150: 0 | E150: 200000 | H150: 2000 | J150: 200000 | K150: -200000 | L150: -235967.12
A151: 44975 | C151: 13109.28 | D151: 0 | E151: 9427.43 | G151: 3681.85 | K151: -190572.57 | L151: -222857.84
A152: 45003 | C152: 13109.28 | D152: 0 | E152: 9940.5 | G152: 3168.78 | K152: -180632.07 | L152: -209748.56
A153: 45034 | C153: 13109.28 | D153: 0 | E153: 9783.98 | G153: 3325.3 | K153: -118032.82 | L153: -131092.88
A154: 45064 | C154: 13109.29 | D154: 0 | E154: 10841.35 | G154: 2267.94 | K154: -107191.47 | L154: -117983.59
A155: 45095 | C155: 13109.29 | D155: 0 | E155: 10981 | G155: 2128.29 | K155: -96210.47 | L155: -104874.3
A156: 45125 | C156: 13109.29 | D156: 0 | E156: 11260.65 | G156: 1848.64 | K156: -84949.82 | L156: -91765.01
A157: 45156 | C157: 13109.29 | D157: 0 | E157: 11422.61 | G157: 1686.68 | K157: -73527.21 | L157: -78655.72
A158: 45187 | C158: 13109.29 | D158: 0 | E158: 11649.41 | G158: 1459.88 | K158: -61877.8 | L158: -65546.43
A159: 45217 | C159: 13109.29 | D159: 0 | E159: 11920.34 | G159: 1188.95 | K159: -49957.46 | L159: -52437.14
A160: 45248 | C160: 13109.29 | D160: 0 | E160: 12117.38 | G160: 991.91 | K160: -37840.08 | L160: -39327.85
A161: 45278 | C161: 13109.29 | D161: 0 | E161: 12382.21 | G161: 727.08 | K161: -25457.87 | L161: -26218.56
A162: 45309 | C162: 13109.29 | D162: 0 | E162: 12603.82 | G162: 505.47 | K162: -12854.05 | L162: -13109.27
A163: 45340 | C163: 13109.27 | D163: 0 | E163: 12854.05 | G163: 255.22 | K163: 0 | L163: 0
G164: =SUM(G151:G163) -> 23235.99

Sheet Day4 - Partial Settlement (RT)
A1: Partial Settlement (Revised Term)
A3: Original
A5: Payment Schedule
A6: Date | B6: Defer Date | C6: Total Due | D6: Total Cap | E6: Principal | F6: Principal Profit | G6: REC Profit | H6: Charge | I6: Tax | J6: Total Pymt | K6: Outstanding | L6: O/S Principal + Profit
A7: 45323 | C7: 5750 | D7: 0 | E7: 500000 | H7: 5000 | I7: 750 | J7: 500000 | K7: -500000 | L7: -658990.35
A8: 45350 | C8: 10983.17 | D8: 0 | E8: 6730.49 | G8: 4252.68 | H8: 0 | K8: -493269.51 | L8: -648007.18
A9: 45379 | C9: 10983.17 | D9: 0 | E9: 6476.96 | G9: 4506.21 | H9: 0 | K9: -486792.55 | L9: -637024.01 | N9: 3 INSTALLMENTS | P9: =SUM(C8:C10) -> 32949.51
A10: 45410 | C10: 10983.17 | D10: 0 | E10: 6229.44 | G10: 4753.73 | H10: 0 | K10: -480563.11 | L10: -626040.84 | N10: 3 PRINCIPAL | P10: =SUM(E8:E10) -> 19436.89
A11: 45440 | C11: 10983.17 | D11: 0 | E11: 6441.65 | G11: 4541.52 | H11: 0 | K11: -474121.46 | L11: -615057.67 | N11: 3 PROFIT | P11: =SUM(G8:G10) -> 13512.62
A12: 45471 | C12: 10983.17 | D12: 0 | E12: 6353.18 | G12: 4629.99 | H12: 0 | K12: -467768.28 | L12: -604074.5
A13: 45501 | C13: 10983.17 | D13: 0 | E13: 6562.57 | G13: 4420.6 | H13: 0 | K13: -461205.71 | L13: -593091.33
A14: 45532 | C14: 10983.17 | D14: 0 | E14: 6479.3 | G14: 4503.87 | H14: 0 | K14: -454726.41 | L14: -582108.16
A15: 45563 | C15: 10983.17 | D15: 0 | E15: 6542.58 | G15: 4440.59 | H15: 0 | K15: -448183.83 | L15: -571124.99
A16: 45593 | C16: 10983.17 | D16: 0 | E16: 6747.65 | G16: 4235.52 | H16: 0 | K16: -441436.18 | L16: -560141.82
A17: 45624 | C17: 10983.17 | D17: 0 | E17: 6672.36 | G17: 4310.81 | H17: 0 | K17: -434763.82 | L17: -549158.65
A18: 45654 | C18: 10983.17 | D18: 0 | E18: 6874.48 | G18: 4108.69 | H18: 0 | K18: -427889.34 | L18: -538175.48
A19: 45685 | C19: 10983.17 | D19: 0 | E19: 6804.65 | G19: 4178.52 | H19: 0 | K19: -421084.69 | L19: -527192.31
A20: 45716 | C20: 10983.17 | D20: 0 | E20: 6871.1 | G20: 4112.07 | H20: 0 | K20: -414213.59 | L20: -516209.14
A21: 45744 | C21: 10983.17 | D21: 0 | E21: 7329.65 | G21: 3653.52 | H21: 0 | K21: -406883.94 | L21: -505225.97
A22: 45775 | C22: 10983.17 | D22: 0 | E22: 7009.78 | G22: 3973.39 | H22: 0 | K22: -399874.16 | L22: -494242.8
A23: 45805 | C23: 10983.17 | D23: 0 | E23: 7204.2 | G23: 3778.97 | H23: 0 | K23: -392669.96 | L23: -483259.63
... A67: 47146 | C67: 10983.32 | D67: 0 | E67: 10877.14 | G67: 106.18 | H67: 0 | K67: 0 | L67: 0
E68: =SUM(E8:E67) -> 500000 | G68: =SUM(G8:G67) -> 158990.35
A70: Revised Term
A72: Payment Schedule
A73: Date | B73: Defer Date | C73: Total Due | D73: Total Cap | E73: Principal | F73: Principal Profit | G73: REC Profit | H73: Charge | I73: Tax | J73: Total Pymt | K73: Outstanding | L73: O/S Principal + Profit
A74: 45323 | C74: 5750 | D74: 0 | E74: 500000 | H74: 5000 | I74: 750 | J74: 500000 | K74: -500000 | L74: -658990.35
A75: 45350 | C75: 10983.17 | D75: 0 | E75: 7316.46 | G75: 3666.71 | H75: 0 | K75: -473246.65 | L75: -615057.67
A76: 45379 | C76: 10983.17 | D76: 0 | E76: 6620.02 | G76: 4363.15 | H76: 0 | K76: -466626.63 | L76: -604074.5
A77: 45410 | C77: 10983.17 | D77: 0 | E77: 6384.36 | G77: 4598.81 | H77: 0 | K77: -460242.27 | L77: -593091.33
A78: 45440 | C78: 10983.17 | D78: 0 | E78: 6593.6 | G78: 4389.57 | H78: 0 | K78: -453648.67 | L78: -582108.16
A79: 45471 | C79: 10983.17 | D79: 0 | E79: 6512.26 | G79: 4470.91 | H79: 0 | K79: -447136.41 | L79: -571124.99
A80: 45501 | C80: 10983.17 | D80: 0 | E80: 6718.6 | G80: 4264.57 | H80: 0 | K80: -440417.81 | L80: -560141.82
A81: 45532 | C81: 10983.17 | D81: 0 | E81: 6642.66 | G81: 4340.51 | H81: 0 | K81: -433775.15 | L81: -549158.65
A82: 45563 | C82: 10983.17 | D82: 0 | E82: 6708.12 | G82: 4275.05 | H82: 0 | K82: -427067.03 | L82: -538175.48
A83: 45593 | C83: 10983.17 | D83: 0 | E83: 6910.01 | G83: 4073.16 | H83: 0 | K83: -420157.02 | L83: -527192.31
A84: 45624 | C84: 10983.17 | D84: 0 | E84: 6842.34 | G84: 4140.83 | H84: 0 | K84: -413314.68 | L84: -516209.14
A85: 45654 | C85: 10983.17 | D85: 0 | E85: 7041.17 | G85: 3942 | H85: 0 | K85: -406273.51 | L85: -505225.97
A86: 45685 | C86: 10983.17 | D86: 0 | E86: 6979.17 | G86: 4004 | H86: 0 | K86: -399294.34 | L86: -494242.8
... A131: 47054 | C131: 10983.32 | D131: 0 | E131: 10879.53 | G131: 103.79 | H131: 0 | K131: 0 | L131: 0
E132: =SUM(E75:E131) -> 480563.11 | G132: =SUM(G75:G131) -> 145477.73
E133: =+[3]Original!P77 -> 0 | G133: =+[3]Original!P78 -> 0
E134: =SUM(E132:E133) -> 480563.11 | G134: =SUM(G132:G133) -> 145477.73

Sheet Day4 - Principal Decrease - Ins
A1: Original
A3: Payment Schedule | M3: Generated Date: 18-Aug-2024 19:58:09
A5: Date | B5: Defer Date | C5: Total Due | D5: Total Cap | E5: Principal | F5: Principal Profit | G5: REC Profit | H5: Charge | I5: Tax | J5: Total Pymt | K5: Outstanding | L5: O/S Principal + Profit
A6: 45321 | C6: 5750 | D6: 0 | E6: 500000 | H6: 5000 | I6: 750 | J6: 500000 | K6: '-500,000.00' | L6: '-572,552.76'
A7: 45350 | C7: 9542.55 | D7: 0 | E7: 7367.4 | G7: 2175.15 | K7: '-492,632.60' | L7: '-563,010.21'
A8: 45379 | C8: 9542.55 | D8: 0 | E8: 7399.45 | G8: 2143.1 | K8: '-485,233.15' | L8: '-553,467.66'
A9: 45410 | C9: 9542.55 | D9: 0 | E9: 7286.06 | G9: 2256.49 | K9: '-477,947.09' | L9: '-543,925.11'
A10: 45440 | C10: 9542.55 | D10: 0 | E10: 7391.64 | G10: 2150.91 | K10: '-470,555.45' | L10: '-534,382.56'
A11: 45471 | C11: 9542.55 | D11: 0 | E11: 7354.31 | G11: 2188.24 | K11: '-463,201.14' | L11: '-524,840.01'
A12: 45501 | C12: 9542.55 | D12: 0 | E12: 7458 | G12: 2084.55 | K12: '-455,743.14' | L12: '-515,297.46'
A13: 45532 | C13: 9542.55 | D13: 0 | E13: 7423.2 | G13: 2119.35 | H13: 0 | K13: '-448,319.94' | L13: '-505,754.91' | N13: 6 INSTALLMENT | O13: =SUM(C13:C18) -> 57255.3
A14: 45563 | C14: 9542.55 | D14: 0 | E14: 7457.72 | G14: 2084.83 | H14: 0 | K14: '-440,862.22' | L14: '-496,212.36' | N14: FEE | O14: =SUM(G14:G16) -> 6083.85
A15: 45593 | C15: 9542.55 | D15: 0 | E15: 7558.53 | G15: 1984.02 | H15: 0 | K15: '-433,303.69' | L15: '-486,669.81' | N15: PRINCIPAL | O15: =O13-O14 -> 51171.45
A16: 45624 | C16: 9542.55 | D16: 0 | E16: 7527.55 | G16: 2015 | H16: 0 | K16: '-425,776.14' | L16: '-477,127.26'
A17: 45654 | C17: 9542.55 | D17: 0 | E17: 7626.42 | G17: 1916.13 | H17: 0 | K17: '-418,149.72' | L17: '-467,584.71'
A18: 45685 | C18: 9542.55 | D18: 0 | E18: 7598.02 | G18: 1944.53 | H18: 0 | K18: '-410,551.70' | L18: '-458,042.16'
A19: 45716 | C19: 9542.55 | D19: 0 | E19: 7633.35 | G19: 1909.2 | H19: 0 | K19: '-402,918.35' | L19: '-448,499.61'
A20: 45744 | C20: 9542.55 | D20: 0 | E20: 7850.17 | G20: 1692.38 | H20: 0 | K20: '-395,068.18' | L20: '-438,957.06'
A21: 45775 | C21: 9542.55 | D21: 0 | E21: 7705.35 | G21: 1837.2 | H21: 0 | K21: '-387,362.83' | L21: '-429,414.51'
A22: 45805 | C22: 9542.55 | D22: 0 | E22: 7799.29 | G22: 1743.26 | H22: 0 | K22: '-379,563.54' | L22: '-419,871.96'
A23: 45836 | C23: 9542.55 | D23: 0 | E23: 7777.46 | G23: 1765.09 | H23: 0 | K23: '-371,786.08' | L23: '-410,329.41'
A24: 45866 | C24: 9542.55 | D24: 0 | E24: 7869.39 | G24: 1673.16 | H24: 0 | K24: '-363,916.69' | L24: '-400,786.86'
A25: 45897 | C25: 9542.55 | D25: 0 | E25: 7850.22 | G25: 1692.33 | H25: 0 | K25: '-356,066.47' | L25: '-391,244.31'
A26: 45928 | C26: 9542.55 | D26: 0 | E26: 7886.72 | G26: 1655.83 | H26: 0 | K26: '-348,179.75' | L26: '-381,701.76'
A27: 45958 | C27: 9542.55 | D27: 0 | E27: 7975.63 | G27: 1566.92 | H27: 0 | K27: '-340,204.12' | L27: '-372,159.21'
... A65: 47115 | C65: 9542.55 | D65: 0 | E65: 9457.24 | G65: 85.31 | H65: 0 | K65: '-9,498.15' | L65: '-9,542.31'
A66: 47146 | C66: 9542.31 | D66: 0 | E66: 9498.15 | G66: 44.16 | H66: 0 | K66: 0 | L66: 0
A69: Principal Decrease - Installment
A71: Payment Schedule | M71: Generated Date: 18-Aug-2024 20:13:24
A73: Date | B73: Defer Date | C73: Total Due | D73: Total Cap | E73: Principal | F73: Principal Profit | G73: REC Profit | H73: Charge | I73: Tax | J73: Total Pymt | K73: Outstanding | L73: O/S Principal + Profit
A74: 45321 | C74: 5750 | D74: 0 | E74: 500000 | H74: 5000 | I74: 750 | J74: 500000 | K74: '-500,000.00' | L74: '-572,552.76'
A75: 45350 | C75: 9542.55 | D75: 0 | E75: 7367.4 | G75: 2175.15 | K75: '-492,632.60' | L75: '-563,010.21'
A76: 45379 | C76: 9542.55 | D76: 0 | E76: 7399.45 | G76: 2143.1 | K76: '-485,233.15' | L76: '-553,467.66'
A77: 45410 | C77: 9542.55 | D77: 0 | E77: 7286.06 | G77: 2256.49 | K77: '-477,947.09' | L77: '-543,925.11'
A78: 45440 | C78: 9542.55 | D78: 0 | E78: 7391.64 | G78: 2150.91 | K78: '-470,555.45' | L78: '-534,382.56'
A79: 45471 | C79: 9542.55 | D79: 0 | E79: 7354.31 | G79: 2188.24 | K79: '-463,201.14' | L79: '-524,840.01'
A80: 45501 | C80: 9542.55 | D80: 0 | E80: 7458 | G80: 2084.55 | K80: '-455,743.14' | L80: '-515,297.46'
A81: 45522 | C81: 6083.85 | D81: 0 | H81: 6083.85 | K81: '-404,571.69' | L81: '-464,126.01'
A82: 45532 | C82: 8594.93 | D82: 0 | E82: 6478.84 | G82: 2116.09 | H82: 0 | K82: '-398,092.85' | L82: '-455,531.08'
A83: 45563 | C83: 8594.93 | D83: 0 | E83: 6519.47 | G83: 2075.46 | H83: 0 | K83: '-391,573.38' | L83: '-446,936.15'
A84: 45593 | C84: 8594.93 | D84: 0 | E84: 6619.31 | G84: 1975.62 | H84: 0 | K84: '-384,954.07' | L84: '-438,341.22'
A85: 45624 | C85: 8594.93 | D85: 0 | E85: 6587.96 | G85: 2006.97 | H85: 0 | K85: '-378,366.11' | L85: '-429,746.29'
A86: 45654 | C86: 8594.93 | D86: 0 | E86: 6685.94 | G86: 1908.99 | H86: 0 | K86: '-371,680.17' | L86: '-421,151.36'
A87: 45685 | C87: 8594.93 | D87: 0 | E87: 6657.17 | G87: 1937.76 | H87: 0 | K87: '-365,023.00' | L87: '-412,556.43'
A88: 45716 | C88: 8594.93 | D88: 0 | E88: 6691.88 | G88: 1903.05 | H88: 0 | K88: '-358,331.12' | L88: '-403,961.50'
A89: 45744 | C89: 8594.93 | D89: 0 | E89: 6907.55 | G89: 1687.38 | H89: 0 | K89: '-351,423.57' | L89: '-395,366.57'
A90: 45775 | C90: 8594.93 | D90: 0 | E90: 6762.78 | G90: 1832.15 | H90: 0 | K90: '-344,660.79' | L90: '-386,771.64'
A91: 45805 | C91: 8594.93 | D91: 0 | E91: 6856 | G91: 1738.93 | H91: 0 | K91: '-337,804.79' | L91: '-378,176.71'
A92: 45836 | C92: 8594.93 | D92: 0 | E92: 6833.78 | G92: 1761.15 | H92: 0 | K92: '-330,971.01' | L92: '-369,581.78'
A93: 45866 | C93: 8594.93 | D93: 0 | E93: 6925.07 | G93: 1669.86 | H93: 0 | K93: '-324,045.94' | L93: '-360,986.85'
... A134: 47115 | C134: 8594.93 | D134: 0 | E134: 8508.86 | G134: 86.07 | H134: 0 | K134: '-8,550.14' | L134: '-8,594.72'
A135: 47146 | C135: 8594.72 | D135: 0 | E135: 8550.14 | G135: 44.58 | H135: 0 | K135: 0 | L135: 0

Sheet Day4 - Principal Dec - Term
A2: Original
A4: Payment Schedule | M4: Generated Date: 18-Aug-2024 16:17:24
A6: Date | B6: Defer Date | C6: Total Due | D6: Total Cap | E6: Principal | F6: Principal Profit | G6: REC Profit | H6: Charge | I6: Tax | J6: Total Pymt | K6: Outstanding | L6: O/S Principal + Profit
A7: 45320 | C7: 4600 | D7: 0 | E7: 400000 | H7: 4000 | I7: 600 | J7: 400000 | K7: -400000 | L7: -400000
A8: 45350 | C8: 12250.33 | D8: 0 | E8: 8962.66 | G8: 3287.67 | K8: -391037.34 | L8: -394325.01
A9: 45379 | C9: 12250.33 | D9: 0 | E9: 8366.74 | G9: 3883.59 | K9: -382670.6 | L9: -389841.86
A10: 45410 | C10: 12250.33 | D10: 0 | E10: 8187.73 | G10: 4062.6 | K10: -374482.87 | L10: -385716.73
A11: 45440 | C11: 12250.33 | D11: 0 | E11: 8402.9 | G11: 3847.43 | K11: -366079.97 | L11: -381161.26
A12: 45471 | C12: 12250.33 | D12: 0 | E12: 8363.86 | G12: 3886.47 | K12: -357716.11 | L12: -376683.87
A13: 45501 | C13: 12250.33 | D13: 0 | E13: 8575.16 | G13: 3675.17 | K13: -349140.95 | L13: -371783.88 | N13: 45522
A14: 45532 | C14: 12250.33 | D14: 0 | E14: 8543.7 | G14: 3706.63 | H14: 0 | K14: -340597.25 | L14: -359533.55
A15: 45563 | C15: 12250.33 | D15: 0 | E15: 8634.4 | G15: 3615.93 | H15: 0 | K15: -331962.85 | L15: -347283.22 | N15: Fee | O15: =SUM(G15:G17) -> 10456.93
A16: 45593 | C16: 12250.33 | D16: 0 | E16: 8839.75 | G16: 3410.58 | H16: 0 | K16: -323123.1 | L16: -335032.89 | N16: Principal | O16: =O17-O15 -> 63045.05
A17: 45624 | C17: 12250.33 | D17: 0 | E17: 8819.91 | G17: 3430.42 | H17: 0 | K17: -314303.19 | L17: -322782.56 | N17: 6 Installment | O17: =SUM(C14:C19) -> 73501.98
A18: 45654 | C18: 12250.33 | D18: 0 | E18: 9021.19 | G18: 3229.14 | H18: 0 | K18: -305282 | L18: -310532.23
A19: 45685 | C19: 12250.33 | D19: 0 | E19: 9009.32 | G19: 3241.01 | H19: 0 | K19: -296272.68 | L19: -298281.9
A20: 45716 | C20: 12250.33 | D20: 0 | E20: 9104.97 | G20: 3145.36 | H20: 0 | K20: -287167.71 | L20: -286031.57
A21: 45744 | C21: 12250.33 | D21: 0 | E21: 9496.67 | G21: 2753.66 | H21: 0 | K21: -277671.04 | L21: -273781.24
A22: 45775 | C22: 12250.33 | D22: 0 | E22: 9302.45 | G22: 2947.88 | H22: 0 | K22: -268368.59 | L22: -261530.91
A23: 45805 | C23: 12250.33 | D23: 0 | E23: 9493.12 | G23: 2757.21 | H23: 0 | K23: -258875.47 | L23: -249280.58
A24: 45836 | C24: 12250.33 | D24: 0 | E24: 9501.99 | G24: 2748.34 | H24: 0 | K24: -249373.48 | L24: -237030.25
A25: 45866 | C25: 12250.33 | D25: 0 | E25: 9688.27 | G25: 2562.06 | H25: 0 | K25: -239685.21 | L25: -224779.92
A26: 45897 | C26: 12250.33 | D26: 0 | E26: 9705.73 | G26: 2544.6 | H26: 0 | K26: -229979.48 | L26: -212529.59
A27: 45928 | C27: 12250.33 | D27: 0 | E27: 9808.77 | G27: 2441.56 | H27: 0 | K27: -220170.71 | L27: -200279.26
A28: 45958 | C28: 12250.33 | D28: 0 | E28: 9988.3 | G28: 2262.03 | H28: 0 | K28: -210182.41 | L28: -188028.93
A29: 45989 | C29: 12250.33 | D29: 0 | E29: 10018.94 | G29: 2231.39 | H29: 0 | K29: -200163.47 | L29: -175778.6
... A47: 46535 | C47: 12250.47 | D47: 0 | E47: 12125.9 | G47: 124.57 | H47: 0 | K47: 0 | L47: 44727.48
A50: Principal Decrease - Term Reduction
A52: Payment Schedule | M52: Generated Date: 18-Aug-2024 16:28:08
A54: Date | B54: Defer Date | C54: Total Due | D54: Total Cap | E54: Principal | F54: Principal Profit | G54: REC Profit | H54: Charge | I54: Tax | J54: Total Pymt | K54: Outstanding | L54: O/S Principal + Profit
A55: 45320 | C55: 4600 | D55: 0 | E55: 400000 | H55: 4000 | I55: 600 | J55: 400000 | K55: '-400,000.00' | L55: '-400,000.00'
A56: 45350 | C56: 12250.33 | D56: 0 | E56: 8962.66 | G56: 3287.67 | K56: '-391,037.34' | L56: '-394,325.01'
A57: 45379 | C57: 12250.33 | D57: 0 | E57: 8366.74 | G57: 3883.59 | K57: '-382,670.60' | L57: '-389,841.86'
A58: 45410 | C58: 12250.33 | D58: 0 | E58: 8187.73 | G58: 4062.6 | K58: '-374,482.87' | L58: '-385,716.73'
A59: 45440 | C59: 12250.33 | D59: 0 | E59: 8402.9 | G59: 3847.43 | K59: '-366,079.97' | L59: '-381,161.26'
A60: 45471 | C60: 12250.33 | D60: 0 | E60: 8363.86 | G60: 3886.47 | K60: '-357,716.11' | L60: '-376,683.87'
A61: 45501 | C61: 12250.33 | D61: 0 | E61: 8575.16 | G61: 3675.17 | K61: '-349,140.95' | L61: '-371,783.88'
A62: 45522 | C62: 10456.93 | D62: 0 | H62: 10456.93 | K62: '-286,095.90' | L62: '-308,738.83'
A63: 45532 | C63: 12250.33 | D63: 0 | E63: 8334.24 | G63: 3916.09 | H63: 0 | K63: '-277,761.66' | L63: '-296,488.50'
A64: 45563 | C64: 12250.33 | D64: 0 | E64: 8021.27 | G64: 4229.06 | H64: 0 | K64: '-269,740.39' | L64: '-284,238.17'
A65: 45593 | C65: 12250.33 | D65: 0 | E65: 8275.88 | G65: 3974.45 | H65: 0 | K65: '-261,464.51' | L65: '-271,987.84'
A66: 45624 | C66: 12250.33 | D66: 0 | E66: 8269.41 | G66: 3980.92 | H66: 0 | K66: '-253,195.10' | L66: '-259,737.51'
A67: 45654 | C67: 12250.33 | D67: 0 | E67: 8519.67 | G67: 3730.66 | H67: 0 | K67: '-244,675.43' | L67: '-247,487.18'
A68: 45685 | C68: 12250.33 | D68: 0 | E68: 8525.03 | G68: 3725.3 | H68: 0 | K68: '-236,150.40' | L68: '-235,236.85'
A69: 45716 | C69: 12250.33 | D69: 0 | E69: 8654.82 | G69: 3595.51 | H69: 0 | K69: '-227,495.58' | L69: '-222,986.52'
A70: 45744 | C70: 12250.33 | D70: 0 | E70: 9121.8 | G70: 3128.53 | H70: 0 | K70: '-218,373.78' | L70: '-210,736.19'
A71: 45775 | C71: 12250.33 | D71: 0 | E71: 8925.48 | G71: 3324.85 | H71: 0 | K71: '-209,448.30' | L71: '-198,485.86'
A72: 45805 | C72: 12250.33 | D72: 0 | E72: 9164.25 | G72: 3086.08 | H72: 0 | K72: '-200,284.05' | L72: '-186,235.53'
A73: 45836 | C73: 12250.33 | D73: 0 | E73: 9200.91 | G73: 3049.42 | H73: 0 | K73: '-191,083.14' | L73: '-173,985.20'
A74: 45866 | C74: 12250.33 | D74: 0 | E74: 9434.85 | G74: 2815.48 | H74: 0 | K74: '-181,648.29' | L74: '-161,734.87'
... A87: 46262 | C87: 12250.33 | D87: 0 | E87: 11376.74 | G87: 873.59 | H87: 0 | K87: '-45,999.91' | L87: '-2,480.58'
A88: 46293 | C88: 12250.33 | D88: 0 | E88: 11549.96 | G88: 700.37 | H88: 0 | K88: '-34,449.95' | L88: 9769.75
A89: 46323 | C89: 34957.73 | D89: 0 | E89: 34449.95 | G89: 507.78 | H89: 0 | K89: 0 | L89: 44727.48

Sheet DayN- APR with Flat Rate
A1: Simulation Details
A2: System Date | B2: 45323
A3: Amount | B3: 200000 | C3: Profit Start Date | D3: 45325
A4: Flat Rate | B4: 0.12 | C4: Total Profit | D4: =SUM(F13:F24) -> 23671.23
A5: Term | B5: 1Y | C5: Instalment Amount | D5: =C13 -> 18639.27
A6: 1st Instalment Date | B6: 45350 | C6: APR | D6: 0.270465
A7: Last Intalment Date | B7: 45685 | C7: IRR | D7: =G13 -> 0.21846564
A8: Simulation Reference | B8: AASIM24032MKW7FWGV | C8: # on Accrual Days | D8: =+B7-A12 -> 360 | E8: Arrangement
A11: Date | B11: Defer Date | C11: Total Due | D11: Total Cap | E11: Principal | F11: Principal Profit | G11: REC Profit | H11: Charge | I11: Tax | J11: Total Pymt | K11: Outstanding
A12: 45325 | C12: 2300 | D12: 0 | E12: 200000 | H12: 2000 | I12: 300 | J12: 200000 | K12: -200000
A13: 45350 | B13: =A13-A12 -> 25 | C13: 18639.27 | D13: 0 | E13: 15646.59 | F13: 2992.68 | G13: =(F13/B13*365)/-K12 -> 0.21846564 | H13: 0 | K13: -184353.41
A14: 45379 | B14: =A14-A13 -> 29 | C14: 18639.27 | D14: 0 | E14: 15439.35 | F14: 3199.92 | G14: =(F14/B14*365)/-K13 -> 0.21846547 | H14: 0 | K14: -168914.06
A15: 45410 | B15: =A15-A14 -> 31 | C15: 18639.27 | D15: 0 | E15: 15505.14 | F15: 3134.13 | G15: =(F15/B15*365)/-K14 -> 0.21846526 | H15: 0 | K15: -153408.92
A16: 45440 | B16: =A16-A15 -> 30 | C16: 18639.27 | D16: 0 | E16: 15884.65 | F16: 2754.62 | G16: =(F16/B16*365)/-K15 -> 0.21846541 | H16: 0 | K16: -137524.27
A17: 45471 | B17: =A17-A16 -> 31 | C17: 18639.27 | D17: 0 | E17: 16087.56 | F17: 2551.71 | G17: =(F17/B17*365)/-K16 -> 0.21846564 | H17: 0 | K17: -121436.71
A18: 45501 | B18: =A18-A17 -> 30 | C18: 18639.27 | D18: 0 | E18: 16458.74 | F18: 2180.53 | G18: =(F18/B18*365)/-K17 -> 0.21846591 | H18: 0 | K18: -104977.97
A19: 45532 | B19: =A19-A18 -> 31 | C19: 18639.27 | D19: 0 | E19: 16691.45 | F19: 1947.82 | G19: =(F19/B19*365)/-K18 -> 0.21846498 | H19: 0 | K19: -88286.52
A20: 45563 | B20: =A20-A19 -> 31 | C20: 18639.27 | D20: 0 | E20: 17001.15 | F20: 1638.12 | G20: =(F20/B20*365)/-K19 -> 0.21846531 | H20: 0 | K20: -71285.37
A21: 45593 | B21: =A21-A20 -> 30 | C21: 18639.27 | D21: 0 | E21: 17359.27 | F21: 1280 | G21: =(F21/B21*365)/-K20 -> 0.21846465 | H21: 0 | K21: -53926.1
A22: 45624 | B22: =A22-A21 -> 31 | C22: 18639.27 | D22: 0 | E22: 17638.69 | F22: 1000.58 | G22: =(F22/B22*365)/-K21 -> 0.21846606 | H22: 0 | K22: -36287.41
A23: 45654 | B23: =A23-A22 -> 30 | C23: 18639.27 | D23: 0 | E23: 17987.69 | F23: 651.58 | G23: =(F23/B23*365)/-K22 -> 0.21846576 | H23: 0 | K23: -18299.72
A24: 45685 | B24: =A24-A23 -> 31 | C24: 18639.26 | D24: 0 | E24: 18299.72 | F24: 339.54 | G24: =(F24/B24*365)/-K23 -> 0.21846289 | H24: 0 | K24: 0
E25: =SUM(E13:E24) -> 200000 | F25: =SUM(F13:F24) -> 23671.23 | H25: =SUM(H12:H24) -> 2000 | I25: =SUM(I12:I24) -> 300
A27: Arrangement Details
A28: System Date | B28: 45323
A29: Amount | B29: 200000 | C29: Profit Start Date | D29: 45323
A30: Flat Rate | B30: =(G50/D34*365)/B29 -> 0.119337 | C30: Total Profit | D30: =SUM(G38:G49) -> 23671.23
A31: Term | B31: 1Y | C31: Instalment Amount | D31: =C38 -> 18639.27
A32: 1st Instalment Date | B32: 45350 | C32: APR | D32: 0.26721
A33: Last Intalment Date | B33: 45685 | C33: IRR | D33: =F38 -> 0.21612731
A34: Arrangement Reference | B34: AA24032X111V | C34: # on Accrual Days | D34: =+B33-D29 -> 362 | F34: AASIM24032TC0MXHSX
A36: Date | B36: Defer Date | C36: Total Due | D36: Total Cap | E36: Principal | F36: Principal Profit | G36: REC Profit | H36: Charge | I36: Tax | J36: Total Pymt | K36: Outstanding
A37: 45323 | C37: 2300 | D37: 0 | E37: 200000 | H37: 2000 | I37: 300 | J37: 200000 | K37: -200000
A38: 45350 | B38: =A38-A37 -> 27 | C38: 18639.27 | D38: 0 | E38: 15441.77 | F38: =(G38/B38*365)/-K37 -> 0.21612731 | G38: 3197.5 | H38: 0 | K38: -184558.23
A39: 45379 | B39: =A39-A38 -> 29 | C39: 18639.27 | D39: 0 | E39: 15470.08 | F39: =(G39/B39*365)/-K38 -> 0.21612735 | G39: 3169.19 | H39: 0 | K39: -169088.15
A40: 45410 | B40: =A40-A39 -> 31 | C40: 18639.27 | D40: 0 | E40: 15535.48 | F40: =(G40/B40*365)/-K39 -> 0.21612765 | G40: 3103.79 | H40: 0 | K40: -153552.67
A41: 45440 | B41: =A41-A40 -> 30 | C41: 18639.27 | D41: 0 | E41: 15911.58 | F41: =(G41/B41*365)/-K40 -> 0.21612711 | G41: 2727.69 | H41: 0 | K41: -137641.09
A42: 45471 | B42: =A42-A41 -> 31 | C42: 18639.27 | D42: 0 | E42: 16112.73 | F42: =(G42/B42*365)/-K41 -> 0.21612711 | G42: 2526.54 | H42: 0 | K42: -121528.36
A43: 45501 | B43: =A43-A42 -> 30 | C43: 18639.27 | D43: 0 | E43: 16480.45 | F43: =(G43/B43*365)/-K42 -> 0.21612769 | G43: 2158.82 | H43: 0 | K43: -105047.91
A44: 45532 | B44: =A44-A43 -> 31 | C44: 18639.27 | D44: 0 | E44: 16711.01 | F44: =(G44/B44*365)/-K43 -> 0.21612716 | G44: 1928.26 | H44: 0 | K44: -88336.9
A45: 45563 | B45: =A45-A44 -> 31 | C45: 18639.27 | D45: 0 | E45: 17017.76 | F45: =(G45/B45*365)/-K44 -> 0.21612681 | G45: 1621.51 | H45: 0 | K45: -71319.14
A46: 45593 | B46: =A46-A45 -> 30 | C46: 18639.27 | D46: 0 | E46: 17372.36 | F46: =(G46/B46*365)/-K45 -> 0.21612812 | G46: 1266.91 | H46: 0 | K46: -53946.78
A47: 45624 | B47: =A47-A46 -> 31 | C47: 18639.27 | D47: 0 | E47: 17649.02 | F47: =(G47/B47*365)/-K46 -> 0.21612773 | G47: 990.25 | H47: 0 | K47: -36297.76
A48: 45654 | B48: =A48-A47 -> 30 | C48: 18639.27 | D48: 0 | E48: 17994.48 | F48: =(G48/B48*365)/-K47 -> 0.21612752 | G48: 644.79 | H48: 0 | K48: -18303.28
A49: 45685 | B49: =A49-A48 -> 31 | C49: 18639.26 | D49: 0 | E49: 18303.28 | F49: =(G49/B49*365)/-K48 -> 0.21613031 | G49: 335.98 | H49: 0 | K49: 0
B50: =SUM(B38:B49) -> 362 | E50: =SUM(E38:E49) -> 200000 | G50: =SUM(G38:G49) -> 23671.23
A52: Variance Analysis | B52: Offer Letter | C52: Finance Arrangement | D52: Difference
A53: Profit Start Date | B53: =+D3 -> 45325 | C53: =+D29 -> 45323
A54: Profit Amount | B54: =D4 -> 23671.23 | C54: =D30 -> 23671.23 | D54: =+C54-B54 -> 0
A55: IRR | B55: =+D7 -> 0.21846564 | C55: =+D33 -> 0.21612731 | D55: =+C55-B55 -> -0.0023383252
A56: APR | B56: =+D6 -> 0.270465 | C56: =+D32 -> 0.26721 | D56: =C56-B56 -> -0.003255
A57: Flat Rate | B57: =B4 -> 0.12 | C57: =B30 -> 0.119337 | D57: =C57-B57 -> -0.00066299793

Sheet DayN - Proposed Acc Entries
A6: Offer Letter | C6: Purchase -
D7: Buy Broker
A10: Purchase Stage
A11: Stage | B11: Debit/Credit | C11: Accounting Entries | D11: Description | E11: Core/ Customized | F11: Account Reflection
A12: Offer Acceptance | B12: DR | C12: Inventory - IA | D12: Internal Account | E12: -10000 | H12: Finance Amount | J12: 10000
B13: CR | C13: Buy Broker's account | D13: Internal Account | E13: =-E12 -> 10000 | H13: Admin Fee 1% | J13: =J12*1% -> 100
B14: DR | C14: Buy Broker's account | D14: Internal Account | E14: =+E12 -> -10000
B15: CR | C15: TA - Bank Account | D15: Nostro Account | E15: =+E13 -> 10000
A16: Status - Request | B16: DR | C16: No Accounting Entry | G16: On Request
B17: CR
A18: Status - Approval | B18: DR | C18: GIT | D18: Goods in Transit | E18: =-J12 -> -10000 | F18: On Balance Sheet | G18: On Spot | H18: VAT | J18: =J13*15% -> 15
B19: CR | C19: Purchase Order | D19: Purchase Order | E19: =-E18 -> 10000 | F19: On Balance Sheet | H19: Net Finance Amount | J19: =J12-J13-J18 -> 9885
A20: Status - Purchase | B20: DR | C20: Purchase Order | D20: Purchase Order | E20: =-E19 -> -10000 | F20: On Balance Sheet
B21: CR | C21: GIT | D21: Goods in Transit | E21: =-E19 -> -10000 | F21: On Balance Sheet | H21: Profit Amount | I21: 0.12 | J21: =J12*I21 -> 1200
B22: DR | C22: Purchases | D22: Purchase | E22: =-J12 -> -10000 | F22: On Balance Sheet
B23: CR | C23: Inventory - IA | D23: Internal Account | E23: =-E22 -> 10000 | F23: On Balance Sheet
A24: Finance / Sale | B24: DR | C24: CURACCOUNT | D24: AA Arrangeement - ACCOUNT | E24: =-J12 -> -10000 | F24: On Balance Sheet
B25: CR | C25: Purchases | D25: Purchase | E25: =-E22 -> 10000 | F25: On Balance Sheet
B26: DR | C26: RECDEFPFT | D26: Profit Receivable | E26: =-J21 -> -1200 | F26: On Balance Sheet
B27: CR | C27: ACCDEFPFT | D27: Unearned Accrued Profit | E27: =-E26 -> 1200 | F27: On Balance Sheet
A28: Admin Fee Due with VAT | B28: Dr | C28: DUEADMINFEE | D28: Admin Fee | E28: =-J13 -> -100
B29: Cr | C29: ACCADMINFEE | D29: Unamortise Admin Fee | E29: =-E28 -> 100
B30: Dr | C30: DUEVAT | D30: VAT | E30: =-J18 -> -15
B31: Cr | C31: VAT Payable | E31: =-E30 -> 15
A32: Brokerage Fee | B32: Dr | C32: BROKERFEE - PL | D32: Brokerage Fee Expense | E32: 50
B33: Cr | C33: Internal Payable | D33: Brokerage Fee Payable | E33: =-E32 -> -50
A34: Payment to Customer | B34: DR | C34: Sell Broker's Account | D34: Internal Account | E34: -10000 | F34: On Balance Sheet
B35: CR | C35: Customer's Account | D35: Disbursment/Repayment Account | E35: 10000 | F35: On Balance Sheet
A36: Broker Settlement (incase of different) | B36: DR | C36: Buy Broker's account | D36: Internal Account | E36: =-E23 -> -10000 | F36: On Balance Sheet
B37: CR | C37: Sell Broker's Account | D37: Internal Account | E37: =-E34 -> 10000 | F37: On Balance Sheet
A38: Recovery of Admin Fee & VAT | B38: Dr | C38: Customer's Account | D38: Disbursment/Repayment Account | E38: =E28 -> -100
B39: Cr | C39: DUEADMINFEE | D39: Admin Fee | E39: =-E28 -> 100
B40: Dr | C40: Customer's Account | D40: Disbursment/Repayment Account | E40: =E30 -> -15
B41: Cr | C41: DUEVAT | D41: VAT | E41: =-E30 -> 15
A42: Actual Repayment to Customer (Net of Financing) | B42: Dr | C42: Customer's Account | D42: Disbursment/Repayment Account | E42: =E35+E38+E40 -> 9885
B43: Cr | C43: BF Account | D43: Internal Account | E43: =-E42 -> -9885
B44: Dr | C44: BF Account | D44: Internal Account | E44: =E42 -> 9885
B45: Cr | C45: Customer Bank Account | D45: XYZ bank account- customer current account | E45: =E43 -> -9885
A46: Upfront Admin Fee By Customer | B46: Dr | C46: BF Account | D46: Internal Account | E46: =E38+E40 -> -115
B47: Cr | C47: Customer's Account | D47: Disbursment/Repayment Account | E47: =-E46 -> 115
A48: Actual Repayment to Customer (Full Financing) | B48: Dr | C48: Customer's Account | D48: Disbursment/Repayment Account | E48: =E35+E38+E40+E47 -> 10000
B49: Cr | C49: BF Account | D49: Internal Account | E49: =-E48 -> -10000
B50: Dr | C50: BF Account | D50: Internal Account | E50: =E48 -> 10000
B51: Cr | C51: Customer Bank Account | D51: XYZ bank account- customer current account | E51: =E49 -> -10000
A53: Daily Realization Profit | B53: DR | C53: ACCDEFPFT | D53: Unearned Accrued Profit | E53: =-E27/365 -> -3.2876712 | F53: On Balance Sheet
B54: CR | C54: PL/ Income | D54: PL Category | E54: =-E53 -> 3.2876712 | F54: On Balance Sheet
A55: Daily Realization of Admin Fee | B55: DR | C55: ACCADMINFEE | D55: Unamortised Admin Fee | E55: =E28/365 -> -0.2739726
B56: CR | C56: PL/ Income | D56: PL Category | E56: =-E55 -> 0.2739726
A59: On Installment Date | B59: DR | C59: DUEACCOUNT | D59: Principal Portion due of Installment | E59: By Core | F59: On Balance Sheet
B60: CR | C60: CURACCOUNT | D60: AA Arrangement - ACCOUNT | E60: By Core | F60: On Balance Sheet
B61: DR | C61: DUEDEFPFT | D61: Profit Portion due of Installment | E61: By Core | F61: On Balance Sheet
B62: CR | C62: RECDEFPFT | D62: Profit Receivable | E62: By Core | F62: On Balance Sheet
A63: Repayment of Finance | B63: DR | C63: Customer's Account | D63: Disbursment/Repayment Account | E63: By Core | F63: On Balance Sheet
B64: CR | C64: DUEACCOUNT | D64: Principal portion of repayment | E64: By Core | F64: On Balance Sheet
B65: CR | C65: DUEDEFPFT | D65: Profit portion of repayment | E65: By Core | F65: On Balance Sheet
A66: Payoff | B66: DR | C66: Customer's Account | D66: Outstanding Principal Amount | E66: By Core | F66: On Balance Sheet
B67: CR | C67: CURACCOUNT | D67: Outstanding Principal Amount | E67: By Core | F67: On Balance Sheet
B68: DR | C68: Customer's Account | D68: Outstanding Profit Amount | E68: By Core | F68: On Balance Sheet
B69: CR | C69: RECDEFPFT | D69: Outstanding Profit Amount | E69: By Core | F69: On Balance Sheet
B70: DR | C70: ACCDEFPFT | D70: Unearned Accrued Profit Amount | E70: By Core | F70: On Balance Sheet
B71: CR | C71: PL/ Income | D71: Unearned Accrued Profit Amount | E71: By Core | F71: On Balance Sheet
B72: DR | C72: PL/ Income | D72: With Bonus amount if applied | E72: By Core | F72: On Balance Sheet
B73: CR | C73: Customer's Account | D73: With Bonus amount if applied | E73: By Core | F73: On Balance Sheet
A76: Cancellation – Cooling Period
A77: Stage | B77: Debit/Credit | C77: Accounting Entries | D77: Description | E77: Core/ Customized | F77: Account Reflection
A78: Reversal of Admin Fee | B78: DR | C78: PL/ Income | D78: Income GL | E78: By Core | F78: On Balance Sheet
B79: CR | C79: Customer A/c. | D79: Disbursment/Repayment Account | E79: By Core | F79: On Balance Sheet
B80: DR | C80: VAT Payable | D80: VAT Payable | E80: By Core | F80: On Balance Sheet
B81: CR | C81: Customer A/c. | D81: Disbursment/Repayment Account | E81: By Core | F81: On Balance Sheet
A82: Reversal of Profit | B82: DR | C82: PL/ Income | D82: PL Category | E82: By Core | F82: On Balance Sheet
B83: CR | C83: ACCDEFPFT | D83: Unearned Profit | E83: By Core | F83: On Balance Sheet
B84: DR | C84: ACCDEFPFT | D84: Unearned Profit | E84: By Core | F84: On Balance Sheet
B85: CR | C85: RECDEFPFT | D85: Profit Receivable | E85: By Core | F85: On Balance Sheet
A86: Principal Settlement | B86: DR | C86: Customer A/c. | D86: Disbursment/Repayment Account | E86: By Core | F86: On Balance Sheet
B87: CR | C87: CURACCOUNT | D87: Outstanding Principal Amount | E87: By Core | F87: On Balance Sheet
A90: Stage | B90: Debit/Credit | C90: Accounting Entries | D90: Description | E90: Core/ Customized | F90: Account Reflection
A91: Early Settlement | B91: DR | C91: DUEEARLYFEE | D91: Due Early Settlement Fee | E91: By Core | F91: On Balance Sheet
B92: CR | C92: PL/ Income | D92: PL Category | E92: By Core | F92: On Balance Sheet
B93: DR | C93: Customer A/c. | D93: Disbursment/Repayment Account | E93: By Core | F93: On Balance Sheet
B94: CR | C94: DUEACCOUNT | D94: Outstanding Principal Amount | E94: By Core | F94: On Balance Sheet
B95: DR | C95: Customer A/c. | D95: Disbursment/Repayment Account | E95: By Core | F95: On Balance Sheet
B96: CR | C96: DUEEARLYFEE | D96: Due Early Settlement Fee | E96: By Core | F96: On Balance Sheet
B97: DR | C97: Customer A/c. | D97: Disbursment/Repayment Account | E97: By Core | F97: On Balance Sheet
B98: CR | C98: RECDEFPFT | D98: Profit Receivable | E98: By Core | F98: On Balance Sheet
B99: DR | C99: ACCDEFPFT | D99: Unearned Profit | E99: By Core | F99: On Balance Sheet
B100: CR | C100: PL/ Income | D100: PL Category | E100: By Core | F100: On Balance Sheet
B101: DR | C101: PL/ Expense | D101: PL Category | E101: By Core | F101: On Balance Sheet
B102: CR | C102: PAYBONUS | D102: Bonus / Rebate | E102: By Core | F102: On Balance Sheet
B103: DR | C103: PAYBONUS | D103: Bonus / Rebate | E103: By Core | F103: On Balance Sheet
B104: CR | C104: Customer A/c. | D104: Disbursment/Repayment Account | E104: By Core | F104: On Balance Sheet
A107: Stage | B107: Debit/Credit | C107: Accounting Entries | D107: Description | E107: Core/ Customized | F107: Account Reflection
A108: Early Settlement - Patrial Settlement of 5 Instalments | B108: DR | C108: ACCDEFPFT | D108: Unearned Profit | E108: By Core | F108: On Balance Sheet
B109: CR | C109: PL/ Income | D109: PL Category | E109: By Core | F109: On Balance Sheet
B110: DR | C110: Customer A/c. | D110: Disbursment/Repayment Account | E110: By Core | F110: On Balance Sheet
B111: CR | C111: RECDEFPFT | D111: Profit Receivable | E111: By Core | F111: On Balance Sheet
B112: DR | C112: Customer A/c. | D112: Disbursment/Repayment Account | E112: By Core | F112: On Balance Sheet
B113: CR | C113: DUEACCOUNT | D113: Outstanding Principal Amount | E113: By Core | F113: On Balance Sheet
A114: Early Settlement - Patrial Settlement of 6 Instalments | B114: DR | C114: DUEPARTIALFEE | D114: Due Partial Settlement Fee | E114: By Core | F114: On Balance Sheet
B115: CR | C115: PL/ Income | D115: PL Category | E115: By Core | F115: On Balance Sheet
B116: DR | C116: Customer A/c. | D116: Disbursment/Repayment Account | E116: By Core | F116: On Balance Sheet
...

Sheet DayN - LOS - LMS Mapping Field
A1: Loan Application Fields | B1: Type | C1: Enabled | D1: Values | E1: Description | F1: Category | G1: Source | H1: LMS Required from LOS | I1: Technical Name | J1: Mapping | K1: Ref Fields | L1: Mandatory | M1: Built Name2
A2: Title | B2: NUMBER | C2: N | D2: 8 | E2: cg_salutation | F2: Personal Info | G2: LOS Session
A3: First Name | B3: VARCHAR2 | C3: Y | D3: 200 CHAR | E3: custfname | F3: Personal Info | G3: LOS Session
A4: Middle Name | B4: VARCHAR2 | C4: Y | D4: 200 CHAR | E4: custmname | F4: Personal Info | G4: LOS Session
A5: Third Name | B5: VARCHAR2 | C5: Y | D5: 200 CHAR | E5: custtname | F5: Personal Info | G5: LOS Session
A6: Family Name | B6: VARCHAR2 | C6: Y | D6: 200 CHAR | E6: custlname | F6: Personal Info | G6: LOS Session
A7: First Name (Arabic) | B7: VARCHAR2 | C7: Y | D7: 200 CHAR | E7: custfname_1 | F7: Personal Info | G7: LOS Session
A8: Middle Name (Arabic) | B8: VARCHAR2 | C8: Y | D8: 200 CHAR | E8: custmname_1 | F8: Personal Info | G8: LOS Session
A9: Third Name (Arabic) | B9: VARCHAR2 | C9: Y | D9: 200 CHAR | E9: custlname_1 | F9: Personal Info | G9: LOS Session
A10: Family Name (Arabic) | B10: VARCHAR2 | C10: Y | D10: 200 CHAR | E10: custfamilyname_1 | F10: Personal Info | G10: LOS Session
A11: Date of Birth | B11: DATE | C11: Y | E11: dobdoi | F11: Personal Info | G11: LOS Session
A12: Age | B12: NUMBER | C12: Y | D12: 3 | E12: age | F12: Personal Info | G12: LOS Session
A13: Nationality | B13: NUMBER | C13: Y | D13: 8 | E13: cg_nationalityid | F13: Personal Info | G13: LOS Session
A14: Gender | B14: VARCHAR2 | C14: Y | D14: 1 CHAR | E14: sex | F14: Personal Info | G14: LOS Session
A15: Social Status | B15: NUMBER | C15: Y | D15: 8 | E15: cg_maritalstatus | F15: Personal Info | G15: LOS Session
A16: Number Of Dependents | B16: NUMBER | C16: Y | D16: 8 | E16: no_of_dependents | F16: Personal Info | G16: LOS Session
A17: Type of Residence | B17: NUMBER | C17: Y | D17: 8 | E17: cg_residencetype | F17: Personal Info | G17: LOS Session
A18: National ID or Iqma Number | B18: NUMBER | C18: Y | D18: 8 | F18: Personal Info | G18: LOS Session
A19: ID type | B19: NUMBER | C19: Y | D19: 8 | E19: cg_idtype | F19: ID Info | G19: LOS Session
A20: ID Number | B20: VARCHAR2 | C20: Y | D20: 80 CHAR | E20: idnumber | F20: ID Info | G20: LOS Session
A21: ID Expiry Date | B21: DATE | C21: Y | E21: date_of_expiry | F21: ID Info | G21: LOS Session
A22: Mobile Phone | B22: NUMBER | C22: Y | D22: 10 | E22: mobile | F22: Contact Info | G22: LOS Session
A23: Mobile Phone 2 | B23: VARCHAR2 | C23: N | D23: 60 CHAR | E23: phone2 | F23: Contact Info | G23: LOS Session
A24: E-Mail | B24: VARCHAR2 | C24: Y | D24: 200 CHAR | E24: email | F24: Contact Info | G24: LOS Session
A25: Nature Of Employment | B25: NUMBER | C25: Y | D25: 8 | E25: cg_employmentstatus | F25: Employment Info | G25: LOS Session
A26: Employer Name | B26: VARCHAR2 | C26: Y | D26: 360 CHAR | E26: other_emp_busname | F26: Employment Info | G26: LOS Session
A27: Occupation/Position Job Title | B27: NUMBER | C27: N | D27: 8 | E27: cg_occupationjobtitle | F27: Employment Info | G27: LOS Session
A28: Joining Date | B28: DATE | C28: Y | E28: joiningdate | F28: Employment Info | G28: LOS Session
A29: Type of Sector | B29: NUMBER | C29: Y | D29: 8 | E29: cg_sectype | F29: Employment Info | G29: LOS Session
A30: Commercial Number | B30: VARCHAR2 | C30: N | D30: 20 CHAR | E30: commercialregistrationnumber | F30: Employment Info | G30: LOS Session
A31: Grade | F31: Employment Info | G31: LOS Session
A32: Customer Type (Civilian/Military | B32: NUMBER | C32: Y | D32: 8 | E32: cg_subsec | F32: Employment Info | G32: LOS Session
A33: Experience at Current Employment | B33: NUMBER | C33: Y | D33: 3 | E33: yearsatcurrempl | F33: Employment Info | G33: LOS Session
A34: Total Monthly Income | B34: NUMBER | C34: N | D34: 3 | E34: totalyrsinempl | F34: Employment Info | G34: LOS Session
A35: Basic Salary | B35: VARCHAR2 | C35: Y | D35: 10 | E35: basicsalary | F35: Employment Info | G35: LOS Session
A36: Housing Allowance | B36: VARCHAR2 | D36: 10 | E36: housingallowance | F36: Employment Info | G36: LOS Session
A37: Transfer Allowance | F37: Employment Info | G37: LOS Session
A38: Other Allowance | B38: VARCHAR2 | D38: 10 | E38: totalallownces | F38: Employment Info | G38: LOS Session
A39: Education expenses | B39: VARCHAR2 | D39: 10 | E39: totaldeductions | F39: Basic Obligation | G39: LOS Session
A40: Food expenses | F40: Basic Obligation | G40: LOS Session
A41: Housing expenses | F41: Basic Obligation | G41: LOS Session
A42: Electricity services | F42: Basic Obligation | G42: LOS Session
A43: Domestic workers’ wages | F43: Basic Obligation | G43: LOS Session
A44: Health care expenses | F44: Basic Obligation | G44: LOS Session
A45: Individual insurance expenses | F45: Basic Obligation | G45: LOS Session
A46: Transportation and communications expenses | F46: Basic Obligation | G46: LOS Session
A47: Any future costs | F47: Basic Obligation | G47: LOS Session
A48: Finance Info | F48: Finance Info | G48: LOS Session
A49: Requested Amount | B49: NUMBER | C49: Y | D49: (21,6) | E49: amountfinanced | F49: Finance Info | G49: LOS Session
A50: No. Of Installment | B50: NUMBER | C50: Y | D50: 3 | E50: tenure | F50: Finance Info | G50: LMS Session | H50: LOS
A51: Simulation ref | B51: CHAR | G51: LMS Session | H51: LOS
A52: customer | B52: NUMBER | G52: LMS Session | H52: LOS | I52: CUSTOMER | J52: IS.CONTRACT>CUSTOMER | K52: CORE | L52: Y | M52: SMB
A53: ISProduct | B53: NUMBER | G53: LMS Session | H53: Auto generated | I53: PRODUCT | J53: IS.CONTRACT>PRODUCT | K53: CORE | L53: N | M53: SMB
A54: status | B54: DROPDOWN | G54: LMS Session | H54: Auto generated | I54: STATUS | J54: IS.CONTRACT>STATUS | K54: CORE | L54: N | M54: SMB
A55: statusValueDate | B55: DATE | G55: LMS Session | H55: LOS | I55: STATUS.VALUE.DATE | J55: IS.CONTRACT>STATUS.VALUE.DATE | K55: CORE | L55: N | M55: SMB
A56: currency | B56: CHAR | G56: LMS Session | H56: Auto generated | I56: CURRENCY | J56: IS.CONTRACT>CURRENCY | K56: CORE | L56: Y | M56: SMB
A57: valueDate | B57: DATE | G57: LMS Session | H57: Auto generated | I57: VALUE.DATE | J57: IS.CONTRACT>VALUE.DATE | K57: CORE | L57: N | M57: SMB
A58: GB assetDescription | B58: CHAR | G58: LMS Session | H58: LOS | I58: DESCRIPTION | J58: IS.CONTRACT>DESCRIPTION | K58: CORE | L58: Y | M58: SMB
A59: requestAmount | B59: NUMBER | G59: LMS Session | H59: Auto generated | I59: REQUEST.AMOUNT | J59: IS.CONTRACT>REQUEST.AMOUNT | K59: CORE | L59: Y | M59: SMB
A60: commodity.1 | B60: CHAR | G60: LMS Session | H60: Auto generated | I60: COMMODITY | J60: IS.CONTRACT>COMMODITY | K60: CORE | L60: Y | M60: SMB
A61: buyBroker.1.1 | B61: NUMBER | G61: LMS Session | H61: Auto generated | I61: BUY.BROKER | J61: IS.CONTRACT>BUY.BROKER | K61: CORE | L61: N | M61: SMB
A62: buyBrokerAcct.1.1 | B62: NUMBER | G62: LMS Session | H62: Auto generated | I62: BUY.BROKER.ACCT | J62: IS.CONTRACT>BUY.BROKER.ACCT | K62: CORE | L62: N | M62: SMB
A63: buyBrokerWashAcct.1.1 | B63: CHAR | G63: LMS Session | H63: Auto generated | I63: BUY.BR.WASH.ACCT | J63: IS.CONTRACT>BUY.BR.WASH.ACCT | K63: CORE | L63: N | M63: SMB
... A73: applicationId | B73: CHAR | G73: LMS Session | H73: LOS | I73: SMB.APP.ID | J73: IS.CONTRACT>SMB.APP.ID | K73: LF | L73: Y | M73: SMB
A74: hyperPayRegId | G74: LMS Session | H74: LOS | I74: SMB.HYP.REG.ID | J74: IS.CONTRACT>SMB.HYP.REG.ID | K74: LF | L74: N | M74: SMB
A75: loanOfferDate | B75: DATE | G75: LMS Session | H75: Auto generated | I75: SMB.OFFER.DATE | J75: IS.CONTRACT>SMB.OFFER.DATE | K75: LF | L75: Y | M75: SMB
A76: VendorRefId | B76: CHAR | G76: LMS Session | H76: Auto generated | I76: SMB.EIGER.ID | J76: IS.CONTRACT>SMB.EIGER.ID | K76: LF | L76: Y | M76: TA
A77: documentId | B77: CHAR | G77: LMS Session | H77: LOS | I77: SMB.DOC.ID | J77: IS.CONTRACT>SMB.DOC.ID | K77: LF | L77: N | M77: SMB
A78: tenor | B78: CHAR | G78: LMS Session | H78: LOS | I78: SMB.TENOR | J78: IS.CONTRACT>SMB.TENOR | K78: LF | L78: Y | M78: SMB
A79: profitRate | B79: NUMBER | G79: LMS Session | H79: LOS | I79: SMB.PROFIT.RATE | J79: IS.CONTRACT>SMB.PROFIT.RATE | K79: LF | L79: N | M79: SMB
A80: AA Product | B80: CHAR | G80: LMS Session | H80: Auto generated | I80: SMB.INF.PRODUCT | J80: IS.CONTRACT>SMB.INF.PRODUCT | K80: LF | L80: Y | M80: SMB
A81: Commodity Broker | B81: CHAR | G81: LMS Session | H81: LOS | I81: SMB.COMM.BROKER | J81: IS.CONTRACT>SMB.COMM.BROKER | K81: LF | L81: Y | M81: SMB
A82: Simulated Arrangement Id | B82: CHAR | G82: LMS Session | H82: LOS | I82: ARRANGEMENT | J82: IS.CONTRACT>ARRANGEMENT | K82: CORE | L82: N | M82: SMB
A83: Simulation Refrence | B83: CHAR | G83: LMS Session | H83: LOS | I83: SIM.REF | J83: IS.CONTRACT>SIM.REF | K83: CORE | L83: Y | M83: SMB
A84: Dao | B84: NUMBER | G84: LMS Session | H84: LOS | I84: DAO | J84: IS.CONTRACT>DAO | K84: CORE | L84: N | M84: SMB
A85: Customer Bank Account | B85: NUMBER | G85: LMS Session | H85: LOS | I85: Not Available | J85: LOCAL FIELD REQUIRED | K85: LF | L85: Y | M85: TA
A86: Customer Bank Code | B86: CHAR | G86: LMS Session | H86: LOS | I86: Not Available | J86: LOCAL FIELD REQUIRED | K86: LF | L86: Y | M86: TA
... A101: brFeeTaxAmountFcy | B101: CHAR | G101: LMS Session | H101: Auto generated | I101: BR.FEE.TAX.AMT.FCY | J101: IS.CONTRACT>BR.FEE.TAX.AMT.FCY | K101: CORE | L101: N | M101: SMB
A102: Financing Type | B102: LOV | C102: Y | D102: LOV: New Loan Restructured Top-up Buy-Out | E102: Financing Type | F102: Finance Type | G102: LMS Session | H102: Auto generated | K102: CORE | L102: N | M102: SMB
A103: Old Arrangement Refrence | B103: CHAR | C103: Y | E103: Old Arrangement Refrence | F103: OldArrRef | G103: LMS Session | H103: Input Field | I103: BH.REST.ARR.ID | J103: IS.CONTRACT>BH.REST.ARR.ID | K103: CORE | L103: N | M103: SMB
A104: Buy-out Amount | B104: NUMBER | C104: Y | E104: Buy-out Amount | F104: Buy-outAmt | G104: LMS Session | H104: Input Field | K104: CORE | L104: N | M104: SMB
A105: Restrucutre Type | B105: LOV | C105: Y | D105: LOV: Principal Only Principal + Profit Top-up with Principal Top-up with Principal and Profit | E105: Restrucutre Type | F105: RestructureInfo | G105: LMS Session | H105: Auto generated | I105: BH.PFT.REST.TYPE | J105: IS.CONTRACT>BH.PFT.REST.TYPE | K105: CORE | L105: N | M105: SMB
A106: Top-up Type | B106: LOV | C106: Y | D106: LOV: Top-up with Principal Top-up with Principal and Profit | E106: Top-up Type | F106: TopupInfo | G106: LMS Session | H106: Auto generated | I106: BH.PFT.REST.TYPE | J106: IS.CONTRACT>BH.PFT.REST.TYPE | K106: CORE | L106: N | M106: SMB

Sheet DayN-File Upload
A1: ACCOUNT_NO | B1: CIF_ID | C1: TRAN_DT | D1: AMOUNT | E1: CONTRACT_NO | F1: reference for transaction | G1: RECEIVEDFROM | H1: Type
A2: Fransi bank | B2: 158170 | C2: 45535 | D2: 1600 | E2: TWQ0081815 | G2: Primary Applicant | H2: Direct Bank Transfer Payment
A3: SNB bank | B3: 158170 | C3: 45536 | D3: 1601 | E3: TWQ0081816 | G3: Insurance Payment for Total Loss | H3: SADAD
A4: Alinma bank | B4: 158170 | C4: 45537 | D4: 1602 | E4: TWQ0081817 | G4: Cancelled Contract Payment | H4: Credit Card (POS)
A5: GIB bank | B5: 158170 | C5: 45538 | D5: 1603 | E5: TWQ0081818 | G5: Payment from NPL Customers | H5: Debit Card (POS)
A6: AlBilad bank | B6: 158170 | C6: 45539 | D6: 1604 | E6: TWQ0081819 | G6: Early Loan Settlement Payment | H6: Credit Note Payment
A7: Saud british bank | B7: 158170 | C7: 45540 | D7: 1605 | E7: TWQ0081820 | G7: Court Payment | H7: Direct Cheque Payment
A8: ANB bank | B8: 158170 | C8: 45541 | D8: 1606 | E8: TWQ0081821 | G8: Third Parties Payment without Template
A9: SAIB bank | B9: 158170 | C9: 45542 | D9: 1607 | E9: TWQ0081822 | G9: Third Parties Payment with Template
A10: Alrajhi bank | B10: 158170 | C10: 45543 | D10: 1608 | E10: TWQ0081823 | G10: Insurance (Compensation)
A11: Riyad bank | B11: 158170 | C11: 45544 | D11: 1609 | E11: TWQ0081824 | G11: Auction
A12: Aljazira bank | B12: 158170 | C12: 45545 | D12: 1610 | E12: TWQ0081825
J14: NOTE: ALI TO SHARE THE PROCESS OF EB FILE UPLOAD

Sheet DayN-DefermentWith Overdue
A1: Pre-Deferment
A2: Date | B2: Total Due | C2: Total Cap | D2: Principal | E2: REC Profit | F2: Charge | G2: Tax | H2: Total Pymt | I2: Outstanding | J2: O/S Principal + Profit
A3: 45261 | B3: 0 | C3: 0 | D3: 12000000 | H3: 12000000 | I3: -12000000 | J3: -13223333
A4: 45292 | B4: 1101944.4 | C4: 0 | D4: 910889.61 | E4: 191054.83 | I4: -11089110 | J4: -12121389 | K4: overdue bills-AA240430Q2Q6
A5: 45323 | B5: 1101944.4 | C5: 0 | D5: 930909.36 | E5: 171035.08 | I5: -10158201 | J5: -11019444
A6: 45352 | B6: 1101944.4 | C6: 0 | D6: 955375.62 | E6: 146568.82 | I6: -9202825.4 | J6: -9917500
A7: 45383 | B7: 1101944.4 | C7: 0 | D7: 960002.85 | E7: 141941.59 | I7: -8242822.6 | J7: -8815555.6
A8: 45413 | B8: 1101944.4 | C8: 0 | D8: 978910.76 | E8: 123033.68 | I8: -7263911.8 | J8: -7713611.1
A9: 45444 | B9: 1101944.4 | C9: 0 | D9: 989908.06 | E9: 112036.38 | I9: -6274003.7 | J9: -6611666.7
A10: 45474 | B10: 1101944.4 | C10: 0 | D10: 1008297.7 | E10: 93646.78 | I10: -5265706.1 | J10: -5509722.2
A11: 45505 | B11: 1101944.4 | C11: 0 | D11: 1020727.8 | E11: 81216.66 | I11: -4244978.3 | J11: -4407777.8
A12: 45536 | B12: 1101944.4 | C12: 0 | D12: 1036471.2 | E12: 65473.26 | I12: -3208507.1 | J12: -3305833.4
A13: 45566 | B13: 1101944.4 | C13: 0 | D13: 1054053.8 | E13: 47890.69 | I13: -2154453.4 | J13: -2203888.9
A14: 45597 | B14: 1101944.4 | C14: 0 | D14: 1068714.8 | E14: 33229.64 | I14: -1085738.6 | J14: -1101944.5
A15: 45627 | B15: 1101944.5 | C15: 0 | D15: 1085738.6 | E15: 16205.92 | I15: 0 | J15: 0
D16: =SUM(D4:D15) -> 12000000 | E16: =SUM(E4:E15) -> 1223333.3
A17: Scenario1- Post- Overdue Deferment added in next instalement
A18: Date | B18: Total Due | C18: Total Cap | D18: Principal | E18: REC Profit | F18: Charge | G18: Tax | H18: Total Pymt | I18: Outstanding | J18: O/S Principal + Profit
A19: 45261 | B19: 0 | C19: 0 | D19: 12000000 | H19: 12000000 | I19: -12000000 | J19: -13223333
A20: 45352 | B20: 3305833.3 | C20: 0 | D20: 2770902.3 | E20: 534931 | I20: -9229097.7 | J20: -9917500
A21: 45383 | B21: 1101944.4 | C21: 0 | D21: 965116.49 | E21: 136827.95 | I21: -8263981.2 | J21: -8815555.6
A22: 45413 | B22: 1101944.4 | C22: 0 | D22: 983377.27 | E22: 118567.17 | I22: -7280603.9 | J22: -7713611.1
A23: 45444 | B23: 1101944.4 | C23: 0 | D23: 994004.3 | E23: 107940.14 | I23: -6286599.6 | J23: -6611666.7
A24: 45474 | B24: 1101944.4 | C24: 0 | D24: 1011747.7 | E24: 90196.76 | I24: -5274851.9 | J24: -5509722.2
A25: 45505 | B25: 1101944.4 | C25: 0 | D25: 1023741 | E25: 78203.44 | I25: -4251110.9 | J25: -4407777.8
A26: 45536 | B26: 1101944.4 | C26: 0 | D26: 1038918.7 | E26: 63025.75 | I26: -3212192.2 | J26: -3305833.4
A27: 45566 | B27: 1101944.4 | C27: 0 | D27: 1055857.6 | E27: 46086.81 | I27: -2156334.6 | J27: -2203888.9
A28: 45597 | B28: 1101944.4 | C28: 0 | D28: 1069975.2 | E28: 31969.2 | I28: -1086359.4 | J28: -1101944.5
A29: 45627 | B29: 1101944.5 | C29: 0 | D29: 1086359.4 | E29: 15585.11 | I29: 0 | J29: 0
D30: =SUM(D20:D29) -> 12000000 | E30: =SUM(E20:E29) -> 1223333.3
A31: Scenario-2 Post- Overdue Deferment Term Extended
A32: Date | B32: Total Due | C32: Total Cap | D32: Principal | E32: REC Profit | F32: Charge | G32: Tax | H32: Total Pymt | I32: Outstanding | J32: O/S Principal + Profit
A33: 45261 | B33: 0 | C33: 0 | D33: 12000000 | H33: 12000000 | I33: -12000000 | J33: -13223333
A34: 45352 | B34: 1101944.4 | C34: 0 | D34: 651808.61 | E34: 450135.83 | I34: -11348191 | J34: -12121389
A35: 45383 | B35: 1101944.4 | C35: 0 | D35: 973794.08 | E35: 128150.36 | I35: -10374397 | J35: -11019444
A36: 45413 | B36: 1101944.4 | C36: 0 | D36: 988569.88 | E36: 113374.56 | I36: -9385827.4 | J36: -9917500
A37: 45444 | B37: 1101944.4 | C37: 0 | D37: 995954.23 | E37: 105990.21 | I37: -8389873.2 | J37: -8815555.6
A38: 45474 | B38: 1101944.4 | C38: 0 | D38: 1010257.4 | E38: 91687.08 | I38: -7379615.8 | J38: -7713611.1
A39: 45505 | B39: 1101944.4 | C39: 0 | D39: 1018609.5 | E39: 83334.9 | I39: -6361006.3 | J39: -6611666.7
A40: 45536 | B40: 1101944.4 | C40: 0 | D40: 1030112.3 | E40: 71832.17 | I40: -5330894 | J40: -5509722.2
A41: 45566 | B41: 1101944.4 | C41: 0 | D41: 1043686.8 | E41: 58257.63 | I41: -4287207.2 | J41: -4407777.8
A42: 45597 | B42: 1101944.4 | C42: 0 | D42: 1053530.8 | E42: 48413.63 | I42: -3233676.4 | J42: -3305833.4
A43: 45627 | B43: 1101944.4 | C43: 0 | D43: 1066605.8 | E43: 35338.6 | I43: -2167070.6 | J43: -2203888.9
A44: 45658 | B44: 1101944.4 | C44: 0 | D44: 1077472.6 | E44: 24471.82 | I44: -1089597.9 | J44: -1101944.5
A45: 45689 | B45: 1101944.5 | C45: 0 | D45: 1089597.9 | E45: 12346.54 | I45: 0 | J45: 0
D46: =SUM(D34:D45) -> 12000000 | E46: =SUM(E34:E45) -> 1223333.3
A47: Accounting entries
A48: in this case backdated entries will be Debit Profit from expense and Debit current Principal Receivable. In both the cases Overdue item will be Credited with their respective heads,

Sheet SA Transact Grace Schedule
A2: Payment Schedule | M2: Generated Date: 14-Jan-2025 18:03:35 | S2: Excel APR | U2: Excel IRR
S3: =XIRR(S5:S35,A5:A35) -> 0.16154171 | U3: =IRR(U5:U41,0)*12 -> 0.15062271
A4: Date | B4: Defer Date | C4: Total Due | D4: Total Cap | E4: Principal | F4: Principal Profit | G4: REC Profit | H4: Charge | I4: Tax | J4: Total Pymt | K4: Outstanding | L4: O/S Principal + Profit
A5: 45341 | C5: 0 | D5: 0 | E5: 50000 | J5: 50000 | K5: -50000 | L5: -50000 | M5: T24 IRR | N5: Days | O5: Profit | P5: Accumulated Profit | Q5: Balance | R5: T24 APR | S5: =K5 -> -50000 | T5: 0 | U5: =+S5 -> -50000
A6: 45554 | B6: 210 | C6: 2166.67 | D6: 0 | E6: =C6-G6 -> 0 | G6: 2166.67 | H6: 0 | J6: 0 | K6: -50000 | L6: -47833.33 | M6: 0.15292664 | N6: 210 | O6: =-L5*M6/360*210 -> 4460.3603 | P6: =+O6 -> 4460.3603 | Q6: =P6-G6 -> 2293.6903 | R6: =E42 -> 0.161541 | S6: =+C6 -> 2166.67 | T6: 1 | U6: 0
A7: 45584 | B7: 30 | C7: 2166.67 | D7: 0 | E7: =C7-G7 -> 0 | G7: 2166.67 | H7: 0 | K7: -50000 | L7: -45666.66 | N7: 30 | O7: =-K6*M6/360*30 -> 637.19432 | P7: =+Q6+O7 -> 2930.8846 | Q7: =P7-G7 -> 764.21459 | S7: =+C7 -> 2166.67 | T7: 2 | U7: 0
A8: 45615 | B8: 30 | C8: 2166.67 | D8: 0 | E8: =C8-G8 -> 765.27 | G8: 1401.4 | H8: 0 | K8: -49234.73 | L8: -43499.99 | N8: 30 | O8: =-K7*M6/360*30 -> 637.19432 | P8: =+Q7+O8 -> 1401.4089 | Q8: =P8-G8 -> 0.0089135967 | S8: =+C8 -> 2166.67 | T8: 3 | U8: 0
A9: 45645 | B9: 30 | C9: 2166.67 | D9: 0 | E9: =C9-G9 -> 1539.2282 | G9: =-K8*$M$6/360*B9 -> 627.44181 | H9: 0 | K9: -47695.5 | L9: -41333.32 | S9: =+C9 -> 2166.67 | T9: 4 | U9: 0
A10: 45676 | B10: 30 | C10: 2166.67 | D10: 0 | E10: =C10-G10 -> 1558.844 | G10: =-K9*$M$6/360*B10 -> 607.82604 | H10: 0 | K10: -46136.66 | L10: -39166.65 | S10: =+C10 -> 2166.67 | T10: 5 | U10: 0
A11: 45707 | B11: 30 | C11: 2166.67 | D11: 0 | E11: =C11-G11 -> 1578.7096 | G11: =-K10*$M$6/360*B11 -> 587.96036 | H11: 0 | K11: -44557.95 | L11: -36999.98 | S11: =+C11 -> 2166.67 | T11: 6 | U11: 0
A12: 45735 | B12: 30 | C12: 2166.67 | D12: 0 | E12: =C12-G12 -> 1598.8285 | G12: =-K11*$M$6/360*B12 -> 567.84146 | H12: 0 | K12: -42959.12 | L12: -34833.31 | S12: =+C12 -> 2166.67 | T12: 7 | U12: =+S6 -> 2166.67
A13: 45766 | B13: 30 | C13: 2166.67 | D13: 0 | E13: =C13-G13 -> 1619.2039 | G13: =-K12*$M$6/360*B13 -> 547.46615 | H13: 0 | K13: -41339.92 | L13: -32666.64 | S13: =+C13 -> 2166.67 | T13: 8 | U13: =+S7 -> 2166.67
A14: 45796 | B14: 30 | C14: 2166.67 | D14: 0 | E14: =C14-G14 -> 1639.8388 | G14: =-K13*$M$6/360*B14 -> 526.83125 | H14: 0 | K14: -39700.08 | L14: -30499.97 | S14: =+C14 -> 2166.67 | T14: 9 | U14: =+S8 -> 2166.67
A15: 45827 | B15: 30 | C15: 2166.67 | D15: 0 | E15: =C15-G15 -> 1660.7367 | G15: =-K14*$M$6/360*B15 -> 505.93331 | H15: 0 | K15: -38039.34 | L15: -28333.3 | S15: =+C15 -> 2166.67 | T15: 10 | U15: =+S9 -> 2166.67
A16: 45857 | B16: 30 | C16: 2166.67 | D16: 0 | E16: =C16-G16 -> 1681.901 | G16: =-K15*$M$6/360*B16 -> 484.76903 | H16: 0 | K16: -36357.44 | L16: -26166.63 | S16: =+C16 -> 2166.67 | T16: 11 | U16: =+S10 -> 2166.67
A17: 45888 | B17: 30 | C17: 2166.67 | D17: 0 | E17: =C17-G17 -> 1703.3349 | G17: =-K16*$M$6/360*B17 -> 463.33509 | H17: 0 | K17: -34654.11 | L17: -23999.96 | S17: =+C17 -> 2166.67 | T17: 12 | U17: =+S11 -> 2166.67
A18: 45919 | B18: 30 | C18: 2166.67 | D18: 0 | E18: =C18-G18 -> 1725.042 | G18: =-K17*$M$6/360*B18 -> 441.62804 | H18: 0 | J18: 0 | K18: -32929.07 | L18: -21833.29 | S18: =+C18 -> 2166.67 | T18: 13 | U18: =+S12 -> 2166.67
A19: 45949 | B19: 30 | C19: 2166.67 | D19: 0 | E19: =C19-G19 -> 1747.0257 | G19: =-K18*$M$6/360*B19 -> 419.64433 | H19: 0 | K19: -31182.04 | L19: -19666.62 | S19: =+C19 -> 2166.67 | T19: 14 | U19: =+S13 -> 2166.67
A20: 45980 | B20: 30 | C20: 2166.67 | D20: 0 | E20: =C20-G20 -> 1769.2896 | G20: =-K19*$M$6/360*B20 -> 397.38038 | H20: 0 | K20: -29412.75 | L20: -17499.95 | S20: =+C20 -> 2166.67 | T20: 15 | U20: =+S14 -> 2166.67
A21: 46010 | B21: 30 | C21: 2166.67 | D21: 0 | E21: =C21-G21 -> 1791.8373 | G21: =-K20*$M$6/360*B21 -> 374.83275 | H21: 0 | K21: -27620.91 | L21: -15333.28 | S21: =+C21 -> 2166.67 | T21: 16 | U21: =+S15 -> 2166.67
A22: 46041 | B22: 30 | C22: 2166.67 | D22: 0 | E22: =C22-G22 -> 1814.6723 | G22: =-K21*$M$6/360*B22 -> 351.99774 | H22: 0 | K22: -25806.24 | L22: -13166.61 | S22: =+C22 -> 2166.67 | T22: 17 | U22: =+S16 -> 2166.67
A23: 46072 | B23: 30 | C23: 2166.67 | D23: 0 | E23: =C23-G23 -> 1837.7982 | G23: =-K22*$M$6/360*B23 -> 328.87179 | H23: 0 | J23: 0 | K23: -23968.44 | L23: -10999.94 | S23: =+C23 -> 2166.67 | T23: 18 | U23: =+S17 -> 2166.67
A24: 46100 | B24: 30 | C24: 2166.67 | D24: 0 | E24: =C24-G24 -> 1861.2189 | G24: =-K23*$M$6/360*B24 -> 305.45108 | H24: 0 | K24: -22107.22 | L24: -8833.27 | S24: =+C24 -> 2166.67 | T24: 19 | U24: =+S18 -> 2166.67
A25: 46131 | B25: 30 | C25: 2166.67 | D25: 0 | E25: =C25-G25 -> 1884.9381 | G25: =-K24*$M$6/360*B25 -> 281.7319 | H25: 0 | K25: -20222.28 | L25: -6666.6 | S25: =+C25 -> 2166.67 | T25: 20 | U25: =+S19 -> 2166.67
A26: 46161 | B26: 30 | C26: 2166.67 | D26: 0 | E26: =C26-G26 -> 1908.9596 | G26: =-K25*$M$6/360*B26 -> 257.71044 | H26: 0 | K26: -18313.32 | L26: -4499.93 | S26: =+C26 -> 2166.67 | T26: 21 | U26: =+S20 -> 2166.67
A27: 46192 | B27: 30 | C27: 2166.67 | D27: 0 | E27: =C27-G27 -> 1933.2871 | G27: =-K26*$M$6/360*B27 -> 233.38287 | H27: 0 | K27: -16380.03 | L27: -2333.26 | S27: =+C27 -> 2166.67 | T27: 22 | U27: =+S21 -> 2166.67
A28: 46222 | B28: 30 | C28: 2166.67 | D28: 0 | E28: =C28-G28 -> 1957.9248 | G28: =-K27*$M$6/360*B28 -> 208.74524 | H28: 0 | K28: -14422.11 | L28: -166.59 | S28: =+C28 -> 2166.67 | T28: 23 | U28: =+S22 -> 2166.67
A29: 46253 | B29: 30 | C29: 2166.67 | D29: 0 | E29: =C29-G29 -> 1982.8763 | G29: =-K28*$M$6/360*B29 -> 183.79373 | H29: 0 | K29: -12439.23 | L29: 2000.08 | S29: =+C29 -> 2166.67 | T29: 24 | U29: =+S23 -> 2166.67
A30: 46284 | B30: 30 | C30: 2166.67 | D30: 0 | E30: =C30-G30 -> 2008.1459 | G30: =-K29*$M$6/360*B30 -> 158.52413 | H30: 0 | K30: -10431.08 | L30: 4166.75 | S30: =+C30 -> 2166.67 | T30: 25 | U30: =+S24 -> 2166.67
A31: 46314 | B31: 30 | C31: 2166.67 | D31: 0 | E31: =C31-G31 -> 2033.7375 | G31: =-K30*$M$6/360*B31 -> 132.9325 | H31: 0 | K31: -8397.34 | L31: 6333.42 | S31: =+C31 -> 2166.67 | T31: 26 | U31: =+S25 -> 2166.67
A32: 46345 | B32: 30 | C32: 2166.67 | D32: 0 | E32: =C32-G32 -> 2059.6553 | G32: =-K31*$M$6/360*B32 -> 107.01475 | H32: 0 | K32: -6337.68 | L32: 8500.09 | S32: =+C32 -> 2166.67 | T32: 27 | U32: =+S26 -> 2166.67
A33: 46375 | B33: 30 | C33: 2166.67 | D33: 0 | E33: =C33-G33 -> 2085.9033 | G33: =-K32*$M$6/360*B33 -> 80.766674 | H33: 0 | K33: -4251.78 | L33: 10666.76 | S33: =+C33 -> 2166.67 | T33: 28 | U33: =+S27 -> 2166.67
A34: 46406 | B34: 30 | C34: 2166.67 | D34: 0 | E34: =C34-G34 -> 2112.4858 | G34: =-K33*$M$6/360*B34 -> 54.184202 | H34: 0 | K34: -2139.29 | L34: 12833.43 | S34: =+C34 -> 2166.67 | T34: 29 | U34: =+S28 -> 2166.67
A35: 46437 | B35: 30 | C35: 2166.57 | D35: 0 | E35: =C35-G35 -> 2139.3071 | G35: =-K34*$M$6/360*B35 -> 27.262869 | H35: 0 | K35: 0 | L35: 15000 | S35: =+C35 -> 2166.57 | T35: 30 | U35: =+S29 -> 2166.67
C36: =SUM(C6:C35) -> 65000 | E36: =SUM(E6:E35) -> 50000 | G36: =SUM(G6:G35) -> 15000 | T36: 31 | U36: =+S30 -> 2166.67
T37: 32 | U37: =+S31 -> 2166.67
T38: 33 | U38: =+S32 -> 2166.67
D39: TA | E39: SA | T39: 34 | U39: =+S33 -> 2166.67
C40: Profit | D40: 15000 | E40: 15000 | T40: 35 | U40: =+S34 -> 2166.67
C41: Installment | D41: 2166.67 | E41: 2166.67 | T41: 36 | U41: =+S35 -> 2166.57
C42: APR | D42: 0.2469 | E42: 0.161541
C43: IRR | D43: 0.2141 | E43: 0.1529

Sheet VAT e-invoice temp

Sheet 513744

Sheet financing department pending 
A1: Twark product pending isuees
A2: cancelation Process | B2: There are 2 types of cancellation
B3: 1-after disbursement the contract and the financed amount not transferred to customer in this case just, we make (cancel contract maker and cancel contract checker) and the impact in GL is disbursement entries reversed.
B5: 2- after disbursement the contract and the financed amount transferred to customer in this case there are procedures form central bank we have to follow it:
B6: A-customer have to return the financed amount to the company.
B7: B- confession from the customer he want to cancel the contract and he return the amount to our bank account.
B8: C-bank account statement from the customer to check the financed amount movement in his account iif the customer use the amount or transfer part or whole of amount in this case we inform him he have to close the contract by early termination but if there isn’t any movement for the financed amount just we transfer the amount to him then he immediately return the amount to the company in this case we have to cancel the contract and the impact in GL disbursement entries reversed.
A9: Write off | B9: 1. The total outstanding will not be rested.
B10: 2. You can capture a payment after writ off and it will be deducted from the total outstanding but hase aspecific GL indector like attched below.
B11: 3. DPD will keep increasing and assigned to a collector.
B12: 4. The status will appear as "Write off" and it will not be included in the portfolio report.
A13: Write off GL
A14: Account | B14: GL impact | C14: Financial details impact
A15: Provision - Doubtful Debts | B15: DR (principal total outstanding amount) | C15: The total outstanding will not be rested.
A16: Deferred Rev-Interes | B16: DR (Rev-Interes amount)
A17: Account Receivable | B17: CR (total outstanding amount)
A19: bank GL | B19: DR (amount paid after write off ) | C19: reflect in decreasing outstanding balance by amount paid
A20: Bad Debts Recoveries | B20: CR (amount paid after write off )
A21: Restructure | B21: reschedulement there are several steps: -request from customer for reschdulment current contract with collection department -check the eligibility for the customer to restructure by credit team. -if the customer is elgibale creat new twrek contract with its all stages and this new contract financed amount will be (prinple amount+overdues amount for the current contract). -relate reschedule checker stage for old contract by acceptance from customer in new contract . -after sign the new contract and approve the promissory note GL for new contract is disbursed. -Restructure entries for old contarct is disbursed.
A30: Restructure GL
A31: New contract | B31: New contract | C31: DR | D31: CR
A32: Purchase of New Asset_2 | B32: Inventory | C32: 24900
A33: Purchase of New Asset_2 | B33: A/c Payable | D33: 24900
A34: commodity | B34: A/c Payable | D34: 24900
A35: commodity | B35: Account Recievable | C35: 24900
A36: commodity | B36: Account Recievable | D36: 24900
A37: commodity | B37: Ashton vendor | C37: 24900
A38: Disbursement | B38: Inventory | D38: 24900
A39: Disbursement | B39: Deferred Rev - Interest | D39: 26144.99
A40: Disbursement | B40: Account Recievable | C40: 26144.99
A41: Disbursement | B41: Account Recievable | C41: 24900
A42: Admin fees | B42: Output VAT 15% for domestic | D42: 37.35
A43: Admin fees | B43: Deferred Revenue-Admin Fees | D43: 249
A44: Admin fees | B44: Account Recievable | C44: 249
A45: Admin fees | B45: Account Recievable | C45: 37.35
A46: NORMAL - Rental Payment | B46: Account Recievable | D46: 24900
A47: NORMAL - Rental Payment | B47: Sell Broker's Account | C47: 24900
A48: buy and sell broker account | B48: Buy Broker's Account | D48: 24900
A49: buy and sell broker account | B49: Sell Broker's Account | C49: 24900
A51: REFUND - Refund | B51: clearing account (in case of restructure in new twrek contract no financed amount transferred it closed current contract) | D51: 24613.65
A52: REFUND - Refund | B52: Account Recievable | C52: 24613.65
B53: old contract
A54: Restructure | B54: clearing account | C54: 24613.65
A55: Restructure | B55: Account Recievable | D55: 24613.65
A56: manuall process for twrek | B56: in this case we need screen to review the transactions before proceed transfer the financed amount to customer account by refund funcution. - after we finsh all procedures (Purchase of New Asset_commodity_Credit customer balance _admin fees deduction) customer balance will be credit with 24613.65(financed amount) we will manully transfer this amount to customer bank account (IPAN NO) then reflect in GL DR customer balance by same amount after trasfer (refund function).
A59: GL manuall process for twrek | B59: GL name | C59: DR | D59: CR
A60: Purchase of New Asset_ | B60: Inventory | C60: 24900
A61: Purchase of New Asset_ | B61: A/c Payable | D61: 24900
A62: commodity | B62: A/c Payable | D62: 24900
A63: commodity | B63: Account Recievable | C63: 24900
A64: commodity | B64: Account Recievable | D64: 24900
A65: commodity | B65: Ashton vendor | C65: 24900
A66: Disbursement | B66: Inventory | D66: 24900
A67: Disbursement | B67: Deferred Rev - Interest | D67: 26144.99
A68: Disbursement | B68: Account Recievable | C68: 26144.99
A69: Disbursement | B69: Account Recievable | C69: 24900
A70: Admin fees | B70: Output VAT 15% for domestic | D70: 37.35
A71: Admin fees | B71: Deferred Revenue-Admin Fees | D71: 249
A72: Admin fees | B72: Account Recievable | C72: 249
A73: Admin fees | B73: Account Recievable | C73: 37.35
A74: Credit customer balance | B74: Account Recievable | D74: 24900
A75: Credit customer balance | B75: Sell Broker's Account | C75: 24900
B76: Buy Broker's Account | D76: 24900
B77: Sell Broker's Account | C77: 24900
A79: REFUND in case not integration with bank this will made manullay by refund function | B79: 1103310542 - Gulf International Bank Tamweel 20000001232-O/C | D79: 24613.65
A80: REFUND in case not integration with bank this will made manullay by refund function | B80: 1104000001 - Account Recievable | C80: 24613.65
A82: after we finsh all procedures (Purchase of New Asset_commodity_Credit customer balance _admin fees deduction) customer balance will be credit with 24613.65(financed amount) we will manully transfer this amount to customer bank account (IPAN NO) then reflect in GL DR customer balance by same amount after trasfer (refund function)
A85: Example based on T24
A86: Status - Approval | B86: GIT | C86: Goods in Transit | D86: -10000
B87: Purchase Order | C87: Purchase Order | D87: 10000
A88: Status - Purchase | B88: Purchase Order | C88: Purchase Order | D88: 10000
B89: GIT | C89: Goods in Transit | D89: -10000
B90: Purchases | C90: Purchase | D90: -10000
B91: Buy Broker's account | C91: Internal Account | D91: 10000
A92: Finance / Sale | B92: CURACCOUNT | C92: AA Arrangeement - ACCOUNT | D92: -10000
B93: Purchases | C93: Purchase | D93: 10000
B94: RECDEFPFT | C94: Profit Receivable | D94: -1200
B95: ACCDEFPFT | C95: Unearned Accrued Profit | D95: 1200
A96: Admin Fee Due with VAT | B96: DUEADMINFEE | C96: Admin Fee | D96: -100
B97: ACCADMINFEE | C97: Unamortise Admin Fee | D97: 100
B98: DUEVAT | C98: VAT Receivable | D98: -15
B99: VAT Payable | D99: 15
A100: Payment to Customer | B100: Sell Broker's Account | C100: Internal Account | D100: -10000
B101: Customer's Account | C101: Disbursment/Repayment Account | D101: 10000
A102: Broker Settlement (incase of different) | B102: Buy Broker's Account | C102: Internal Account | D102: -10000
B103: Sell Broker's Account | C103: Internal Account | D103: 10000
A105: Actual Repayment to Customer (Net of Financing) | B105: Customer's Account | C105: Disbursment/Repayment Account | D105: -100
B106: DUEADMINFEE | C106: Admin Fee | D106: 100
B107: Customer's Account | C107: Disbursment/Repayment Account | D107: -15
B108: DUEVAT | C108: VAT | D108: 15
B109: Customer's Account | C109: Disbursment/Repayment Account | D109: 9885
B110: BF Account | C110: Internal Account | D110: -9885
A111: in case not integration with bank this will made manullay by refund function | B111: BF Account | C111: Internal Account | D111: 9885
B112: Customer Bank Account | C112: XYZ bank account- customer current account | D112: -9885

Sheet grace period calculation
B3: TAMWEEL ALOULA COMPANY
B4: (CLOSED JOINT STOCK COMPANY)
E5: Amortization Table
E7: Loan ID | K7: رقم العقد | N7: 418 | O7: SN | V7: عقود غير موجوده في المحفظة
E8: Name | K8: اسم العميل | Y8: VAT finance | AA8: Corporate
E9: ID no | K9: رقم الهوية | Y9: One time | AA9: Retail
E10: Contract type | F10: Retail | K10: حالة العقد
E11: VAT on principle type | G11: VAT finance | K11: نوع الضريبة المضافة على المبلغ الممول
E12: Cash Price | G12: 50000 | I12: Total Cost Term | K12: =IF(G11=Y8,G15+G16+G18,G15+G18) -> 65000
E13: Down Payment | G13: 0 | I13: Cost Inst | K13: =(K12-G17)/K20 -> 2166.6667
E14: Vat on down payment | G14: =G13*K18 -> 0 | I14: Total Contract Amount | K14: =IF(G11=Y9,G12+G18+G20+G21,G12+G16+G18+G20+G21+G14) -> 65000
E15: Financed Amount | G15: =+G12-G13 -> 50000 | I15: EMI | K15: =ROUND(IF(G11=Y8,G15+G16+G18+G20+G21-G17,G15+G18+G20+G21)/K20,2) -> 2166.67
E16: VAT on financed | G16: =G15*K18 -> 0 | I16: Profit | K16: 0.1
E17: RV-Balloon | G17: 0 | I17: Insurance | K17: 0
E18: Interest | G18: =IF(G11=$Y$8,(G15+G16)*K16*(K24/12),G15*K16*(K24/12)) -> 15000 | I18: VAT % | K18: 0
E19: Net APR (NetExcl.insurance&Fees) | G19: =((1+(RATE(K20,(K15-(((G20+G21)/K24))),-(G15+G16),G17,0)))^12)-1 -> 0.23635328 | I19: System profit input | K19: =+G18/(G15+G16)/(K20/12) -> 0.12
E20: Insurance Amount | G20: =IF(G11=$Y$8,(G12*(1+K18))*K17*(K24/12),G12*K17*(K24/12)) -> 0 | I20: N#of repayment | K20: 30
D21: =+G21+G20 -> 0 | E21: VAT On Insurance | G21: =IF(K18=0,0,$G$20*(K18)) -> 0 | I21: Finance IRR (Monthly) | K21: =RATE(K20,K13,IF(G11=Y8,-(G15+G16),-G15),G17,0) -> 0.017837627
E22: Admin Fees | G22: =IF(AND(F10="Retail",+K23*G15>5000),5000,+K23*G15) -> 500 | I22: APR | K22: =((1+(RATE(K20,K15,-(G15+G16-G22-G23),G17,0)))^12)-1 -> 0.24693202
E23: VAT On Admin | G23: =$G$22*K18 -> 0 | I23: Admin Fees % | K23: 0.01
E24: Grace period | G24: 6 | I24: Total contract maturity | K24: =+K20+G24 -> 36
B26: Financed | C26: حالة القسط | D26: رقم القسط | E26: قيمة الأصل الابتدائية | F26: التأمين | G26: الربح | H26: الأصل | I26: قيمة الضريبة على القيمة الممولة | J26: قيمة الضريبة على التأمين | K26: القسط الشهرى | L26: القيمة المتبقية من الأصل
B27: Ins# | C27: Inst status | D27: Ins# | E27: Opening Balance (Capital) | F27: Insurance | G27: Interest | H27: Principal | I27: VAT On Finance Amount | J27: VAT On Insurance | K27: Monthly Installment | L27: Ending Balance (Capital) | M27: =I7 -> 0 | U27: 598
B28: =IF(D28<=$G$24,0,IF(D28>$K$24,"",IF($G$11=$Y$8,$G$15+$G$16,$G$15))) -> 0 | C28: =+IF(D28="","",IF(D28<=$G$24,"Grace period","contract maturity")) -> Grace period | D28: 1 | E28: =IF(G11=Y8,G15+G16,G15) -> 50000 | F28: =IF(C28=$E$24,0,IF(D28>$K$24,"",IF(D28<=$K$24,$G$20/$K$20,0))) -> 0 | G28: =IF(C28="grace period",0,IF(D28>$K$24,"",IF(E28=0,$G$15*$K$21,E28*$K$21))) -> 0 | H28: =IF(D28<=$G$24,0,IF(D28>$K$24,"",K28-J28-G28-F28-I28)) -> 0 | I28: =IF(D28<=$G$24,0,IF(D28>$K$24,"",IF($G$11=$Y$10,IF(D28=$K$24,(($G$16-($G$17*$K$18))/$K$20)+($G$17*$K$18),(($G$16-($G$17*$K$18))/$K$20)),0))) -> 0 | J28: =IF(D28<=$G$24,0,IF(D28>$K$24,"",$G$21/$K$20)) -> 0 | K28: =IF(B28=0,F28+G28,IF(D28<=$G$24,0,IF(D28>$K$24,"",IF($G$11=$Y$10,IF(D28=$K$24,$G$17+$K$15+($G$17*$K$18),IF(D28<$K$24,$K$15,0)),IF(D28=$K$24,$G$17+$K$15,IF(D28<$K$24,$K$15,0)))))) -> 0 | L28: =IF(D28>$K$24,"",E28-H28) -> 50000 | M28: =$K$7 -> رقم العقد | U28: 599 | AB28: =+K28-J28-H28-G28-F28 -> 0 | AD28: =+SUM(G28:G87) -> 14999.969 | AE28: =+AD28-G18 -> -0.030740968
B29: =IF(D29<=$G$24,0,IF(D29>$K$24,"",IF($G$11=$Y$8,$G$15+$G$16,$G$15))) -> 0 | C29: =+IF(D29="","",IF(D29<=$G$24,"Grace period","contract maturity")) -> Grace period | D29: =IFERROR(IF(D28+1>$K$24,"",D28+1),"") -> 2 | E29: =+IF(AND(B29>1,E28=0,B29),B29,L28) -> 50000 | F29: =IF(C29=$E$24,0,IF(D29>$K$24,"",IF(D29<=$K$24,$G$20/$K$20,0))) -> 0 | G29: =IF(C29="grace period",0,IF(D29>$K$24,"",IF(E29=0,$G$15*$K$21,E29*$K$21))) -> 0 | H29: =IF(D29<=$G$24,0,IF(D29>$K$24,"",K29-J29-G29-F29-I29)) -> 0 | I29: =IF(D29<=$G$24,0,IF(D29>$K$24,"",IF($G$11=$Y$10,IF(D29=$K$24,(($G$16-($G$17*$K$18))/$K$20)+($G$17*$K$18),(($G$16-($G$17*$K$18))/$K$20)),0))) -> 0 | J29: =IF(D29<=$G$24,0,IF(D29>$K$24,"",$G$21/$K$20)) -> 0 | K29: =IF(B29=0,F29+G29,IF(D29<=$G$24,0,IF(D29>$K$24,"",IF($G$11=$Y$10,IF(D29=$K$24,$G$17+$K$15+($G$17*$K$18),IF(D29<$K$24,$K$15,0)),IF(D29=$K$24,$G$17+$K$15,IF(D29<$K$24,$K$15,0)))))) -> 0 | L29: =IF(D29>$K$24,"",E29-H29) -> 50000 | M29: =$K$7 -> رقم العقد | O29: =+K29-F29-G29 -> 0 | U29: 601 | AB29: =+K29-J29-H29-G29-F29 -> 0
B30: =IF(D30<=$G$24,0,IF(D30>$K$24,"",IF($G$11=$Y$8,$G$15+$G$16,$G$15))) -> 0 | C30: =+IF(D30="","",IF(D30<=$G$24,"Grace period","contract maturity")) -> Grace period | D30: =IFERROR(IF(D29+1>$K$24,"",D29+1),"") -> 3 | E30: =+IF(AND(B30>1,E29=0,B30),B30,L29) -> 50000 | F30: =IF(C30=$E$24,0,IF(D30>$K$24,"",IF(D30<=$K$24,$G$20/$K$20,0))) -> 0 | G30: =IF(C30="grace period",0,IF(D30>$K$24,"",IF(E30=0,$G$15*$K$21,E30*$K$21))) -> 0 | H30: =IF(D30<=$G$24,0,IF(D30>$K$24,"",K30-J30-G30-F30-I30)) -> 0 | I30: =IF(D30<=$G$24,0,IF(D30>$K$24,"",IF($G$11=$Y$10,IF(D30=$K$24,(($G$16-($G$17*$K$18))/$K$20)+($G$17*$K$18),(($G$16-($G$17*$K$18))/$K$20)),0))) -> 0 | J30: =IF(D30<=$G$24,0,IF(D30>$K$24,"",$G$21/$K$20)) -> 0 | K30: =IF(B30=0,F30+G30,IF(D30<=$G$24,0,IF(D30>$K$24,"",IF($G$11=$Y$10,IF(D30=$K$24,$G$17+$K$15+($G$17*$K$18),IF(D30<$K$24,$K$15,0)),IF(D30=$K$24,$G$17+$K$15,IF(D30<$K$24,$K$15,0)))))) -> 0 | L30: =IF(D30>$K$24,"",E30-H30) -> 50000 | M30: =$K$7 -> رقم العقد | O30: =+K30-F30-G30 -> 0 | U30: 620 | AB30: =+K30-J30-H30-G30-F30 -> 0
B31: =IF(D31<=$G$24,0,IF(D31>$K$24,"",IF($G$11=$Y$8,$G$15+$G$16,$G$15))) -> 0 | C31: =+IF(D31="","",IF(D31<=$G$24,"Grace period","contract maturity")) -> Grace period | D31: =IFERROR(IF(D30+1>$K$24,"",D30+1),"") -> 4 | E31: =+IF(AND(B31>1,E30=0,B31),B31,L30) -> 50000 | F31: =IF(C31=$E$24,0,IF(D31>$K$24,"",IF(D31<=$K$24,$G$20/$K$20,0))) -> 0 | G31: =IF(C31="grace period",0,IF(D31>$K$24,"",IF(E31=0,$G$15*$K$21,E31*$K$21))) -> 0 | H31: =IF(D31<=$G$24,0,IF(D31>$K$24,"",K31-J31-G31-F31-I31)) -> 0 | I31: =IF(D31<=$G$24,0,IF(D31>$K$24,"",IF($G$11=$Y$10,IF(D31=$K$24,(($G$16-($G$17*$K$18))/$K$20)+($G$17*$K$18),(($G$16-($G$17*$K$18))/$K$20)),0))) -> 0 | J31: =IF(D31<=$G$24,0,IF(D31>$K$24,"",$G$21/$K$20)) -> 0 | K31: =IF(B31=0,F31+G31,IF(D31<=$G$24,0,IF(D31>$K$24,"",IF($G$11=$Y$10,IF(D31=$K$24,$G$17+$K$15+($G$17*$K$18),IF(D31<$K$24,$K$15,0)),IF(D31=$K$24,$G$17+$K$15,IF(D31<$K$24,$K$15,0)))))) -> 0 | L31: =IF(D31>$K$24,"",E31-H31) -> 50000 | M31: =$K$7 -> رقم العقد | O31: =+K31-F31-G31 -> 0 | U31: 672 | AB31: =+K31-J31-H31-G31-F31 -> 0
B32: =IF(D32<=$G$24,0,IF(D32>$K$24,"",IF($G$11=$Y$8,$G$15+$G$16,$G$15))) -> 0 | C32: =+IF(D32="","",IF(D32<=$G$24,"Grace period","contract maturity")) -> Grace period | D32: =IFERROR(IF(D31+1>$K$24,"",D31+1),"") -> 5 | E32: =+IF(AND(B32>1,E31=0,B32),B32,L31) -> 50000 | F32: =IF(C32=$E$24,0,IF(D32>$K$24,"",IF(D32<=$K$24,$G$20/$K$20,0))) -> 0 | G32: =IF(C32="grace period",0,IF(D32>$K$24,"",IF(E32=0,$G$15*$K$21,E32*$K$21))) -> 0 | H32: =IF(D32<=$G$24,0,IF(D32>$K$24,"",K32-J32-G32-F32-I32)) -> 0 | I32: =IF(D32<=$G$24,0,IF(D32>$K$24,"",IF($G$11=$Y$10,IF(D32=$K$24,(($G$16-($G$17*$K$18))/$K$20)+($G$17*$K$18),(($G$16-($G$17*$K$18))/$K$20)),0))) -> 0 | J32: =IF(D32<=$G$24,0,IF(D32>$K$24,"",$G$21/$K$20)) -> 0 | K32: =IF(B32=0,F32+G32,IF(D32<=$G$24,0,IF(D32>$K$24,"",IF($G$11=$Y$10,IF(D32=$K$24,$G$17+$K$15+($G$17*$K$18),IF(D32<$K$24,$K$15,0)),IF(D32=$K$24,$G$17+$K$15,IF(D32<$K$24,$K$15,0)))))) -> 0 | L32: =IF(D32>$K$24,"",E32-H32) -> 50000 | M32: =$K$7 -> رقم العقد | O32: =+K32-F32-G32 -> 0 | U32: 704 | AB32: =+K32-J32-H32-G32-F32 -> 0
B33: =IF(D33<=$G$24,0,IF(D33>$K$24,"",IF($G$11=$Y$8,$G$15+$G$16,$G$15))) -> 0 | C33: =+IF(D33="","",IF(D33<=$G$24,"Grace period","contract maturity")) -> Grace period | D33: =IFERROR(IF(D32+1>$K$24,"",D32+1),"") -> 6 | E33: =+IF(AND(B33>1,E32=0,B33),B33,L32) -> 50000 | F33: =IF(C33=$E$24,0,IF(D33>$K$24,"",IF(D33<=$K$24,$G$20/$K$20,0))) -> 0 | G33: =IF(C33="grace period",0,IF(D33>$K$24,"",IF(E33=0,$G$15*$K$21,E33*$K$21))) -> 0 | H33: =IF(D33<=$G$24,0,IF(D33>$K$24,"",K33-J33-G33-F33-I33)) -> 0 | I33: =IF(D33<=$G$24,0,IF(D33>$K$24,"",IF($G$11=$Y$10,IF(D33=$K$24,(($G$16-($G$17*$K$18))/$K$20)+($G$17*$K$18),(($G$16-($G$17*$K$18))/$K$20)),0))) -> 0 | J33: =IF(D33<=$G$24,0,IF(D33>$K$24,"",$G$21/$K$20)) -> 0 | K33: =IF(B33=0,F33+G33,IF(D33<=$G$24,0,IF(D33>$K$24,"",IF($G$11=$Y$10,IF(D33=$K$24,$G$17+$K$15+($G$17*$K$18),IF(D33<$K$24,$K$15,0)),IF(D33=$K$24,$G$17+$K$15,IF(D33<$K$24,$K$15,0)))))) -> 0 | L33: =IF(D33>$K$24,"",E33-H33) -> 50000 | M33: =$K$7 -> رقم العقد | O33: =+K33-F33-G33 -> 0 | U33: 707 | AB33: =+K33-J33-H33-G33-F33 -> 0
B34: =IF(D34<=$G$24,0,IF(D34>$K$24,"",IF($G$11=$Y$8,$G$15+$G$16,$G$15))) -> 50000 | C34: =+IF(D34="","",IF(D34<=$G$24,"Grace period","contract maturity")) -> contract maturity | D34: =IFERROR(IF(D33+1>$K$24,"",D33+1),"") -> 7 | E34: =+IF(AND(B34>1,E33=0,B34),B34,L33) -> 50000 | F34: =IF(C34=$E$24,0,IF(D34>$K$24,"",IF(D34<=$K$24,$G$20/$K$20,0))) -> 0 | G34: =IF(C34="grace period",0,IF(D34>$K$24,"",IF(E34=0,$G$15*$K$21,E34*$K$21))) -> 891.88135 | H34: =IF(D34<=$G$24,0,IF(D34>$K$24,"",K34-J34-G34-F34-I34)) -> 1274.7886 | I34: =IF(D34<=$G$24,0,IF(D34>$K$24,"",IF($G$11=$Y$10,IF(D34=$K$24,(($G$16-($G$17*$K$18))/$K$20)+($G$17*$K$18),(($G$16-($G$17*$K$18))/$K$20)),0))) -> 0 | J34: =IF(D34<=$G$24,0,IF(D34>$K$24,"",$G$21/$K$20)) -> 0 | K34: =IF(B34=0,F34+G34,IF(D34<=$G$24,0,IF(D34>$K$24,"",IF($G$11=$Y$10,IF(D34=$K$24,$G$17+$K$15+($G$17*$K$18),IF(D34<$K$24,$K$15,0)),IF(D34=$K$24,$G$17+$K$15,IF(D34<$K$24,$K$15,0)))))) -> 2166.67 | L34: =IF(D34>$K$24,"",E34-H34) -> 48725.211 | M34: =$K$7 -> رقم العقد | O34: =+K34-F34-G34 -> 1274.7886 | U34: 730 | AB34: =+K34-J34-H34-G34-F34 -> 0
B35: =IF(D35<=$G$24,0,IF(D35>$K$24,"",IF($G$11=$Y$8,$G$15+$G$16,$G$15))) -> 50000 | C35: =+IF(D35="","",IF(D35<=$G$24,"Grace period","contract maturity")) -> contract maturity | D35: =IFERROR(IF(D34+1>$K$24,"",D34+1),"") -> 8 | E35: =+IF(AND(B35>1,E34=0,B35),B35,L34) -> 48725.211 | F35: =IF(C35=$E$24,0,IF(D35>$K$24,"",IF(D35<=$K$24,$G$20/$K$20,0))) -> 0 | G35: =IF(C35="grace period",0,IF(D35>$K$24,"",IF(E35=0,$G$15*$K$21,E35*$K$21))) -> 869.14215 | H35: =IF(D35<=$G$24,0,IF(D35>$K$24,"",K35-J35-G35-F35-I35)) -> 1297.5279 | I35: =IF(D35<=$G$24,0,IF(D35>$K$24,"",IF($G$11=$Y$10,IF(D35=$K$24,(($G$16-($G$17*$K$18))/$K$20)+($G$17*$K$18),(($G$16-($G$17*$K$18))/$K$20)),0))) -> 0 | J35: =IF(D35<=$G$24,0,IF(D35>$K$24,"",$G$21/$K$20)) -> 0 | K35: =IF(B35=0,F35+G35,IF(D35<=$G$24,0,IF(D35>$K$24,"",IF($G$11=$Y$10,IF(D35=$K$24,$G$17+$K$15+($G$17*$K$18),IF(D35<$K$24,$K$15,0)),IF(D35=$K$24,$G$17+$K$15,IF(D35<$K$24,$K$15,0)))))) -> 2166.67 | L35: =IF(D35>$K$24,"",E35-H35) -> 47427.683 | M35: =$K$7 -> رقم العقد | O35: =+K35-F35-G35 -> 1297.5279 | U35: 765 | AB35: =+K35-J35-H35-G35-F35 -> 0
B36: =IF(D36<=$G$24,0,IF(D36>$K$24,"",IF($G$11=$Y$8,$G$15+$G$16,$G$15))) -> 50000 | C36: =+IF(D36="","",IF(D36<=$G$24,"Grace period","contract maturity")) -> contract maturity | D36: =IFERROR(IF(D35+1>$K$24,"",D35+1),"") -> 9 | E36: =+IF(AND(B36>1,E35=0,B36),B36,L35) -> 47427.683 | F36: =IF(C36=$E$24,0,IF(D36>$K$24,"",IF(D36<=$K$24,$G$20/$K$20,0))) -> 0 | G36: =IF(C36="grace period",0,IF(D36>$K$24,"",IF(E36=0,$G$15*$K$21,E36*$K$21))) -> 845.99733 | H36: =IF(D36<=$G$24,0,IF(D36>$K$24,"",K36-J36-G36-F36-I36)) -> 1320.6727 | I36: =IF(D36<=$G$24,0,IF(D36>$K$24,"",IF($G$11=$Y$10,IF(D36=$K$24,(($G$16-($G$17*$K$18))/$K$20)+($G$17*$K$18),(($G$16-($G$17*$K$18))/$K$20)),0))) -> 0 | J36: =IF(D36<=$G$24,0,IF(D36>$K$24,"",$G$21/$K$20)) -> 0 | K36: =IF(B36=0,F36+G36,IF(D36<=$G$24,0,IF(D36>$K$24,"",IF($G$11=$Y$10,IF(D36=$K$24,$G$17+$K$15+($G$17*$K$18),IF(D36<$K$24,$K$15,0)),IF(D36=$K$24,$G$17+$K$15,IF(D36<$K$24,$K$15,0)))))) -> 2166.67 | L36: =IF(D36>$K$24,"",E36-H36) -> 46107.011 | M36: =$K$7 -> رقم العقد | O36: =+K36-F36-G36 -> 1320.6727 | U36: 786 | AB36: =+K36-J36-H36-G36-F36 -> 1.1368684e-13
B37: =IF(D37<=$G$24,0,IF(D37>$K$24,"",IF($G$11=$Y$8,$G$15+$G$16,$G$15))) -> 50000 | C37: =+IF(D37="","",IF(D37<=$G$24,"Grace period","contract maturity")) -> contract maturity | D37: =IFERROR(IF(D36+1>$K$24,"",D36+1),"") -> 10 | E37: =+IF(AND(B37>1,E36=0,B37),B37,L36) -> 46107.011 | F37: =IF(C37=$E$24,0,IF(D37>$K$24,"",IF(D37<=$K$24,$G$20/$K$20,0))) -> 0 | G37: =IF(C37="grace period",0,IF(D37>$K$24,"",IF(E37=0,$G$15*$K$21,E37*$K$21))) -> 822.43966 | H37: =IF(D37<=$G$24,0,IF(D37>$K$24,"",K37-J37-G37-F37-I37)) -> 1344.2303 | I37: =IF(D37<=$G$24,0,IF(D37>$K$24,"",IF($G$11=$Y$10,IF(D37=$K$24,(($G$16-($G$17*$K$18))/$K$20)+($G$17*$K$18),(($G$16-($G$17*$K$18))/$K$20)),0))) -> 0 | J37: =IF(D37<=$G$24,0,IF(D37>$K$24,"",$G$21/$K$20)) -> 0 | K37: =IF(B37=0,F37+G37,IF(D37<=$G$24,0,IF(D37>$K$24,"",IF($G$11=$Y$10,IF(D37=$K$24,$G$17+$K$15+($G$17*$K$18),IF(D37<$K$24,$K$15,0)),IF(D37=$K$24,$G$17+$K$15,IF(D37<$K$24,$K$15,0)))))) -> 2166.67 | L37: =IF(D37>$K$24,"",E37-H37) -> 44762.78 | M37: =$K$7 -> رقم العقد | O37: =+K37-F37-G37 -> 1344.2303 | U37: 790 | AB37: =+K37-J37-H37-G37-F37 -> 0
B38: =IF(D38<=$G$24,0,IF(D38>$K$24,"",IF($G$11=$Y$8,$G$15+$G$16,$G$15))) -> 50000 | C38: =+IF(D38="","",IF(D38<=$G$24,"Grace period","contract maturity")) -> contract maturity | D38: =IFERROR(IF(D37+1>$K$24,"",D37+1),"") -> 11 | E38: =+IF(AND(B38>1,E37=0,B38),B38,L37) -> 44762.78 | F38: =IF(C38=$E$24,0,IF(D38>$K$24,"",IF(D38<=$K$24,$G$20/$K$20,0))) -> 0 | G38: =IF(C38="grace period",0,IF(D38>$K$24,"",IF(E38=0,$G$15*$K$21,E38*$K$21))) -> 798.46178 | H38: =IF(D38<=$G$24,0,IF(D38>$K$24,"",K38-J38-G38-F38-I38)) -> 1368.2082 | I38: =IF(D38<=$G$24,0,IF(D38>$K$24,"",IF($G$11=$Y$10,IF(D38=$K$24,(($G$16-($G$17*$K$18))/$K$20)+($G$17*$K$18),(($G$16-($G$17*$K$18))/$K$20)),0))) -> 0 | J38: =IF(D38<=$G$24,0,IF(D38>$K$24,"",$G$21/$K$20)) -> 0 | K38: =IF(B38=0,F38+G38,IF(D38<=$G$24,0,IF(D38>$K$24,"",IF($G$11=$Y$10,IF(D38=$K$24,$G$17+$K$15+($G$17*$K$18),IF(D38<$K$24,$K$15,0)),IF(D38=$K$24,$G$17+$K$15,IF(D38<$K$24,$K$15,0)))))) -> 2166.67 | L38: =IF(D38>$K$24,"",E38-H38) -> 43394.572 | M38: =$K$7 -> رقم العقد | O38: =+K38-F38-G38 -> 1368.2082 | U38: 815 | AB38: =+K38-J38-H38-G38-F38 -> 1.1368684e-13
B39: =IF(D39<=$G$24,0,IF(D39>$K$24,"",IF($G$11=$Y$8,$G$15+$G$16,$G$15))) -> 50000 | C39: =+IF(D39="","",IF(D39<=$G$24,"Grace period","contract maturity")) -> contract maturity | D39: =IFERROR(IF(D38+1>$K$24,"",D38+1),"") -> 12 | E39: =+IF(AND(B39>1,E38=0,B39),B39,L38) -> 43394.572 | F39: =IF(C39=$E$24,0,IF(D39>$K$24,"",IF(D39<=$K$24,$G$20/$K$20,0))) -> 0 | G39: =IF(C39="grace period",0,IF(D39>$K$24,"",IF(E39=0,$G$15*$K$21,E39*$K$21))) -> 774.0562 | H39: =IF(D39<=$G$24,0,IF(D39>$K$24,"",K39-J39-G39-F39-I39)) -> 1392.6138 | I39: =IF(D39<=$G$24,0,IF(D39>$K$24,"",IF($G$11=$Y$10,IF(D39=$K$24,(($G$16-($G$17*$K$18))/$K$20)+($G$17*$K$18),(($G$16-($G$17*$K$18))/$K$20)),0))) -> 0 | J39: =IF(D39<=$G$24,0,IF(D39>$K$24,"",$G$21/$K$20)) -> 0 | K39: =IF(B39=0,F39+G39,IF(D39<=$G$24,0,IF(D39>$K$24,"",IF($G$11=$Y$10,IF(D39=$K$24,$G$17+$K$15+($G$17*$K$18),IF(D39<$K$24,$K$15,0)),IF(D39=$K$24,$G$17+$K$15,IF(D39<$K$24,$K$15,0)))))) -> 2166.67 | L39: =IF(D39>$K$24,"",E39-H39) -> 42001.958 | M39: =$K$7 -> رقم العقد | O39: =+K39-F39-G39 -> 1392.6138 | U39: 824 | AB39: =+K39-J39-H39-G39-F39 -> 0
B40: =IF(D40<=$G$24,0,IF(D40>$K$24,"",IF($G$11=$Y$8,$G$15+$G$16,$G$15))) -> 50000 | C40: =+IF(D40="","",IF(D40<=$G$24,"Grace period","contract maturity")) -> contract maturity | D40: =IFERROR(IF(D39+1>$K$24,"",D39+1),"") -> 13 | E40: =+IF(AND(B40>1,E39=0,B40),B40,L39) -> 42001.958 | F40: =IF(C40=$E$24,0,IF(D40>$K$24,"",IF(D40<=$K$24,$G$20/$K$20,0))) -> 0 | G40: =IF(C40="grace period",0,IF(D40>$K$24,"",IF(E40=0,$G$15*$K$21,E40*$K$21))) -> 749.21527 | H40: =IF(D40<=$G$24,0,IF(D40>$K$24,"",K40-J40-G40-F40-I40)) -> 1417.4547 | I40: =IF(D40<=$G$24,0,IF(D40>$K$24,"",IF($G$11=$Y$10,IF(D40=$K$24,(($G$16-($G$17*$K$18))/$K$20)+($G$17*$K$18),(($G$16-($G$17*$K$18))/$K$20)),0))) -> 0 | J40: =IF(D40<=$G$24,0,IF(D40>$K$24,"",$G$21/$K$20)) -> 0 | K40: =IF(B40=0,F40+G40,IF(D40<=$G$24,0,IF(D40>$K$24,"",IF($G$11=$Y$10,IF(D40=$K$24,$G$17+$K$15+($G$17*$K$18),IF(D40<$K$24,$K$15,0)),IF(D40=$K$24,$G$17+$K$15,IF(D40<$K$24,$K$15,0)))))) -> 2166.67 | L40: =IF(D40>$K$24,"",E40-H40) -> 40584.504 | M40: =$K$7 -> رقم العقد | O40: =+K40-F40-G40 -> 1417.4547 | U40: 1000
B41: =IF(D41<=$G$24,0,IF(D41>$K$24,"",IF($G$11=$Y$8,$G$15+$G$16,$G$15))) -> 50000 | C41: =+IF(D41="","",IF(D41<=$G$24,"Grace period","contract maturity")) -> contract maturity | D41: =IFERROR(IF(D40+1>$K$24,"",D40+1),"") -> 14 | E41: =+IF(AND(B41>1,E40=0,B41),B41,L40) -> 40584.504 | F41: =IF(C41=$E$24,0,IF(D41>$K$24,"",IF(D41<=$K$24,$G$20/$K$20,0))) -> 0 | G41: =IF(C41="grace period",0,IF(D41>$K$24,"",IF(E41=0,$G$15*$K$21,E41*$K$21))) -> 723.93124 | H41: =IF(D41<=$G$24,0,IF(D41>$K$24,"",K41-J41-G41-F41-I41)) -> 1442.7388 | I41: =IF(D41<=$G$24,0,IF(D41>$K$24,"",IF($G$11=$Y$10,IF(D41=$K$24,(($G$16-($G$17*$K$18))/$K$20)+($G$17*$K$18),(($G$16-($G$17*$K$18))/$K$20)),0))) -> 0 | J41: =IF(D41<=$G$24,0,IF(D41>$K$24,"",$G$21/$K$20)) -> 0 | K41: =IF(B41=0,F41+G41,IF(D41<=$G$24,0,IF(D41>$K$24,"",IF($G$11=$Y$10,IF(D41=$K$24,$G$17+$K$15+($G$17*$K$18),IF(D41<$K$24,$K$15,0)),IF(D41=$K$24,$G$17+$K$15,IF(D41<$K$24,$K$15,0)))))) -> 2166.67 | L41: =IF(D41>$K$24,"",E41-H41) -> 39141.765 | M41: =$K$7 -> رقم العقد | O41: =+K41-F41-G41 -> 1442.7388 | U41: 1028
B42: =IF(D42<=$G$24,0,IF(D42>$K$24,"",IF($G$11=$Y$8,$G$15+$G$16,$G$15))) -> 50000 | C42: =+IF(D42="","",IF(D42<=$G$24,"Grace period","contract maturity")) -> contract maturity | D42: =IFERROR(IF(D41+1>$K$24,"",D41+1),"") -> 15 | E42: =+IF(AND(B42>1,E41=0,B42),B42,L41) -> 39141.765 | F42: =IF(C42=$E$24,0,IF(D42>$K$24,"",IF(D42<=$K$24,$G$20/$K$20,0))) -> 0 | G42: =IF(C42="grace period",0,IF(D42>$K$24,"",IF(E42=0,$G$15*$K$21,E42*$K$21))) -> 698.19621 | H42: =IF(D42<=$G$24,0,IF(D42>$K$24,"",K42-J42-G42-F42-I42)) -> 1468.4738 | I42: =IF(D42<=$G$24,0,IF(D42>$K$24,"",IF($G$11=$Y$10,IF(D42=$K$24,(($G$16-($G$17*$K$18))/$K$20)+($G$17*$K$18),(($G$16-($G$17*$K$18))/$K$20)),0))) -> 0 | J42: =IF(D42<=$G$24,0,IF(D42>$K$24,"",$G$21/$K$20)) -> 0 | K42: =IF(B42=0,F42+G42,IF(D42<=$G$24,0,IF(D42>$K$24,"",IF($G$11=$Y$10,IF(D42=$K$24,$G$17+$K$15+($G$17*$K$18),IF(D42<$K$24,$K$15,0)),IF(D42=$K$24,$G$17+$K$15,IF(D42<$K$24,$K$15,0)))))) -> 2166.67 | L42: =IF(D42>$K$24,"",E42-H42) -> 37673.291 | M42: =$K$7 -> رقم العقد | O42: =+K42-F42-G42 -> 1468.4738
B43: =IF(D43<=$G$24,0,IF(D43>$K$24,"",IF($G$11=$Y$8,$G$15+$G$16,$G$15))) -> 50000 | C43: =+IF(D43="","",IF(D43<=$G$24,"Grace period","contract maturity")) -> contract maturity | D43: =IFERROR(IF(D42+1>$K$24,"",D42+1),"") -> 16 | E43: =+IF(AND(B43>1,E42=0,B43),B43,L42) -> 37673.291 | F43: =IF(C43=$E$24,0,IF(D43>$K$24,"",IF(D43<=$K$24,$G$20/$K$20,0))) -> 0 | G43: =IF(C43="grace period",0,IF(D43>$K$24,"",IF(E43=0,$G$15*$K$21,E43*$K$21))) -> 672.00212 | H43: =IF(D43<=$G$24,0,IF(D43>$K$24,"",K43-J43-G43-F43-I43)) -> 1494.6679 | I43: =IF(D43<=$G$24,0,IF(D43>$K$24,"",IF($G$11=$Y$10,IF(D43=$K$24,(($G$16-($G$17*$K$18))/$K$20)+($G$17*$K$18),(($G$16-($G$17*$K$18))/$K$20)),0))) -> 0 | J43: =IF(D43<=$G$24,0,IF(D43>$K$24,"",$G$21/$K$20)) -> 0 | K43: =IF(B43=0,F43+G43,IF(D43<=$G$24,0,IF(D43>$K$24,"",IF($G$11=$Y$10,IF(D43=$K$24,$G$17+$K$15+($G$17*$K$18),IF(D43<$K$24,$K$15,0)),IF(D43=$K$24,$G$17+$K$15,IF(D43<$K$24,$K$15,0)))))) -> 2166.67 | L43: =IF(D43>$K$24,"",E43-H43) -> 36178.623 | M43: =$K$7 -> رقم العقد | O43: =+K43-F43-G43 -> 1494.6679
B44: =IF(D44<=$G$24,0,IF(D44>$K$24,"",IF($G$11=$Y$8,$G$15+$G$16,$G$15))) -> 50000 | C44: =+IF(D44="","",IF(D44<=$G$24,"Grace period","contract maturity")) -> contract maturity | D44: =IFERROR(IF(D43+1>$K$24,"",D43+1),"") -> 17 | E44: =+IF(AND(B44>1,E43=0,B44),B44,L43) -> 36178.623 | F44: =IF(C44=$E$24,0,IF(D44>$K$24,"",IF(D44<=$K$24,$G$20/$K$20,0))) -> 0 | G44: =IF(C44="grace period",0,IF(D44>$K$24,"",IF(E44=0,$G$15*$K$21,E44*$K$21))) -> 645.34079 | H44: =IF(D44<=$G$24,0,IF(D44>$K$24,"",K44-J44-G44-F44-I44)) -> 1521.3292 | I44: =IF(D44<=$G$24,0,IF(D44>$K$24,"",IF($G$11=$Y$10,IF(D44=$K$24,(($G$16-($G$17*$K$18))/$K$20)+($G$17*$K$18),(($G$16-($G$17*$K$18))/$K$20)),0))) -> 0 | J44: =IF(D44<=$G$24,0,IF(D44>$K$24,"",$G$21/$K$20)) -> 0 | K44: =IF(B44=0,F44+G44,IF(D44<=$G$24,0,IF(D44>$K$24,"",IF($G$11=$Y$10,IF(D44=$K$24,$G$17+$K$15+($G$17*$K$18),IF(D44<$K$24,$K$15,0)),IF(D44=$K$24,$G$17+$K$15,IF(D44<$K$24,$K$15,0)))))) -> 2166.67 | L44: =IF(D44>$K$24,"",E44-H44) -> 34657.294 | M44: =$K$7 -> رقم العقد | O44: =+K44-F44-G44 -> 1521.3292
B45: =IF(D45<=$G$24,0,IF(D45>$K$24,"",IF($G$11=$Y$8,$G$15+$G$16,$G$15))) -> 50000 | C45: =+IF(D45="","",IF(D45<=$G$24,"Grace period","contract maturity")) -> contract maturity | D45: =IFERROR(IF(D44+1>$K$24,"",D44+1),"") -> 18 | E45: =+IF(AND(B45>1,E44=0,B45),B45,L44) -> 34657.294 | F45: =IF(C45=$E$24,0,IF(D45>$K$24,"",IF(D45<=$K$24,$G$20/$K$20,0))) -> 0 | G45: =IF(C45="grace period",0,IF(D45>$K$24,"",IF(E45=0,$G$15*$K$21,E45*$K$21))) -> 618.20389 | H45: =IF(D45<=$G$24,0,IF(D45>$K$24,"",K45-J45-G45-F45-I45)) -> 1548.4661 | I45: =IF(D45<=$G$24,0,IF(D45>$K$24,"",IF($G$11=$Y$10,IF(D45=$K$24,(($G$16-($G$17*$K$18))/$K$20)+($G$17*$K$18),(($G$16-($G$17*$K$18))/$K$20)),0))) -> 0 | J45: =IF(D45<=$G$24,0,IF(D45>$K$24,"",$G$21/$K$20)) -> 0 | K45: =IF(B45=0,F45+G45,IF(D45<=$G$24,0,IF(D45>$K$24,"",IF($G$11=$Y$10,IF(D45=$K$24,$G$17+$K$15+($G$17*$K$18),IF(D45<$K$24,$K$15,0)),IF(D45=$K$24,$G$17+$K$15,IF(D45<$K$24,$K$15,0)))))) -> 2166.67 | L45: =IF(D45>$K$24,"",E45-H45) -> 33108.828 | M45: =$K$7 -> رقم العقد | O45: =+K45-F45-G45 -> 1548.4661
B46: =IF(D46<=$G$24,0,IF(D46>$K$24,"",IF($G$11=$Y$8,$G$15+$G$16,$G$15))) -> 50000 | C46: =+IF(D46="","",IF(D46<=$G$24,"Grace period","contract maturity")) -> contract maturity | D46: =IFERROR(IF(D45+1>$K$24,"",D45+1),"") -> 19 | E46: =+IF(AND(B46>1,E45=0,B46),B46,L45) -> 33108.828 | F46: =IF(C46=$E$24,0,IF(D46>$K$24,"",IF(D46<=$K$24,$G$20/$K$20,0))) -> 0 | G46: =IF(C46="grace period",0,IF(D46>$K$24,"",IF(E46=0,$G$15*$K$21,E46*$K$21))) -> 590.58293 | H46: =IF(D46<=$G$24,0,IF(D46>$K$24,"",K46-J46-G46-F46-I46)) -> 1576.0871 | I46: =IF(D46<=$G$24,0,IF(D46>$K$24,"",IF($G$11=$Y$10,IF(D46=$K$24,(($G$16-($G$17*$K$18))/$K$20)+($G$17*$K$18),(($G$16-($G$17*$K$18))/$K$20)),0))) -> 0 | J46: =IF(D46<=$G$24,0,IF(D46>$K$24,"",$G$21/$K$20)) -> 0 | K46: =IF(B46=0,F46+G46,IF(D46<=$G$24,0,IF(D46>$K$24,"",IF($G$11=$Y$10,IF(D46=$K$24,$G$17+$K$15+($G$17*$K$18),IF(D46<$K$24,$K$15,0)),IF(D46=$K$24,$G$17+$K$15,IF(D46<$K$24,$K$15,0)))))) -> 2166.67 | L46: =IF(D46>$K$24,"",E46-H46) -> 31532.741 | M46: =$K$7 -> رقم العقد | O46: =+K46-F46-G46 -> 1576.0871
B47: =IF(D47<=$G$24,0,IF(D47>$K$24,"",IF($G$11=$Y$8,$G$15+$G$16,$G$15))) -> 50000 | C47: =+IF(D47="","",IF(D47<=$G$24,"Grace period","contract maturity")) -> contract maturity | D47: =IFERROR(IF(D46+1>$K$24,"",D46+1),"") -> 20 | E47: =+IF(AND(B47>1,E46=0,B47),B47,L46) -> 31532.741 | F47: =IF(C47=$E$24,0,IF(D47>$K$24,"",IF(D47<=$K$24,$G$20/$K$20,0))) -> 0 | G47: =IF(C47="grace period",0,IF(D47>$K$24,"",IF(E47=0,$G$15*$K$21,E47*$K$21))) -> 562.46927 | H47: =IF(D47<=$G$24,0,IF(D47>$K$24,"",K47-J47-G47-F47-I47)) -> 1604.2007 | I47: =IF(D47<=$G$24,0,IF(D47>$K$24,"",IF($G$11=$Y$10,IF(D47=$K$24,(($G$16-($G$17*$K$18))/$K$20)+($G$17*$K$18),(($G$16-($G$17*$K$18))/$K$20)),0))) -> 0 | J47: =IF(D47<=$G$24,0,IF(D47>$K$24,"",$G$21/$K$20)) -> 0 | K47: =IF(B47=0,F47+G47,IF(D47<=$G$24,0,IF(D47>$K$24,"",IF($G$11=$Y$10,IF(D47=$K$24,$G$17+$K$15+($G$17*$K$18),IF(D47<$K$24,$K$15,0)),IF(D47=$K$24,$G$17+$K$15,IF(D47<$K$24,$K$15,0)))))) -> 2166.67 | L47: =IF(D47>$K$24,"",E47-H47) -> 29928.54 | M47: =$K$7 -> رقم العقد | O47: =+K47-F47-G47 -> 1604.2007
B48: =IF(D48<=$G$24,0,IF(D48>$K$24,"",IF($G$11=$Y$8,$G$15+$G$16,$G$15))) -> 50000 | C48: =+IF(D48="","",IF(D48<=$G$24,"Grace period","contract maturity")) -> contract maturity | D48: =IFERROR(IF(D47+1>$K$24,"",D47+1),"") -> 21 | E48: =+IF(AND(B48>1,E47=0,B48),B48,L47) -> 29928.54 | F48: =IF(C48=$E$24,0,IF(D48>$K$24,"",IF(D48<=$K$24,$G$20/$K$20,0))) -> 0 | G48: =IF(C48="grace period",0,IF(D48>$K$24,"",IF(E48=0,$G$15*$K$21,E48*$K$21))) -> 533.85414 | H48: =IF(D48<=$G$24,0,IF(D48>$K$24,"",K48-J48-G48-F48-I48)) -> 1632.8159 | I48: =IF(D48<=$G$24,0,IF(D48>$K$24,"",IF($G$11=$Y$10,IF(D48=$K$24,(($G$16-($G$17*$K$18))/$K$20)+($G$17*$K$18),(($G$16-($G$17*$K$18))/$K$20)),0))) -> 0 | J48: =IF(D48<=$G$24,0,IF(D48>$K$24,"",$G$21/$K$20)) -> 0 | K48: =IF(B48=0,F48+G48,IF(D48<=$G$24,0,IF(D48>$K$24,"",IF($G$11=$Y$10,IF(D48=$K$24,$G$17+$K$15+($G$17*$K$18),IF(D48<$K$24,$K$15,0)),IF(D48=$K$24,$G$17+$K$15,IF(D48<$K$24,$K$15,0)))))) -> 2166.67 | L48: =IF(D48>$K$24,"",E48-H48) -> 28295.724 | M48: =$K$7 -> رقم العقد | O48: =+K48-F48-G48 -> 1632.8159
B49: =IF(D49<=$G$24,0,IF(D49>$K$24,"",IF($G$11=$Y$8,$G$15+$G$16,$G$15))) -> 50000 | C49: =+IF(D49="","",IF(D49<=$G$24,"Grace period","contract maturity")) -> contract maturity | D49: =IFERROR(IF(D48+1>$K$24,"",D48+1),"") -> 22 | E49: =+IF(AND(B49>1,E48=0,B49),B49,L48) -> 28295.724 | F49: =IF(C49=$E$24,0,IF(D49>$K$24,"",IF(D49<=$K$24,$G$20/$K$20,0))) -> 0 | G49: =IF(C49="grace period",0,IF(D49>$K$24,"",IF(E49=0,$G$15*$K$21,E49*$K$21))) -> 504.72858 | H49: =IF(D49<=$G$24,0,IF(D49>$K$24,"",K49-J49-G49-F49-I49)) -> 1661.9414 | I49: =IF(D49<=$G$24,0,IF(D49>$K$24,"",IF($G$11=$Y$10,IF(D49=$K$24,(($G$16-($G$17*$K$18))/$K$20)+($G$17*$K$18),(($G$16-($G$17*$K$18))/$K$20)),0))) -> 0 | J49: =IF(D49<=$G$24,0,IF(D49>$K$24,"",$G$21/$K$20)) -> 0 | K49: =IF(B49=0,F49+G49,IF(D49<=$G$24,0,IF(D49>$K$24,"",IF($G$11=$Y$10,IF(D49=$K$24,$G$17+$K$15+($G$17*$K$18),IF(D49<$K$24,$K$15,0)),IF(D49=$K$24,$G$17+$K$15,IF(D49<$K$24,$K$15,0)))))) -> 2166.67 | L49: =IF(D49>$K$24,"",E49-H49) -> 26633.783 | M49: =$K$7 -> رقم العقد
B50: =IF(D50<=$G$24,0,IF(D50>$K$24,"",IF($G$11=$Y$8,$G$15+$G$16,$G$15))) -> 50000 | C50: =+IF(D50="","",IF(D50<=$G$24,"Grace period","contract maturity")) -> contract maturity | D50: =IFERROR(IF(D49+1>$K$24,"",D49+1),"") -> 23 | E50: =+IF(AND(B50>1,E49=0,B50),B50,L49) -> 26633.783 | F50: =IF(C50=$E$24,0,IF(D50>$K$24,"",IF(D50<=$K$24,$G$20/$K$20,0))) -> 0 | G50: =IF(C50="grace period",0,IF(D50>$K$24,"",IF(E50=0,$G$15*$K$21,E50*$K$21))) -> 475.08349 | H50: =IF(D50<=$G$24,0,IF(D50>$K$24,"",K50-J50-G50-F50-I50)) -> 1691.5865 | I50: =IF(D50<=$G$24,0,IF(D50>$K$24,"",IF($G$11=$Y$10,IF(D50=$K$24,(($G$16-($G$17*$K$18))/$K$20)+($G$17*$K$18),(($G$16-($G$17*$K$18))/$K$20)),0))) -> 0 | J50: =IF(D50<=$G$24,0,IF(D50>$K$24,"",$G$21/$K$20)) -> 0 | K50: =IF(B50=0,F50+G50,IF(D50<=$G$24,0,IF(D50>$K$24,"",IF($G$11=$Y$10,IF(D50=$K$24,$G$17+$K$15+($G$17*$K$18),IF(D50<$K$24,$K$15,0)),IF(D50=$K$24,$G$17+$K$15,IF(D50<$K$24,$K$15,0)))))) -> 2166.67 | L50: =IF(D50>$K$24,"",E50-H50) -> 24942.196 | M50: =$K$7 -> رقم العقد
B51: =IF(D51<=$G$24,0,IF(D51>$K$24,"",IF($G$11=$Y$8,$G$15+$G$16,$G$15))) -> 50000 | C51: =+IF(D51="","",IF(D51<=$G$24,"Grace period","contract maturity")) -> contract maturity | D51: =IFERROR(IF(D50+1>$K$24,"",D50+1),"") -> 24 | E51: =+IF(AND(B51>1,E50=0,B51),B51,L50) -> 24942.196 | F51: =IF(C51=$E$24,0,IF(D51>$K$24,"",IF(D51<=$K$24,$G$20/$K$20,0))) -> 0 | G51: =IF(C51="grace period",0,IF(D51>$K$24,"",IF(E51=0,$G$15*$K$21,E51*$K$21))) -> 444.9096 | H51: =IF(D51<=$G$24,0,IF(D51>$K$24,"",K51-J51-G51-F51-I51)) -> 1721.7604 | I51: =IF(D51<=$G$24,0,IF(D51>$K$24,"",IF($G$11=$Y$10,IF(D51=$K$24,(($G$16-($G$17*$K$18))/$K$20)+($G$17*$K$18),(($G$16-($G$17*$K$18))/$K$20)),0))) -> 0 | J51: =IF(D51<=$G$24,0,IF(D51>$K$24,"",$G$21/$K$20)) -> 0 | K51: =IF(B51=0,F51+G51,IF(D51<=$G$24,0,IF(D51>$K$24,"",IF($G$11=$Y$10,IF(D51=$K$24,$G$17+$K$15+($G$17*$K$18),IF(D51<$K$24,$K$15,0)),IF(D51=$K$24,$G$17+$K$15,IF(D51<$K$24,$K$15,0)))))) -> 2166.67 | L51: =IF(D51>$K$24,"",E51-H51) -> 23220.436 | M51: =$K$7 -> رقم العقد
B52: =IF(D52<=$G$24,0,IF(D52>$K$24,"",IF($G$11=$Y$8,$G$15+$G$16,$G$15))) -> 50000 | C52: =+IF(D52="","",IF(D52<=$G$24,"Grace period","contract maturity")) -> contract maturity | D52: =IFERROR(IF(D51+1>$K$24,"",D51+1),"") -> 25 | E52: =+IF(AND(B52>1,E51=0,B52),B52,L51) -> 23220.436 | F52: =IF(C52=$E$24,0,IF(D52>$K$24,"",IF(D52<=$K$24,$G$20/$K$20,0))) -> 0 | G52: =IF(C52="grace period",0,IF(D52>$K$24,"",IF(E52=0,$G$15*$K$21,E52*$K$21))) -> 414.19748 | H52: =IF(D52<=$G$24,0,IF(D52>$K$24,"",K52-J52-G52-F52-I52)) -> 1752.4725 | I52: =IF(D52<=$G$24,0,IF(D52>$K$24,"",IF($G$11=$Y$10,IF(D52=$K$24,(($G$16-($G$17*$K$18))/$K$20)+($G$17*$K$18),(($G$16-($G$17*$K$18))/$K$20)),0))) -> 0 | J52: =IF(D52<=$G$24,0,IF(D52>$K$24,"",$G$21/$K$20)) -> 0 | K52: =IF(B52=0,F52+G52,IF(D52<=$G$24,0,IF(D52>$K$24,"",IF($G$11=$Y$10,IF(D52=$K$24,$G$17+$K$15+($G$17*$K$18),IF(D52<$K$24,$K$15,0)),IF(D52=$K$24,$G$17+$K$15,IF(D52<$K$24,$K$15,0)))))) -> 2166.67 | L52: =IF(D52>$K$24,"",E52-H52) -> 21467.963 | M52: =$K$7 -> رقم العقد
B53: =IF(D53<=$G$24,0,IF(D53>$K$24,"",IF($G$11=$Y$8,$G$15+$G$16,$G$15))) -> 50000 | C53: =+IF(D53="","",IF(D53<=$G$24,"Grace period","contract maturity")) -> contract maturity | D53: =IFERROR(IF(D52+1>$K$24,"",D52+1),"") -> 26 | E53: =+IF(AND(B53>1,E52=0,B53),B53,L52) -> 21467.963 | F53: =IF(C53=$E$24,0,IF(D53>$K$24,"",IF(D53<=$K$24,$G$20/$K$20,0))) -> 0 | G53: =IF(C53="grace period",0,IF(D53>$K$24,"",IF(E53=0,$G$15*$K$21,E53*$K$21))) -> 382.93753 | H53: =IF(D53<=$G$24,0,IF(D53>$K$24,"",K53-J53-G53-F53-I53)) -> 1783.7325 | I53: =IF(D53<=$G$24,0,IF(D53>$K$24,"",IF($G$11=$Y$10,IF(D53=$K$24,(($G$16-($G$17*$K$18))/$K$20)+($G$17*$K$18),(($G$16-($G$17*$K$18))/$K$20)),0))) -> 0 | J53: =IF(D53<=$G$24,0,IF(D53>$K$24,"",$G$21/$K$20)) -> 0 | K53: =IF(B53=0,F53+G53,IF(D53<=$G$24,0,IF(D53>$K$24,"",IF($G$11=$Y$10,IF(D53=$K$24,$G$17+$K$15+($G$17*$K$18),IF(D53<$K$24,$K$15,0)),IF(D53=$K$24,$G$17+$K$15,IF(D53<$K$24,$K$15,0)))))) -> 2166.67 | L53: =IF(D53>$K$24,"",E53-H53) -> 19684.231 | M53: =$K$7 -> رقم العقد
B54: =IF(D54<=$G$24,0,IF(D54>$K$24,"",IF($G$11=$Y$8,$G$15+$G$16,$G$15))) -> 50000 | C54: =+IF(D54="","",IF(D54<=$G$24,"Grace period","contract maturity")) -> contract maturity | D54: =IFERROR(IF(D53+1>$K$24,"",D53+1),"") -> 27 | E54: =+IF(AND(B54>1,E53=0,B54),B54,L53) -> 19684.231 | F54: =IF(C54=$E$24,0,IF(D54>$K$24,"",IF(D54<=$K$24,$G$20/$K$20,0))) -> 0 | G54: =IF(C54="grace period",0,IF(D54>$K$24,"",IF(E54=0,$G$15*$K$21,E54*$K$21))) -> 351.11997 | H54: =IF(D54<=$G$24,0,IF(D54>$K$24,"",K54-J54-G54-F54-I54)) -> 1815.55 | I54: =IF(D54<=$G$24,0,IF(D54>$K$24,"",IF($G$11=$Y$10,IF(D54=$K$24,(($G$16-($G$17*$K$18))/$K$20)+($G$17*$K$18),(($G$16-($G$17*$K$18))/$K$20)),0))) -> 0 | J54: =IF(D54<=$G$24,0,IF(D54>$K$24,"",$G$21/$K$20)) -> 0 | K54: =IF(B54=0,F54+G54,IF(D54<=$G$24,0,IF(D54>$K$24,"",IF($G$11=$Y$10,IF(D54=$K$24,$G$17+$K$15+($G$17*$K$18),IF(D54<$K$24,$K$15,0)),IF(D54=$K$24,$G$17+$K$15,IF(D54<$K$24,$K$15,0)))))) -> 2166.67 | L54: =IF(D54>$K$24,"",E54-H54) -> 17868.681 | M54: =$K$7 -> رقم العقد
B55: =IF(D55<=$G$24,0,IF(D55>$K$24,"",IF($G$11=$Y$8,$G$15+$G$16,$G$15))) -> 50000 | C55: =+IF(D55="","",IF(D55<=$G$24,"Grace period","contract maturity")) -> contract maturity | D55: =IFERROR(IF(D54+1>$K$24,"",D54+1),"") -> 28 | E55: =+IF(AND(B55>1,E54=0,B55),B55,L54) -> 17868.681 | F55: =IF(C55=$E$24,0,IF(D55>$K$24,"",IF(D55<=$K$24,$G$20/$K$20,0))) -> 0 | G55: =IF(C55="grace period",0,IF(D55>$K$24,"",IF(E55=0,$G$15*$K$21,E55*$K$21))) -> 318.73487 | H55: =IF(D55<=$G$24,0,IF(D55>$K$24,"",K55-J55-G55-F55-I55)) -> 1847.9351 | I55: =IF(D55<=$G$24,0,IF(D55>$K$24,"",IF($G$11=$Y$10,IF(D55=$K$24,(($G$16-($G$17*$K$18))/$K$20)+($G$17*$K$18),(($G$16-($G$17*$K$18))/$K$20)),0))) -> 0 | J55: =IF(D55<=$G$24,0,IF(D55>$K$24,"",$G$21/$K$20)) -> 0 | K55: =IF(B55=0,F55+G55,IF(D55<=$G$24,0,IF(D55>$K$24,"",IF($G$11=$Y$10,IF(D55=$K$24,$G$17+$K$15+($G$17*$K$18),IF(D55<$K$24,$K$15,0)),IF(D55=$K$24,$G$17+$K$15,IF(D55<$K$24,$K$15,0)))))) -> 2166.67 | L55: =IF(D55>$K$24,"",E55-H55) -> 16020.746 | M55: =$K$7 -> رقم العقد
B56: =IF(D56<=$G$24,0,IF(D56>$K$24,"",IF($G$11=$Y$8,$G$15+$G$16,$G$15))) -> 50000 | C56: =+IF(D56="","",IF(D56<=$G$24,"Grace period","contract maturity")) -> contract maturity | D56: =IFERROR(IF(D55+1>$K$24,"",D55+1),"") -> 29 | E56: =+IF(AND(B56>1,E55=0,B56),B56,L55) -> 16020.746 | F56: =IF(C56=$E$24,0,IF(D56>$K$24,"",IF(D56<=$K$24,$G$20/$K$20,0))) -> 0 | G56: =IF(C56="grace period",0,IF(D56>$K$24,"",IF(E56=0,$G$15*$K$21,E56*$K$21))) -> 285.77209 | H56: =IF(D56<=$G$24,0,IF(D56>$K$24,"",K56-J56-G56-F56-I56)) -> 1880.8979 | I56: =IF(D56<=$G$24,0,IF(D56>$K$24,"",IF($G$11=$Y$10,IF(D56=$K$24,(($G$16-($G$17*$K$18))/$K$20)+($G$17*$K$18),(($G$16-($G$17*$K$18))/$K$20)),0))) -> 0 | J56: =IF(D56<=$G$24,0,IF(D56>$K$24,"",$G$21/$K$20)) -> 0 | K56: =IF(B56=0,F56+G56,IF(D56<=$G$24,0,IF(D56>$K$24,"",IF($G$11=$Y$10,IF(D56=$K$24,$G$17+$K$15+($G$17*$K$18),IF(D56<$K$24,$K$15,0)),IF(D56=$K$24,$G$17+$K$15,IF(D56<$K$24,$K$15,0)))))) -> 2166.67 | L56: =IF(D56>$K$24,"",E56-H56) -> 14139.848 | M56: =$K$7 -> رقم العقد
B57: =IF(D57<=$G$24,0,IF(D57>$K$24,"",IF($G$11=$Y$8,$G$15+$G$16,$G$15))) -> 50000 | C57: =+IF(D57="","",IF(D57<=$G$24,"Grace period","contract maturity")) -> contract maturity | D57: =IFERROR(IF(D56+1>$K$24,"",D56+1),"") -> 30 | E57: =+IF(AND(B57>1,E56=0,B57),B57,L56) -> 14139.848 | F57: =IF(C57=$E$24,0,IF(D57>$K$24,"",IF(D57<=$K$24,$G$20/$K$20,0))) -> 0 | G57: =IF(C57="grace period",0,IF(D57>$K$24,"",IF(E57=0,$G$15*$K$21,E57*$K$21))) -> 252.22133 | H57: =IF(D57<=$G$24,0,IF(D57>$K$24,"",K57-J57-G57-F57-I57)) -> 1914.4487 | I57: =IF(D57<=$G$24,0,IF(D57>$K$24,"",IF($G$11=$Y$10,IF(D57=$K$24,(($G$16-($G$17*$K$18))/$K$20)+($G$17*$K$18),(($G$16-($G$17*$K$18))/$K$20)),0))) -> 0 | J57: =IF(D57<=$G$24,0,IF(D57>$K$24,"",$G$21/$K$20)) -> 0 | K57: =IF(B57=0,F57+G57,IF(D57<=$G$24,0,IF(D57>$K$24,"",IF($G$11=$Y$10,IF(D57=$K$24,$G$17+$K$15+($G$17*$K$18),IF(D57<$K$24,$K$15,0)),IF(D57=$K$24,$G$17+$K$15,IF(D57<$K$24,$K$15,0)))))) -> 2166.67 | L57: =IF(D57>$K$24,"",E57-H57) -> 12225.399 | M57: =$K$7 -> رقم العقد
B58: =IF(D58<=$G$24,0,IF(D58>$K$24,"",IF($G$11=$Y$8,$G$15+$G$16,$G$15))) -> 50000 | C58: =+IF(D58="","",IF(D58<=$G$24,"Grace period","contract maturity")) -> contract maturity | D58: =IFERROR(IF(D57+1>$K$24,"",D57+1),"") -> 31 | E58: =+IF(AND(B58>1,E57=0,B58),B58,L57) -> 12225.399 | F58: =IF(C58=$E$24,0,IF(D58>$K$24,"",IF(D58<=$K$24,$G$20/$K$20,0))) -> 0 | G58: =IF(C58="grace period",0,IF(D58>$K$24,"",IF(E58=0,$G$15*$K$21,E58*$K$21))) -> 218.07211 | H58: =IF(D58<=$G$24,0,IF(D58>$K$24,"",K58-J58-G58-F58-I58)) -> 1948.5979 | I58: =IF(D58<=$G$24,0,IF(D58>$K$24,"",IF($G$11=$Y$10,IF(D58=$K$24,(($G$16-($G$17*$K$18))/$K$20)+($G$17*$K$18),(($G$16-($G$17*$K$18))/$K$20)),0))) -> 0 | J58: =IF(D58<=$G$24,0,IF(D58>$K$24,"",$G$21/$K$20)) -> 0 | K58: =IF(B58=0,F58+G58,IF(D58<=$G$24,0,IF(D58>$K$24,"",IF($G$11=$Y$10,IF(D58=$K$24,$G$17+$K$15+($G$17*$K$18),IF(D58<$K$24,$K$15,0)),IF(D58=$K$24,$G$17+$K$15,IF(D58<$K$24,$K$15,0)))))) -> 2166.67 | L58: =IF(D58>$K$24,"",E58-H58) -> 10276.801 | M58: =$K$7 -> رقم العقد
B59: =IF(D59<=$G$24,0,IF(D59>$K$24,"",IF($G$11=$Y$8,$G$15+$G$16,$G$15))) -> 50000 | C59: =+IF(D59="","",IF(D59<=$G$24,"Grace period","contract maturity")) -> contract maturity | D59: =IFERROR(IF(D58+1>$K$24,"",D58+1),"") -> 32 | E59: =+IF(AND(B59>1,E58=0,B59),B59,L58) -> 10276.801 | F59: =IF(C59=$E$24,0,IF(D59>$K$24,"",IF(D59<=$K$24,$G$20/$K$20,0))) -> 0 | G59: =IF(C59="grace period",0,IF(D59>$K$24,"",IF(E59=0,$G$15*$K$21,E59*$K$21))) -> 183.31375 | H59: =IF(D59<=$G$24,0,IF(D59>$K$24,"",K59-J59-G59-F59-I59)) -> 1983.3563 | I59: =IF(D59<=$G$24,0,IF(D59>$K$24,"",IF($G$11=$Y$10,IF(D59=$K$24,(($G$16-($G$17*$K$18))/$K$20)+($G$17*$K$18),(($G$16-($G$17*$K$18))/$K$20)),0))) -> 0 | J59: =IF(D59<=$G$24,0,IF(D59>$K$24,"",$G$21/$K$20)) -> 0 | K59: =IF(B59=0,F59+G59,IF(D59<=$G$24,0,IF(D59>$K$24,"",IF($G$11=$Y$10,IF(D59=$K$24,$G$17+$K$15+($G$17*$K$18),IF(D59<$K$24,$K$15,0)),IF(D59=$K$24,$G$17+$K$15,IF(D59<$K$24,$K$15,0)))))) -> 2166.67 | L59: =IF(D59>$K$24,"",E59-H59) -> 8293.4451 | M59: =$K$7 -> رقم العقد
B60: =IF(D60<=$G$24,0,IF(D60>$K$24,"",IF($G$11=$Y$8,$G$15+$G$16,$G$15))) -> 50000 | C60: =+IF(D60="","",IF(D60<=$G$24,"Grace period","contract maturity")) -> contract maturity | D60: =IFERROR(IF(D59+1>$K$24,"",D59+1),"") -> 33 | E60: =+IF(AND(B60>1,E59=0,B60),B60,L59) -> 8293.4451 | F60: =IF(C60=$E$24,0,IF(D60>$K$24,"",IF(D60<=$K$24,$G$20/$K$20,0))) -> 0 | G60: =IF(C60="grace period",0,IF(D60>$K$24,"",IF(E60=0,$G$15*$K$21,E60*$K$21))) -> 147.93538 | H60: =IF(D60<=$G$24,0,IF(D60>$K$24,"",K60-J60-G60-F60-I60)) -> 2018.7346 | I60: =IF(D60<=$G$24,0,IF(D60>$K$24,"",IF($G$11=$Y$10,IF(D60=$K$24,(($G$16-($G$17*$K$18))/$K$20)+($G$17*$K$18),(($G$16-($G$17*$K$18))/$K$20)),0))) -> 0 | J60: =IF(D60<=$G$24,0,IF(D60>$K$24,"",$G$21/$K$20)) -> 0 | K60: =IF(B60=0,F60+G60,IF(D60<=$G$24,0,IF(D60>$K$24,"",IF($G$11=$Y$10,IF(D60=$K$24,$G$17+$K$15+($G$17*$K$18),IF(D60<$K$24,$K$15,0)),IF(D60=$K$24,$G$17+$K$15,IF(D60<$K$24,$K$15,0)))))) -> 2166.67 | L60: =IF(D60>$K$24,"",E60-H60) -> 6274.7105 | M60: =$K$7 -> رقم العقد
... B87: =IF(D87<=$G$24,0,IF(D87>$K$24,"",IF($G$11=$Y$8,$G$15+$G$16,$G$15))) | C87: =+IF(D87="","",IF(D87<=$G$24,"Grace period","contract maturity")) | D87: =IFERROR(IF(D86+1>$K$24,"",D86+1),"") | E87: =+IF(AND(B87>1,E86=0,B87),B87,L86) | F87: =IF(C87=$E$24,0,IF(D87>$K$24,"",IF(D87<=$K$24,$G$20/$K$20,0))) | G87: =IF(C87="grace period",0,IF(D87>$K$24,"",IF(E87=0,$G$15*$K$21,E87*$K$21))) | H87: =IF(D87<=$G$24,0,IF(D87>$K$24,"",K87-J87-G87-F87-I87)) | I87: =IF(D87<=$G$24,0,IF(D87>$K$24,"",IF($G$11=$Y$10,IF(D87=$K$24,(($G$16-($G$17*$K$18))/$K$20)+($G$17*$K$18),(($G$16-($G$17*$K$18))/$K$20)),0))) | J87: =IF(D87<=$G$24,0,IF(D87>$K$24,"",$G$21/$K$20)) | K87: =IF(B87=0,F87+G87,IF(D87<=$G$24,0,IF(D87>$K$24,"",IF($G$11=$Y$10,IF(D87=$K$24,$G$17+$K$15+($G$17*$K$18),IF(D87<$K$24,$K$15,0)),IF(D87=$K$24,$G$17+$K$15,IF(D87<$K$24,$K$15,0)))))) | L87: =IF(D87>$K$24,"",E87-H87) | M87: =$K$7 -> رقم العقد
D88: Total | F88: =SUM(F28:F87) -> 0 | G88: =SUM(G28:G87) -> 14999.969 | H88: =SUM(H28:H87) -> 50000.131 | I88: =SUM(I28:I87) -> 0 | J88: =SUM(J28:J87) -> 0 | K88: =SUM(K28:K87) -> 65000.1 | X88: 1619.15
F89: =IF(D89>$K$24,"",IF(D89<=$K$24,$G$20/$K$24,0)) -> 0 | G89: =IF(C89="grace period",0,IF(D89>$K$24,"",IF(E89=0,$G$15*$K$21,E89*$K$21))) -> 891.88135 | H89: =IF(D89<=$G$24,0,IF(D89>$K$24,"",K89-J89-G89-F89-I89)) -> 0 | I89: =I88-G16 -> 0 | J89: =J88-G21 -> 0 | K89: =$AA$17 -> 0
B90: (ملحق لرقم العقد المذكور اعلاه ليصحح معدل النسبة السنوى APR المذكور بصفحة ملخص العقد - جدول الدفعات)
J91: اسم العميل
J92: التاريخ
J93: التوقيع
C100: updated form date 1/07/2020
C101: If there is any issue please contact :-
C102: Mohamad dawod
C103: mohamad.dawod@tamweel-aloula.com
C104: 3766

Sheet fekher
A1: Twark product pending isuees
A2: funcution | B2: finance department comment | C2: Status | D2: Updated Status 16/01/2025
A3: cancelation sheet | B3: please refer to excel sheet(twrek working sheet) named as financing department pending isuees | C3: Confirmed by IT team | D3: Closed
A4: Write off +bulk write off (specific criteria) | B4: please refer to excel sheet(twrek working sheet) named as financing department pending isuees | C4: Confirmed by IT team | D4: Closed
A5: Please confirm which contract will be used, 3 or 4 (SAMA one or TA one)? | B5: Murthy please review with the responsible department | C5: IT action | D5: Closed, SAMA contract will be used for contract 3
A6: Grace period | B6: please refer to excel sheet(twrek working sheet) named as Grace period calculation | C6: will discuss with SA | D6: Closed, we have sent the email and TA has accepted Tranasct Grace Schedule
A7: RESTRUCTURE (rescheduling) | B7: please refer to excel sheet(twrek working sheet) named as financing department pending isuees | C7: will discuss with SA | D7: LM side is closed, but LOS is still open.
A8: Reports (I will send ) | B8: Murthy have to discuss with system arbia | C8: will discuss with SA | D8: Nazim to check with Murthy, Nazim to share the sample reports extracts with Murthy
A9: service module | B9: discussion with abdulkareem.almidani@tamweel-aloula.com | C9: IT action | D9: All functionalities are available in LMS, Integration discussion is required
A10: Top Up (internal purshase dept) | B10: discuss internally then SA team | C10: will discuss with SA | D10: Same as point 12, Topup
A11: external purshase dept | B11: discuss internally then SA team | D11: Same as point12
A12: sub product for twrek (External Purchasing Debts&Internal Purchasing Debts) | B12: please refer to excel sheet(twrek working sheet) named as financing department pending isuees | D12: TA needs to have subproduct for Top-up e.g. Tawarruq (Top-up), in which the old Loan will be closed and new loan will be opened (as we are doing in restructure (top-up). For the sub product the GL should be separated therefore a new product will be created with different name and category. Buy-out for a new financing, if customer has requested to settle its existing other bank loan then funds will be sent to that bank as per defined %. this will also required new product as new category. For both cases, we need to involve LOS team plus some new fields will be added in list of fields file.BSDD will be updated according. Moreover, please also mention product name in product setup sheet with category.
A13: Partial Settlement | B13: discuss internally then SA team | C13: Confirmed by IT team | D13: Closed
A14: manuall process for twrek | B14: please refer to excel sheet(twrek working sheet) named as financing department pending isuees | C14: will discuss with SA | D14: Closed
A15: APIS report | B15: report with all APIS fees this report have attached items Date-customer name-ID NO -fees amount | C15: Confirmed by IT team | D15: Nazim and Murthy
A16: APIS GL impact for each customer | B16: Th GL will be (APIS name) expense as DR ,APIS Accrued expenses as CR ,Description in GL will be customer ID NO. | C16: Confirmed by IT team | D16: Nazim and Murthy
A17: Repayment schdual ,IRR calculation,profit calculation and APR calculation | B17: please refer to excel sheet(twrek working sheet) named Day2 - Simulated Schedule (2) | C17: reviewed by dawwod | D17: Closed
A18: API costing | D18: TA have to share the GL entry frequency for each third-party API. Nazim to Manage this
A19: Cost centre and profit centre configuration | D19: Session required with SA and TA finance team
A20: Provisioning | D20: During the write-off session, TA has provided provisioning entry. Which has to be discussed with the SA Finance team. TA to confirm that they want this entry stage or not. TA session required with the SA finance team is required to discuss that provisioning is covered through IFRS9 or provisioning

Sheet Sheet4
A1: LO System Functions
A2: Desbursment Ijarah | G2: Trail Balance
A3: Desbursment Tawareuq
A4: Desbursment Murabaha | E4: S No | F4: Column1 | G4: Account | H4: Account Type | I4: Debit | J4: Credit
A5: Cancle contract | E5: 1 | F5: Desbursment Ijarah | G5: Collection of Down Payment | H5: 1104000001- Account Recievable | J5: CR
A6: Decline contract | E6: 2 | F6: Desbursment Ijarah | G6: Collection of Down Payment | H6: I/C bank GL | I6: DR | M6: 1
A7: LO System Functions | E7: 3 | F7: Desbursment Ijarah
A8: Payment Captuering | E8: 4 | F8: Desbursment Ijarah | G8: Recording of New Facility | H8: 1106310001 - Inventory | J8: 1
A9: Reschdualing | E9: 5 | F9: Desbursment Ijarah | G9: Recording of New Facility | H9: 2104310001 - Deferred Rev - Interest | J9: 1
A10: Loan Transfer | E10: 6 | F10: Desbursment Ijarah | G10: Recording of New Facility | H10: 2104310002 - Deferred insurance revenues | J10: 1
A11: Waiver | E11: 7 | F11: Desbursment Ijarah | G11: Recording of New Facility | H11: 2112100004 - VAT Non Due | J11: 1
A12: Write off | E12: 8 | F12: Desbursment Ijarah | G12: Recording of New Facility | H12: 2112000001 - Output VAT 15% for domestic | J12: 1
A13: Refund | E13: 9 | F13: Desbursment Ijarah | G13: Recording of New Facility | H13: 1104000001 - Account Recievable | I13: 5
A14: Payment Reversal | E14: 10 | F14: Desbursment Ijarah
A15: Total Loss | E15: 11 | F15: Desbursment Ijarah | G15: Purchase of New Asset | H15: 1106310001 - Inventory | I15: 1
A16: Services | E16: 12 | F16: Desbursment Ijarah | G16: Purchase of New Asset | H16: 1112000001 - Input VAT 15% Domestic | I16: 1
A17: Early Termination | E17: 13 | F17: Desbursment Ijarah | G17: Purchase of New Asset | H17: 2101000001 - A/c Payable | J17: 2
A18: Charges | E18: 14 | F18: Desbursment Ijarah
E19: 15 | F19: Desbursment Ijarah | G19: Recording of Admin Fees | H19: 1104000001 - Account Recievable | I19: DR
E20: 16 | F20: Desbursment Ijarah | G20: Recording of Admin Fees | H20: 2104310003 - Deferred Revenue-Admin Fees | J20: CR
E21: 17
E22: 18 | F22: Desbursment Tawareuq | G22: Recording of New Facility | H22: 1106310001 - Inventory | J22: 1
E23: 19 | F23: Desbursment Tawareuq | G23: Recording of New Facility | H23: 2104310001 - Deferred Rev - Interest | J23: 1
E24: 20 | F24: Desbursment Tawareuq | G24: Recording of New Facility | H24: 1104000001 - Account Recievable | I24: 2
E25: 21 | F25: Desbursment Tawareuq
E26: 22 | F26: Desbursment Tawareuq | G26: Recording of Admin Fees | H26: 2112000001 - Output VAT 15% for domestic | J26: 1
E27: 23 | F27: Desbursment Tawareuq | G27: Recording of Admin Fees | H27: 2104310003 - Deferred Revenue-Admin Fees | J27: 1
E28: 24 | F28: Desbursment Tawareuq | G28: Recording of Admin Fees | H28: 1104000001 - Account Recievable | I28: 2
E29: 25 | F29: Desbursment Tawareuq
E30: 26 | F30: Desbursment Tawareuq | G30: Tawaruq Event | H30: 1104000001 - Account Recievable | J30: 1
E31: 27 | F31: Desbursment Tawareuq | G31: Tawaruq Event | H31: 2101000001 - A/c Payable | J31: 1
E32: 28 | F32: Desbursment Tawareuq | G32: Tawaruq Event | H32: 2101000001 - A/c Payable | J32: 1
E33: 29 | F33: Desbursment Tawareuq | G33: Tawaruq Event | H33: 1104000001 - Account Recievable | I33: 1
E34: 30 | F34: Desbursment Tawareuq | G34: Tawaruq Event | H34: 1104000004 - Ashton vendor | I34: 1
E35: 31 | F35: Desbursment Tawareuq | G35: Tawaruq Event | H35: 1106310001 - Inventory | I35: 1
E36: 32 | F36: Desbursment Tawareuq
E37: 33 | F37: Desbursment Tawareuq | G37: Customer services transaction | H37: 1105310003 - Clearing Account Kastle | J37: 1
E38: 34 | F38: Desbursment Tawareuq | G38: Customer services transaction | H38: 1104000001 - Account Recievable | I38: 1
E39: 35 | F39: Desbursment Tawareuq
E40: 36 | F40: Desbursment Tawareuq | G40: Payment for excess balance | H40: 1104000001 - Account Recievable | J40: 1
E41: 37 | F41: Desbursment Tawareuq | G41: Payment for excess balance | H41: 1105310002 - Clearing Acount | I41: 1
E42: 38 | F42: Desbursment Tawareuq
E43: 39 | F43: Desbursment Tawareuq | G43: Refund | H43: bank -O/C | J43: financed amount -admin fees (CR)
E44: 40 | F44: Desbursment Tawareuq | G44: Refund | H44: 1104000001 - Account Recievable | I44: financed amount -admin fees (DR)
E45: 41 | F45: Desbursment Tawareuq
E46: 42 | F46: Desbursment Tawareuq | G46: Recording of fajr | H46: 1105310002 - Clearing Acount | J46: 1
E47: 43 | F47: Desbursment Tawareuq | G47: Recording of fajr | H47: 1104000004 - Ashton vendor | J47: 1
E48: 44 | F48: Desbursment Tawareuq | G48: Recording of fajr | H48: 600000293-fajr investment | I48: 2
E49: 45 | F49: Desbursment Tawareuq
E51: 46 | F51: Desbursment Murabaha | G51: Purchase of New Asset | H51: 1106310001 - Inventory | I51: DR
E52: 47 | F52: Desbursment Murabaha | G52: Purchase of New Asset | H52: 2101000001 - A/c Payable | J52: CR
E53: 48 | F53: Desbursment Murabaha
E54: 49 | F54: Desbursment Murabaha | G54: Recording of New Facility | H54: 1104000001 - Account Recievable | I54: 2
E55: 50 | F55: Desbursment Murabaha | G55: Recording of New Facility | H55: 1106310001 - Inventory | J55: 2
E56: 51 | F56: Desbursment Murabaha | G56: Recording of New Facility | H56: 2104310001 - Deferred Revenue Profit Auto (Kifah) | J56: 2
E57: 52 | F57: Desbursment Murabaha
E58: 53 | F58: Desbursment Murabaha | G58: Customer services transaction | H58: 1105310003 - Clearing Account Kastle | J58: 2
E59: 54 | F59: Desbursment Murabaha | G59: Customer services transaction | H59: 1104000001 - Account Recievable | I59: 2
E60: 55 | F60: Desbursment Murabaha
E61: 56 | F61: Desbursment Murabaha | G61: Installment Payment | H61: 1105310002 - Clearing account | I61: 2
E62: 57 | F62: Desbursment Murabaha | G62: Installment Payment | H62: 1104000001 - Account Recievable | J62: 2
E63: 58 | F63: Desbursment Murabaha
E64: 59 | F64: Desbursment Murabaha | G64: Refund | H64: bank -O/C | J64: financed amount -admin fees (CR)
E65: 60 | F65: Desbursment Murabaha | G65: Refund | H65: 1104000001 - Account Recievable | I65: financed amount -admin fees (DR)
E66: 61 | F66: Desbursment Murabaha
E67: 62 | F67: Desbursment Murabaha | G67: Recording of fajr | H67: 1105310002 - Clearing Acount | J67: CR
E68: 63 | F68: Desbursment Murabaha | G68: Recording of fajr | H68: 600000293-fajr investment | I68: DR

Sheet Day2 - Simulated Schedule (2)
A1: System Date | B1: 45320 | D1: ballon payment | E1: 0
A2: Offer Issue Date | B2: =+B1 -> 45320 | D2: EMI without ins | E2: =+(E3+F7)/E6 -> 2213.0897
A3: Grace Period | B3: 15 Days | D3: FA | E3: 100000 | G3: this is calculated on 360 day basis, likewise it go same for Grace period which is on 365 day basis
A4: Offer Expiry Date | B4: =+B2+14 -> 45334 | D4: Effcetive rate | E4: =+E5*12 -> 0.11774964
A5: Payment Schedule | D5: IRR | E5: =+RATE(E6,E2,-E3,E1) -> 0.0098124697 | L5: Generated Date: 12-Aug-2024 18:52:41
D6: Tenor | E6: 60
C7: =((F7/E3)/60)*12 -> 0.06557076 | D7: flate rate | E7: 0.06557076 | F7: =+E7*E3*E6/12 -> 32785.38
D8: Annual profit amount | E8: =+E9/5 -> 6557.0746
D9: total profit amount | E9: =SUM(F15:F76) -> 32785.373
D10: APR | E10: =+XIRR(J16:J76,A16:A76) -> 0.13247654
A15: Date | B15: Defer Date | C15: Total Due | D15: Total Cap | E15: Principal BY tamweel | F15: Principal Profit by tamweel | G15: REC Profit | H15: Charge | I15: Tax | J15: Total Pymt by tamweel | K15: Outstanding | L15: O/S Principal + Profit | M15: Total Pymt by SA | N15: Principal according to SA calculation | O15: Principal Profit according to SA calculation | P15: differnce in Princple | Q15: diffrence in profit
A16: 45334 | C16: 1150 | D16: 0 | E16: 100000 | H16: 1000 | I16: 150 | J16: =-E16+C16 -> -98850 | K16: -100000 | M16: ='Day2 - Simulated Schedule'!C9 -> 2213.09
A17: 45350 | C17: 2213.09 | D17: 0 | E17: =+C17-F17 -> 1231.843 | F17: =+-K16*$E$5 -> 981.24697 | H17: 0 | J17: =+C17 -> 2213.09 | K17: =+K16+E17 -> -98768.157 | M17: ='Day2 - Simulated Schedule'!C10 -> 2213.09 | N17: =+'Day2 - Simulated Schedule'!E9 -> 1719.94 | O17: =+'Day2 - Simulated Schedule'!F9 -> 493.15 | P17: =+N17-E17 -> 488.09697 | Q17: =+O17-F17 -> -488.09697
A18: 45379 | C18: 2213.09 | D18: 0 | E18: =+C18-F18 -> 1243.9305 | F18: =+-K17*$E$5 -> 969.15955 | H18: 0 | J18: =+C18 -> 2213.09 | K18: =+K17+E18 -> -97524.227 | M18: ='Day2 - Simulated Schedule'!C11 -> 2213.09 | N18: =+'Day2 - Simulated Schedule'!E10 -> 1276.06 | O18: =+'Day2 - Simulated Schedule'!F10 -> 937.03 | P18: =+N18-E18 -> 32.129549 | Q18: =+O18-F18 -> -32.129549
A19: 45410 | C19: 2213.09 | D19: 0 | E19: =+C19-F19 -> 1256.1365 | F19: =+-K18*$E$5 -> 956.95352 | H19: 0 | J19: =+C19 -> 2213.09 | K19: =+K18+E19 -> -96268.09 | M19: ='Day2 - Simulated Schedule'!C12 -> 2213.09 | N19: =+'Day2 - Simulated Schedule'!E11 -> 1224.45 | O19: =+'Day2 - Simulated Schedule'!F11 -> 988.64 | P19: =+N19-E19 -> -31.686481 | Q19: =+O19-F19 -> 31.686481
A20: 45440 | C20: 2213.09 | D20: 0 | E20: =+C20-F20 -> 1268.4623 | F20: =+-K19*$E$5 -> 944.62772 | H20: 0 | J20: =+C20 -> 2213.09 | K20: =+K19+E20 -> -94999.628 | M20: ='Day2 - Simulated Schedule'!C13 -> 2213.09 | N20: =+'Day2 - Simulated Schedule'!E12 -> 1268.42 | O20: =+'Day2 - Simulated Schedule'!F12 -> 944.67 | P20: =+N20-E20 -> -0.042282337 | Q20: =+O20-F20 -> 0.042282337
A21: 45471 | C21: 2213.09 | D21: 0 | E21: =+C21-F21 -> 1280.909 | F21: =+-K20*$E$5 -> 932.18097 | H21: 0 | J21: =+C21 -> 2213.09 | K21: =+K20+E21 -> -93718.719 | M21: ='Day2 - Simulated Schedule'!C14 -> 2213.09 | N21: =+'Day2 - Simulated Schedule'!E13 -> 1249.85 | O21: =+'Day2 - Simulated Schedule'!F13 -> 963.24 | P21: =+N21-E21 -> -31.05903 | Q21: =+O21-F21 -> 31.05903
A22: 45501 | C22: 2213.09 | D22: 0 | E22: =+C22-F22 -> 1293.4779 | F22: =+-K21*$E$5 -> 919.61209 | H22: 0 | J22: =+C22 -> 2213.09 | K22: =+K21+E22 -> -92425.241 | M22: ='Day2 - Simulated Schedule'!C15 -> 2213.09 | N22: =+'Day2 - Simulated Schedule'!E14 -> 1293.25 | O22: =+'Day2 - Simulated Schedule'!F14 -> 919.84 | P22: =+N22-E22 -> -0.22791112 | Q22: =+O22-F22 -> 0.22791112
A23: 45532 | C23: 2213.09 | D23: 0 | E23: =+C23-F23 -> 1306.1701 | F23: =+-K22*$E$5 -> 906.91988 | H23: 0 | J23: =+C23 -> 2213.09 | K23: =+K22+E23 -> -91119.071 | M23: ='Day2 - Simulated Schedule'!C16 -> 2213.09 | N23: =+'Day2 - Simulated Schedule'!E15 -> 1275.77 | O23: =+'Day2 - Simulated Schedule'!F15 -> 937.32 | P23: =+N23-E23 -> -30.400124 | Q23: =+O23-F23 -> 30.400124
A24: 45563 | C24: 2213.09 | D24: 0 | E24: =+C24-F24 -> 1318.9869 | F24: =+-K23*$E$5 -> 894.10312 | H24: 0 | J24: =+C24 -> 2213.09 | K24: =+K23+E24 -> -89800.084 | M24: ='Day2 - Simulated Schedule'!C17 -> 2213.09 | N24: =+'Day2 - Simulated Schedule'!E16 -> 1288.77 | O24: =+'Day2 - Simulated Schedule'!F16 -> 924.32 | P24: =+N24-E24 -> -30.216879 | Q24: =+O24-F24 -> 30.216879
A25: 45593 | C25: 2213.09 | D25: 0 | E25: =+C25-F25 -> 1331.9294 | F25: =+-K24*$E$5 -> 881.1606 | H25: 0 | J25: =+C25 -> 2213.09 | K25: =+K24+E25 -> -88468.154 | M25: ='Day2 - Simulated Schedule'!C18 -> 2213.09 | N25: =+'Day2 - Simulated Schedule'!E17 -> 1331.3 | O25: =+'Day2 - Simulated Schedule'!F17 -> 881.79 | P25: =+N25-E25 -> -0.62939752 | Q25: =+O25-F25 -> 0.62939752
A26: 45624 | C26: 2213.09 | D26: 0 | E26: =+C26-F26 -> 1344.9989 | F26: =+-K25*$E$5 -> 868.09109 | H26: 0 | J26: =+C26 -> 2213.09 | K26: =+K25+E26 -> -87123.156 | M26: ='Day2 - Simulated Schedule'!C19 -> 2213.09 | N26: =+'Day2 - Simulated Schedule'!E18 -> 1315.48 | O26: =+'Day2 - Simulated Schedule'!F18 -> 897.61 | P26: =+N26-E26 -> -29.518914 | Q26: =+O26-F26 -> 29.518914
A27: 45654 | C27: 2213.09 | D27: 0 | E27: =+C27-F27 -> 1358.1967 | F27: =+-K26*$E$5 -> 854.89332 | H27: 0 | J27: =+C27 -> 2213.09 | K27: =+K26+E27 -> -85764.959 | M27: ='Day2 - Simulated Schedule'!C20 -> 2213.09 | N27: =+'Day2 - Simulated Schedule'!E19 -> 1357.41 | O27: =+'Day2 - Simulated Schedule'!F19 -> 855.68 | P27: =+N27-E27 -> -0.7866755 | Q27: =+O27-F27 -> 0.7866755
A28: 45685 | C28: 2213.09 | D28: 0 | E28: =+C28-F28 -> 1371.5239 | F28: =+-K27*$E$5 -> 841.56606 | H28: 0 | J28: =+C28 -> 2213.09 | K28: =+K27+E28 -> -84393.435 | M28: ='Day2 - Simulated Schedule'!C21 -> 2213.09 | N28: =+'Day2 - Simulated Schedule'!E20 -> 1342.72 | O28: =+'Day2 - Simulated Schedule'!F20 -> 870.37 | P28: =+N28-E28 -> -28.803939 | Q28: =+O28-F28 -> 28.803939
... A76: 47146 | C76: 2213.07 | D76: 0 | E76: =+C76-F76 -> 2191.5654 | F76: =+-K75*$E$5 -> 21.5046 | H76: 0 | J76: =+C76 -> 2213.07 | K76: =+K75+E76 -> 0.0070597325 | M76: ='Day2 - Simulated Schedule'!C69 -> 0 | N76: =+'Day2 - Simulated Schedule'!E68 -> 2190.72 | O76: =+'Day2 - Simulated Schedule'!F68 -> 22.35 | P76: =+N76-E76 -> -0.84540016 | Q76: =+O76-F76 -> 0.84540016
F77: =SUM(F17:F76) -> 32785.373 | O77: =SUM(O17:O76) -> 32785.38

Sheet financing department pending is
